Workbook

Sheet Inputs
A1: Parameter | B1: Value | C1: Notes
A2: ISA_Total (current, overwrite to use manual total) | B2: 65436.24 | C2: If blank, Holdings sum will be used
A3: Apr_Contribution (£) | B3: 20000 | C3: Planned April VWRA top-up
A4: Add_DFNS_Today (£) | B4: 400 | C4: Amount to add to DFNS today
A5: DFNS_reported_value (£) | B5: 747 | C5: Current DFNS market value from statement
A6: DFNS_reported_return_pct (decimal) | B6: 1.04 | C6: Your reported DFNS return (e.g., 104% -> 1.04)
A7: Trailing_Stop_pct (decimal) | B7: 0.25 | C7: 25% trailing stop
A8: DFNS_Target_pct_of_ISA (decimal) | B8: 0.04 | C8: Target DFNS weight of ISA
A9: M&G_Target_pct_of_ISA (decimal) | B9: 0.05 | C9: Target M&G weight of ISA after trimming
A10: ShortTerm_Capital (£) | B10: 3000 | C10: Short-term pot size

Sheet Holdings
A1: Ticker | B1: Name | C1: MarketValue | D1: Price | E1: Shares
A2: CASH_ISA | B2: ISA Cash | C2: 424.57
A3: RLSTMKT | B3: Royal London Money Market | C3: 48503.71
A4: MGDIV | B4: M&G Global Dividend | C4: 7927.75
A5: HSPX | B5: HSBC S&P 500 ETF | C5: 6037.57
A6: IWQU | B6: iShares MSCI World Quality | C6: 663.46
A7: BCHS | B7: Invesco Blockchain (BCHS) | C7: 619.8
A8: DFNS | B8: VanEck Defence ETF | C8: 747.28
A9: IGLN | B9: iShares Physical Gold ETC | C9: 512.1
A10: VWRA | B10: VWRA placeholder (current holding) | C10: 0

Sheet Calculations
A1: Metric | B1: Formula | C1: Value (calculated)
A2: ISA_Total_calc | B2: =IF(Inputs!B1="",SUM(Holdings!C2:C10),Inputs!B1)
A3: M&G_target_value | B3: =Inputs!B9 * B2
A4: M&G_sell_amount | B4: =MAX(0, VLOOKUP("MGDIV",Holdings!A:C,3,FALSE) - B3)
A5: Cash_available_to_buy_VWRA | B5: =B4 + VLOOKUP("CASH_ISA",Holdings!A:C,3,FALSE)
A6: VWRA_buy_amount_today | B6: =B5
A7: DFNS_original_cost | B7: =VLOOKUP("DFNS",Holdings!A:C,3,FALSE) / (1 + Inputs!B6)
A8: DFNS_post_add_value | B8: =VLOOKUP("DFNS",Holdings!A:C,3,FALSE) + Inputs!B4
A9: DFNS_aggregate_cost_basis | B9: =B7 + Inputs!B4
A10: DFNS_unrealised_gain_after_add | B10: =B8 - B9
A11: Sell_amount_to_recover_original_cost | B11: =B7
A12: Sell_percent_of_post_position | B12: =IF(B8>0, B11 / B8, 0)
A13: DFNS_trailing_stop_price | B13: =IFERROR(VLOOKUP("DFNS",Holdings!A:E,4,FALSE) * (1 - Inputs!B7), "Price missing")
A14: DFNS_target_value_for_pct | B14: =Inputs!B8 * B2
A15: DFNS_additional_needed_for_target | B15: =MAX(0, B14 - B8)
A16: Funds_remaining_after_DFNS_funding_for_VWRA | B16: =MAX(0, B6 - B15)

Sheet Orders_Template
A1: Account | B1: Action | C1: Ticker | D1: Amount_GBP (formula) | E1: Qty (formula) | F1: LimitPrice (use Holdings price) | G1: Notes
A2: ISA | B2: SELL | C2: MGDIV | D2: =Calculations!B4 | E2: =IFERROR(Calculations!B4 / VLOOKUP("MGDIV",Holdings!A:D,4,FALSE),"Price missing") | F2: =VLOOKUP("MGDIV",Holdings!A:D,4,FALSE) | G2: Trim to target %
A3: ISA | B3: BUY | C3: VWRA | D3: =Calculations!B6 | E3: =IFERROR(Calculations!B6 / VLOOKUP("VWRA",Holdings!A:D,4,FALSE),"Price missing") | F3: =VLOOKUP("VWRA",Holdings!A:D,4,FALSE) | G3: Buy VWRA with proceeds + cash
A4: ISA | B4: BUY | C4: DFNS | D4: =Calculations!B15 | E4: =IFERROR(Calculations!B15 / VLOOKUP("DFNS",Holdings!A:D,4,FALSE),"Price missing") | F4: =VLOOKUP("DFNS",Holdings!A:D,4,FALSE) | G4: Top DFNS to target pct

Sheet ShortTerm_Planner
A1: Ticker | B1: Name | C1: Target% | D1: ShortTermCapital (link) | E1: £ Alloc (formula) | F1: Price (link to Holdings) | G1: Qty formula
A2: 3QQQ.L | B2: 3x Nasdaq Levered | C2: 0.4 | D2: =Inputs!B10 | E2: =C2 * D2 | F2: =VLOOKUP("3QQQ.L",Holdings!A:D,4,FALSE) | G2: =IFERROR(E2 / F2, "Price missing")
A3: SMGB.L | B3: VanEck Semiconductors | C3: 0.3 | D3: =Inputs!B10 | E3: =C3 * D3 | F3: =VLOOKUP("SMGB.L",Holdings!A:D,4,FALSE) | G3: =IFERROR(E3 / F3, "Price missing")
A4: AIAI.L | B4: L&G AI ETF | C4: 0.2 | D4: =Inputs!B10 | E4: =C4 * D4 | F4: =VLOOKUP("AIAI.L",Holdings!A:D,4,FALSE) | G4: =IFERROR(E4 / F4, "Price missing")
A5: CASH_ST | B5: Cash buffer | C5: 0.1 | D5: =Inputs!B10 | E5: =C5 * D5

Sheet Dashboard
A1: Report generated | B1: 2026-01-07 15:37
A3: Key metric | B3: Formula/Value
A4: ISA total (calc) | B4: =Calculations!B2
A5: M&G sell amount (to trim to target) | B5: =Calculations!B4
A6: VWRA buy amount today (from proceeds + cash) | B6: =Calculations!B6
A7: DFNS original cost | B7: =Calculations!B7
A8: DFNS post-add value | B8: =Calculations!B8
A9: DFNS aggregate cost basis | B9: =Calculations!B9
A10: Sell percent of post DFNS position to recover original cost | B10: =Calculations!B12
A11: DFNS trailing stop price (based on Holdings Price) | B11: =Calculations!B13
A12: DFNS additional needed for target pct | B12: =Calculations!B15
A13: Funds remaining after DFNS funding for VWRA | B13: =Calculations!B16
