Workbook
Name Param_LTV_Tol: Parameters!$B$6
Name Param_MaxDTI: Parameters!$B$10
Name Param_MaxOrigLTV: Parameters!$B$4
Name Param_MinDSCR: Parameters!$B$11
Name Param_Rate_Tol: Parameters!$B$9

Sheet Parameters
A1: VALIDATION PARAMETERS - CONFIGURE THRESHOLDS HERE
A4: Parameter | B4: Value | C4: Notes
A5: Max_Orig_LTV_Prime | B5: 80 | C5: Above requires MIG
A6: Max_Orig_LTV_Overall | B6: 95 | C6: Hard limit
A7: Min_Orig_LTV | B7: 10 | C7: Very low - check second lien
A8: LTV_Calc_Tolerance | B8: 0.5 | C8: Rounding tolerance %
A9: Min_Rate | B9: 0.5 | C9: Below is unusual
A10: Max_Rate_Overall | B10: 15 | C10: Sub-prime maximum
A11: Rate_Calc_Tolerance | B11: 0.25 | C11: Index+Margin vs Current Rate
A12: Max_DTI | B12: 60 | C12: Overall DTI limit %
A13: Min_BTL_DSCR | B13: 100 | C13: Below is negative cash flow
A14: Min_Term_Months | B14: 60 | C14: 5 years minimum
A15: Max_Term_Months | B15: 480 | C15: 40 years maximum

Sheet Loan_Tape_Input
A1: AR1_Cutoff | B1: AR3_LoanID | C1: AR19_NumDebt | D1: AR26_Income1 | E1: AR27_IncomeVerif | F1: AR36_Bankrupt | G1: AR46_BureauScore | H1: AR55_Orig | I1: AR56_Maturity | J1: AR61_Term | K1: AR66_OrigBal | L1: AR67_CurrBal | M1: AR69_RepayMethod | N1: AR70_PayFreq | O1: AR71_PayDue | P1: AR73_DTI | Q1: AR84_Lien | R1: AR107_RateType | S1: AR108_RateIndex | T1: AR109_CurrRate | U1: AR110_Margin | V1: AR122_Restruc | W1: AR130_Occupancy | X1: AR135_OrigLTV | Y1: AR136_OrigVal | Z1: AR141_CurrLTV | AA1: AR143_CurrVal | AB1: AR154_Rental | AC1: AR155_NumBTL | AD1: AR156_DSCR | AE1: AR166_Status | AF1: AR169_ArrBal | AG1: AR170_MonthsArr | AH1: AR177_Default | AI1: AR189_Employ2 | AJ1: AR207_BureauScore2
A2: 2024-11-30 | B2: LOAN001 | C2: 1 | D2: 50000 | E2: Full | F2: No | G2: 750 | H2: 2020-01-15 | I2: 2045-01-15 | J2: 300 | K2: 200000 | L2: 185000 | M2: Repayment | N2: Monthly | O2: 1200 | P2: 35 | Q2: First | R2: Fixed | S2: Fixed | T2: 3.5 | U2: 0 | V2: No | W2: Owner Occupied | X2: 75 | Y2: 266667 | Z2: 69 | AA2: 268000 | AB2: 0 | AC2: 0 | AD2: 0 | AE2: Current | AF2: 0 | AG2: 0 | AH2: No | AJ2: 0
A3: 2024-11-30 | B3: LOAN002 | C3: 2 | D3: 60000 | E3: Basic | F3: No | G3: 680 | H3: 2019-06-20 | I3: 2044-06-20 | J3: 300 | K3: 300000 | L3: 280000 | M3: Interest Only | N3: Monthly | O3: 850 | P3: 40 | Q3: First | R3: Variable | S3: SONIA | T3: 4.25 | U3: 1.5 | V3: No | W3: Buy-to-Let | X3: 80 | Y3: 375000 | Z3: 74.7 | AA3: 375000 | AB3: 18000 | AC3: 2 | AD3: 127 | AE3: Current | AF3: 0 | AG3: 0 | AH3: No | AI3: Employed | AJ3: 720
A4: 2024-11-30 | B4: LOAN003 | C4: 1 | D4: 45000 | E4: Full | F4: Yes | G4: 550 | H4: 2021-03-10 | I4: 2046-03-10 | J4: 300 | K4: 150000 | L4: 145000 | M4: Bullet | N4: Monthly | O4: 0 | P4: 30 | Q4: First | R4: Tracker | S4: BoE Base | T4: 5.5 | U4: 2 | V4: No | W4: Owner Occupied | X4: 70 | Y4: 214286 | Z4: 67.8 | AA4: 214000 | AB4: 0 | AC4: 0 | AD4: 0 | AE4: Arrears | AF4: 2400 | AG4: 2 | AH4: No | AJ4: 0

Sheet Validation_Results
A1: COMPREHENSIVE LOAN-LEVEL VALIDATION RESULTS
A2: Row | B2: LoanID | C2: Rule | D2: Description | E2: Severity | F2: Status | G2: Field1 | H2: Val1 | I2: Field2 | J2: Val2 | K2: Details
A3: 2 | B3: =Loan_Tape_Input!B2 -> 0 | C3: R1.1 | D3: Bullet must be Semi-Annual/Annual | E3: CRITICAL | F3: =IF(Loan_Tape_Input!M2="Bullet",IF(OR(Loan_Tape_Input!N2="Semi-Annual",Loan_Tape_Input!N2="Annual"),"PASS","FAIL"),"N/A") -> 0 | G3: AR69 | H3: =Loan_Tape_Input!M2 -> 0 | I3: AR70 | J3: =Loan_Tape_Input!N2 -> 0 | K3: =IF(F3="FAIL",H3&" with "&J3,"") -> 0
A4: 2 | B4: =Loan_Tape_Input!B2 -> 0 | C4: R2.1 | D4: BTL: Rental>0, NumBTL>=1, DSCR>=100 | E4: CRITICAL | F4: =IF(Loan_Tape_Input!W2="Buy-to-Let",IF(AND(Loan_Tape_Input!AB2>0,Loan_Tape_Input!AC2>=1,Loan_Tape_Input!AD2>=100),"PASS","FAIL"),"N/A") -> 0 | G4: AR130 | H4: =Loan_Tape_Input!W2 -> 0 | I4: BTL Fields | J4: =Loan_Tape_Input!AB2&"/"&Loan_Tape_Input!AC2&"/"&Loan_Tape_Input!AD2 -> 0 | K4: =IF(F4="FAIL","BTL missing required fields","") -> 0
A5: 2 | B5: =Loan_Tape_Input!B2 -> 0 | C5: R6.1 | D5: Orig LTV = (OrigBal/OrigVal)*100 | E5: CRITICAL | F5: =IF(ABS(Loan_Tape_Input!X2-(Loan_Tape_Input!K2/Loan_Tape_Input!Y2*100))<=Param_LTV_Tol,"PASS","FAIL") -> 0 | G5: AR135 | H5: =Loan_Tape_Input!X2 -> 0 | I5: Calculated | J5: =Loan_Tape_Input!K2/Loan_Tape_Input!Y2*100 -> 0 | K5: =IF(F5="FAIL","LTV: "&TEXT(H5,"0.0")&"% vs "&TEXT(J5,"0.0")&"%","") -> 0
A6: 2 | B6: =Loan_Tape_Input!B2 -> 0 | C6: R6.2 | D6: Curr LTV = (CurrBal/CurrVal)*100 | E6: CRITICAL | F6: =IF(ABS(Loan_Tape_Input!Z2-(Loan_Tape_Input!L2/Loan_Tape_Input!AA2*100))<=Param_LTV_Tol,"PASS","FAIL") -> 0 | G6: AR141 | H6: =Loan_Tape_Input!Z2 -> 0 | I6: Calculated | J6: =Loan_Tape_Input!L2/Loan_Tape_Input!AA2*100 -> 0 | K6: =IF(F6="FAIL","CLTV: "&TEXT(H6,"0.0")&"% vs "&TEXT(J6,"0.0")&"%","") -> 0
A7: 2 | B7: =Loan_Tape_Input!B2 -> 0 | C7: R5.1 | D7: MonthsArr=0 then ArrBal=0 | E7: CRITICAL | F7: =IF(Loan_Tape_Input!AG2=0,IF(Loan_Tape_Input!AF2=0,"PASS","FAIL"),"N/A") -> 0 | G7: AR170 | H7: =Loan_Tape_Input!AG2 -> 0 | I7: AR169 | J7: =Loan_Tape_Input!AF2 -> 0 | K7: =IF(F7="FAIL","Months=0 but Bal="&J7,"") -> 0
A8: 2 | B8: =Loan_Tape_Input!B2 -> 0 | C8: R9.1 | D8: Orig<=Cutoff<Maturity | E8: CRITICAL | F8: =IF(AND(Loan_Tape_Input!H2<=Loan_Tape_Input!A2,Loan_Tape_Input!A2<Loan_Tape_Input!I2),"PASS","FAIL") -> 0 | G8: AR55 | H8: =Loan_Tape_Input!H2 -> 0 | I8: AR56 | J8: =Loan_Tape_Input!I2 -> 0 | K8: =IF(F8="FAIL","Date sequence error","") -> 0
A9: 3 | B9: =Loan_Tape_Input!B3 -> 0 | C9: R1.1 | D9: Bullet must be Semi-Annual/Annual | E9: CRITICAL | F9: =IF(Loan_Tape_Input!M3="Bullet",IF(OR(Loan_Tape_Input!N3="Semi-Annual",Loan_Tape_Input!N3="Annual"),"PASS","FAIL"),"N/A") -> 0 | G9: AR69 | H9: =Loan_Tape_Input!M3 -> 0 | I9: AR70 | J9: =Loan_Tape_Input!N3 -> 0 | K9: =IF(F9="FAIL",H9&" with "&J9,"") -> 0
A10: 3 | B10: =Loan_Tape_Input!B3 -> 0 | C10: R2.1 | D10: BTL: Rental>0, NumBTL>=1, DSCR>=100 | E10: CRITICAL | F10: =IF(Loan_Tape_Input!W3="Buy-to-Let",IF(AND(Loan_Tape_Input!AB3>0,Loan_Tape_Input!AC3>=1,Loan_Tape_Input!AD3>=100),"PASS","FAIL"),"N/A") -> 0 | G10: AR130 | H10: =Loan_Tape_Input!W3 -> 0 | I10: BTL Fields | J10: =Loan_Tape_Input!AB3&"/"&Loan_Tape_Input!AC3&"/"&Loan_Tape_Input!AD3 -> 0 | K10: =IF(F10="FAIL","BTL missing required fields","") -> 0
A11: 3 | B11: =Loan_Tape_Input!B3 -> 0 | C11: R6.1 | D11: Orig LTV = (OrigBal/OrigVal)*100 | E11: CRITICAL | F11: =IF(ABS(Loan_Tape_Input!X3-(Loan_Tape_Input!K3/Loan_Tape_Input!Y3*100))<=Param_LTV_Tol,"PASS","FAIL") -> 0 | G11: AR135 | H11: =Loan_Tape_Input!X3 -> 0 | I11: Calculated | J11: =Loan_Tape_Input!K3/Loan_Tape_Input!Y3*100 -> 0 | K11: =IF(F11="FAIL","LTV: "&TEXT(H11,"0.0")&"% vs "&TEXT(J11,"0.0")&"%","") -> 0
A12: 3 | B12: =Loan_Tape_Input!B3 -> 0 | C12: R6.2 | D12: Curr LTV = (CurrBal/CurrVal)*100 | E12: CRITICAL | F12: =IF(ABS(Loan_Tape_Input!Z3-(Loan_Tape_Input!L3/Loan_Tape_Input!AA3*100))<=Param_LTV_Tol,"PASS","FAIL") -> 0 | G12: AR141 | H12: =Loan_Tape_Input!Z3 -> 0 | I12: Calculated | J12: =Loan_Tape_Input!L3/Loan_Tape_Input!AA3*100 -> 0 | K12: =IF(F12="FAIL","CLTV: "&TEXT(H12,"0.0")&"% vs "&TEXT(J12,"0.0")&"%","") -> 0
A13: 3 | B13: =Loan_Tape_Input!B3 -> 0 | C13: R5.1 | D13: MonthsArr=0 then ArrBal=0 | E13: CRITICAL | F13: =IF(Loan_Tape_Input!AG3=0,IF(Loan_Tape_Input!AF3=0,"PASS","FAIL"),"N/A") -> 0 | G13: AR170 | H13: =Loan_Tape_Input!AG3 -> 0 | I13: AR169 | J13: =Loan_Tape_Input!AF3 -> 0 | K13: =IF(F13="FAIL","Months=0 but Bal="&J13,"") -> 0
A14: 3 | B14: =Loan_Tape_Input!B3 -> 0 | C14: R9.1 | D14: Orig<=Cutoff<Maturity | E14: CRITICAL | F14: =IF(AND(Loan_Tape_Input!H3<=Loan_Tape_Input!A3,Loan_Tape_Input!A3<Loan_Tape_Input!I3),"PASS","FAIL") -> 0 | G14: AR55 | H14: =Loan_Tape_Input!H3 -> 0 | I14: AR56 | J14: =Loan_Tape_Input!I3 -> 0 | K14: =IF(F14="FAIL","Date sequence error","") -> 0
A15: 4 | B15: =Loan_Tape_Input!B4 -> 0 | C15: R1.1 | D15: Bullet must be Semi-Annual/Annual | E15: CRITICAL | F15: =IF(Loan_Tape_Input!M4="Bullet",IF(OR(Loan_Tape_Input!N4="Semi-Annual",Loan_Tape_Input!N4="Annual"),"PASS","FAIL"),"N/A") -> 0 | G15: AR69 | H15: =Loan_Tape_Input!M4 -> 0 | I15: AR70 | J15: =Loan_Tape_Input!N4 -> 0 | K15: =IF(F15="FAIL",H15&" with "&J15,"") -> 0
A16: 4 | B16: =Loan_Tape_Input!B4 -> 0 | C16: R2.1 | D16: BTL: Rental>0, NumBTL>=1, DSCR>=100 | E16: CRITICAL | F16: =IF(Loan_Tape_Input!W4="Buy-to-Let",IF(AND(Loan_Tape_Input!AB4>0,Loan_Tape_Input!AC4>=1,Loan_Tape_Input!AD4>=100),"PASS","FAIL"),"N/A") -> 0 | G16: AR130 | H16: =Loan_Tape_Input!W4 -> 0 | I16: BTL Fields | J16: =Loan_Tape_Input!AB4&"/"&Loan_Tape_Input!AC4&"/"&Loan_Tape_Input!AD4 -> 0 | K16: =IF(F16="FAIL","BTL missing required fields","") -> 0
A17: 4 | B17: =Loan_Tape_Input!B4 -> 0 | C17: R6.1 | D17: Orig LTV = (OrigBal/OrigVal)*100 | E17: CRITICAL | F17: =IF(ABS(Loan_Tape_Input!X4-(Loan_Tape_Input!K4/Loan_Tape_Input!Y4*100))<=Param_LTV_Tol,"PASS","FAIL") -> 0 | G17: AR135 | H17: =Loan_Tape_Input!X4 -> 0 | I17: Calculated | J17: =Loan_Tape_Input!K4/Loan_Tape_Input!Y4*100 -> 0 | K17: =IF(F17="FAIL","LTV: "&TEXT(H17,"0.0")&"% vs "&TEXT(J17,"0.0")&"%","") -> 0
A18: 4 | B18: =Loan_Tape_Input!B4 -> 0 | C18: R6.2 | D18: Curr LTV = (CurrBal/CurrVal)*100 | E18: CRITICAL | F18: =IF(ABS(Loan_Tape_Input!Z4-(Loan_Tape_Input!L4/Loan_Tape_Input!AA4*100))<=Param_LTV_Tol,"PASS","FAIL") -> 0 | G18: AR141 | H18: =Loan_Tape_Input!Z4 -> 0 | I18: Calculated | J18: =Loan_Tape_Input!L4/Loan_Tape_Input!AA4*100 -> 0 | K18: =IF(F18="FAIL","CLTV: "&TEXT(H18,"0.0")&"% vs "&TEXT(J18,"0.0")&"%","") -> 0
A19: 4 | B19: =Loan_Tape_Input!B4 -> 0 | C19: R5.1 | D19: MonthsArr=0 then ArrBal=0 | E19: CRITICAL | F19: =IF(Loan_Tape_Input!AG4=0,IF(Loan_Tape_Input!AF4=0,"PASS","FAIL"),"N/A") -> 0 | G19: AR170 | H19: =Loan_Tape_Input!AG4 -> 0 | I19: AR169 | J19: =Loan_Tape_Input!AF4 -> 0 | K19: =IF(F19="FAIL","Months=0 but Bal="&J19,"") -> 0
A20: 4 | B20: =Loan_Tape_Input!B4 -> 0 | C20: R9.1 | D20: Orig<=Cutoff<Maturity | E20: CRITICAL | F20: =IF(AND(Loan_Tape_Input!H4<=Loan_Tape_Input!A4,Loan_Tape_Input!A4<Loan_Tape_Input!I4),"PASS","FAIL") -> 0 | G20: AR55 | H20: =Loan_Tape_Input!H4 -> 0 | I20: AR56 | J20: =Loan_Tape_Input!I4 -> 0 | K20: =IF(F20="FAIL","Date sequence error","") -> 0

Sheet Validation_Summary
A1: VALIDATION SUMMARY BY RULE
A3: Rule | B3: Description | C3: Severity | D3: Checks | E3: Pass | F3: Fail | G3: Fail_Rate
A4: R1.1 | B4: Bullet repayment frequency | C4: CRITICAL | D4: =COUNTIFS(Validation_Results!C:C,A4,Validation_Results!F:F,"<>N/A") -> 0 | E4: =COUNTIFS(Validation_Results!C:C,A4,Validation_Results!F:F,"PASS") -> 0 | F4: =COUNTIFS(Validation_Results!C:C,A4,Validation_Results!F:F,"FAIL") -> 0 | G4: =IF(D4=0,0,F4/D4) -> 0
A5: R2.1 | B5: BTL required fields | C5: CRITICAL | D5: =COUNTIFS(Validation_Results!C:C,A5,Validation_Results!F:F,"<>N/A") -> 0 | E5: =COUNTIFS(Validation_Results!C:C,A5,Validation_Results!F:F,"PASS") -> 0 | F5: =COUNTIFS(Validation_Results!C:C,A5,Validation_Results!F:F,"FAIL") -> 0 | G5: =IF(D5=0,0,F5/D5) -> 0
A6: R6.1 | B6: Original LTV calculation | C6: CRITICAL | D6: =COUNTIFS(Validation_Results!C:C,A6,Validation_Results!F:F,"<>N/A") -> 0 | E6: =COUNTIFS(Validation_Results!C:C,A6,Validation_Results!F:F,"PASS") -> 0 | F6: =COUNTIFS(Validation_Results!C:C,A6,Validation_Results!F:F,"FAIL") -> 0 | G6: =IF(D6=0,0,F6/D6) -> 0
A7: R6.2 | B7: Current LTV calculation | C7: CRITICAL | D7: =COUNTIFS(Validation_Results!C:C,A7,Validation_Results!F:F,"<>N/A") -> 0 | E7: =COUNTIFS(Validation_Results!C:C,A7,Validation_Results!F:F,"PASS") -> 0 | F7: =COUNTIFS(Validation_Results!C:C,A7,Validation_Results!F:F,"FAIL") -> 0 | G7: =IF(D7=0,0,F7/D7) -> 0
A8: R5.1 | B8: Arrears consistency | C8: CRITICAL | D8: =COUNTIFS(Validation_Results!C:C,A8,Validation_Results!F:F,"<>N/A") -> 0 | E8: =COUNTIFS(Validation_Results!C:C,A8,Validation_Results!F:F,"PASS") -> 0 | F8: =COUNTIFS(Validation_Results!C:C,A8,Validation_Results!F:F,"FAIL") -> 0 | G8: =IF(D8=0,0,F8/D8) -> 0
A9: R9.1 | B9: Date sequencing | C9: CRITICAL | D9: =COUNTIFS(Validation_Results!C:C,A9,Validation_Results!F:F,"<>N/A") -> 0 | E9: =COUNTIFS(Validation_Results!C:C,A9,Validation_Results!F:F,"PASS") -> 0 | F9: =COUNTIFS(Validation_Results!C:C,A9,Validation_Results!F:F,"FAIL") -> 0 | G9: =IF(D9=0,0,F9/D9) -> 0
A10: TOTAL | D10: =SUM(D4:D9) -> 0 | E10: =SUM(E4:E9) -> 0 | F10: =SUM(F4:F9) -> 0 | G10: =IF(D10=0,0,F10/D10) -> 0
