Workbook

Sheet Polaris_Base
A1: Polaris 2025-3 – Baseline capital structure vs WAFF×WALS (S&P)
A3: INPUTS (blue)
A5: Class | B5: Rating (S&P) | C5: Amount (£m) | D5: Margin (bp) | E5: S&P CE (%) | F5: Calc CE (%) | G5: WAFF×WALS credit coverage (%) | H5: Headroom (CE - coverage) (%) | I5: Headroom (£m)
A6: A | B6: AAA (sf) | C6: 377.325 | D6: 0.82 | E6: 12.25 | F6: =SUM(C7:C12)/C13*100 | G6: =IF(J6="","",VLOOKUP(J6,$A$17:$E$22,4,FALSE)) | H6: =IF(G6="","",F6-G6) | I6: =IF(H6="","",H6/100*C13) | J6: AAA
A7: B-Dfrd | B7: AA (sf) | C7: 23.65 | D7: 1.1 | E7: 6.75 | F7: =SUM(C8:C12)/C13*100 | G7: =IF(J7="","",VLOOKUP(J7,$A$17:$E$22,4,FALSE)) | H7: =IF(G7="","",F7-G7) | I7: =IF(H7="","",H7/100*C13) | J7: AA
A8: C-Dfrd | B8: A- (sf) | C8: 13.975 | D8: 1.4 | E8: 3.5 | F8: =SUM(C9:C12)/C13*100 | G8: =IF(J8="","",VLOOKUP(J8,$A$17:$E$22,4,FALSE)) | H8: =IF(G8="","",F8-G8) | I8: =IF(H8="","",H8/100*C13) | J8: A
A9: D-Dfrd | B9: BBB- (sf) | C9: 7.525 | D9: 1.65 | E9: 1.75 | F9: =SUM(C10:C12)/C13*100 | G9: =IF(J9="","",VLOOKUP(J9,$A$17:$E$22,4,FALSE)) | H9: =IF(G9="","",F9-G9) | I9: =IF(H9="","",H9/100*C13) | J9: BBB
A10: E-Dfrd | B10: BB+ (sf) | C10: 3.225 | D10: 2.48 | E10: 1 | F10: =SUM(C11:C12)/C13*100 | G10: =IF(J10="","",VLOOKUP(J10,$A$17:$E$22,4,FALSE)) | H10: =IF(G10="","",F10-G10) | I10: =IF(H10="","",H10/100*C13) | J10: BB
A11: F-Dfrd | B11: B- (sf) | C11: 3.44 | D11: 3.98 | E11: 0.2 | F11: =SUM(C12:C12)/C13*100 | G11: =IF(J11="","",VLOOKUP(J11,$A$17:$E$22,4,FALSE)) | H11: =IF(G11="","",F11-G11) | I11: =IF(H11="","",H11/100*C13) | J11: B
A12: G-Dfrd | B12: CCC (sf) | C12: 0.86 | D12: 5.48 | E12: 0 | F12: =0 | G12: =IF(J12="","",VLOOKUP(J12,$A$17:$E$22,4,FALSE)) | H12: =IF(G12="","",F12-G12) | I12: =IF(H12="","",H12/100*C13)
A13: Total A–G | C13: =SUM(C6:C12)
A15: S&P Table 3 – WAFF/WALS (inputs)
A16: Rating level | B16: WAFF (%) | C16: WALS (%) | D16: Credit coverage (%) | E16: Credit coverage (decimal)
A17: AAA | B17: 30.82 | C17: 35.3 | D17: 10.88 | E17: =D17/100
A18: AA | B18: 20.67 | C18: 30.12 | D18: 6.23 | E18: =D18/100
A19: A | B19: 15.52 | C19: 21.8 | D19: 3.38 | E19: =D19/100
A20: BBB | B20: 10.35 | C20: 17.24 | D20: 1.78 | E20: =D20/100
A21: BB | B21: 5.17 | C21: 14.08 | D21: 0.73 | E21: =D21/100
A22: B | B22: 3.88 | C22: 11.28 | D22: 0.44 | E22: =D22/100
A25: Other classes (not in A–G CE denominator)
A26: Class | B26: Rating (S&P) | C26: Amount (£m) | D26: Margin (bp) | E26: S&P CE (%) | F26: Included in A–G CE? | G26: Notes
A27: X1-Dfrd | B27: B- (sf) | C27: 10.75 | D27: 3.59 | E27: 0 | F27: No | G27: Used for structural/tax/equity plumbing (0% CE in S&P table)
A28: X2-Dfrd | B28: CCC (sf) | C28: 6.45 | D28: 3.59 | E28: 0 | F28: No | G28: Used for structural/tax/equity plumbing (0% CE in S&P table)

Sheet Proposed_AE_X
A1: Proposed optimisation – Notes only to Class E (+ single Class X), replace F/G with Equity
A3: INPUTS (blue)
A5: Tranche | B5: Type | C5: Amount (£m) | D5: Included in CE denom? | E5: CE denom amount (£m) | F5: CE (%) (calc) | G5: Target CE (%) | H5: Delta vs target (bp)
A6: A | B6: Note | C6: =Polaris_Base!C6 | D6: Yes | E6: =IF(D6="Yes",C6,0) | F6: =SUM(E7:E11)/E13*100 | G6: =Polaris_Base!E6 | H6: =(F6-G6)*100
A7: B | B7: Note | C7: =Polaris_Base!C7 | D7: Yes | E7: =IF(D7="Yes",C7,0) | F7: =SUM(E8:E11)/E13*100 | G7: =Polaris_Base!E7 | H7: =(F7-G7)*100
A8: C | B8: Note | C8: =Polaris_Base!C8 | D8: Yes | E8: =IF(D8="Yes",C8,0) | F8: =SUM(E9:E11)/E13*100 | G8: =Polaris_Base!E8 | H8: =(F8-G8)*100
A9: D | B9: Note | C9: =Polaris_Base!C9 | D9: Yes | E9: =IF(D9="Yes",C9,0) | F9: =SUM(E10:E11)/E13*100 | G9: =Polaris_Base!E9 | H9: =(F9-G9)*100
A10: E | B10: Note | C10: =Polaris_Base!C10 | D10: Yes | E10: =IF(D10="Yes",C10,0) | F10: =SUM(E11:E11)/E13*100 | G10: =Polaris_Base!E10 | H10: =(F10-G10)*100
A11: Equity tail (replaces F+G) | B11: Equity | C11: =Polaris_Base!C11+Polaris_Base!C12 | D11: Yes | E11: =IF(D11="Yes",C11,0) | F11: =0 | G11: =Polaris_Base!E10 | H11: =(F11-G11)*100
A12: X (collapsed X1+X2) | B12: Note | C12: =Polaris_Base!C27+Polaris_Base!C28 | D12: No | E12: =IF(D12="Yes",C12,0)
A13: Total CE denominator | E13: =SUM(E6:E12)

Sheet Prefunding_Map
A1: Prefunding reserves – funding map under simplified structure
A3: INPUTS (blue)
A5: Pre-Funding Principal Reserve (£) | B5: 1.0438168e+08 | D5: Assumption: % of Revenue Reserve funded from Class X proceeds | E5: 1
A6: Pre-Funding Revenue Reserve (£) | B6: 2799846.5 | D6: Class X size (£m) (from Proposed sheet) | E6: =Proposed_AE_X!C12*1000000
A7: Total Pre-Funding Reserves (£) | B7: =B5+B6
D8: Revenue Reserve funded from Class X (£) | E8: =MIN(B6,E6*E5)
D9: Revenue Reserve remainder (funded elsewhere) (£) | E9: =B6-E8
A10: Notes
A11: This sheet isolates prefunding reserves; total transaction sources/uses will include initial loan purchase price, fees, swap premia, etc.
