Workbook

Sheet Input Data
A1: RMBS Structural Efficiency Analysis
A2: CE Multiple Methodology: Interactive Effects Decomposition
A4: OLD STRUCTURE
A5: Class | B5: Rating | C5: % of Coll | D5: CE % | E5: £ Balance | F5: CE Multiple | G5: Margin | H5: WAFF×WAL | I5: Calc CE Mult | J5: Notes
A6: A | B6: AAA | C6: 0.8775 | D6: 0.1225 | E6: 342225000 | F6: 0.0113 | G6: 0.0082 | H6: 10.88 | I6: =D6/H6 -> 0.011259191 | J6: =D6 / H6 -> 0.011259191
A7: B | B7: AA | C7: 0.055 | D7: 0.0675 | E7: 21450000 | F7: 0.0108 | G7: 0.011 | H7: 6.23 | I7: =D7/H7 -> 0.010834671 | J7: =D7 / H7 -> 0.010834671
A8: C | B8: A | C8: 0.0325 | D8: 0.035 | E8: 12675000 | F8: 0.0104 | G8: 0.014 | H8: 3.38 | I8: =D8/H8 -> 0.01035503 | J8: =D8 / H8 -> 0.01035503
A9: D | B9: BBB | C9: 0.0175 | D9: 0.0175 | E9: 6825000 | F9: 0.0098 | G9: 0.0165 | H9: 1.78 | I9: =D9/H9 -> 0.0098314607 | J9: =D9 / H9 -> 0.0098314607
A10: E | B10: BB | C10: 0.0075 | D10: 0.01 | E10: 2925000 | F10: 0.0137 | G10: 0.0248 | H10: 0.73 | I10: =D10/H10 -> 0.01369863 | J10: =D10 / H10 -> 0.01369863
A11: F | B11: B | C11: 0.008 | D11: 0.002 | E11: 3120000 | F11: 0.0045 | G11: 0.0398 | H11: 0.44 | I11: =D11/H11 -> 0.0045454545 | J11: =D11 / H11 -> 0.0045454545
A12: G | B12: CCC | C12: 0.002 | D12: 0 | E12: 780000 | F12: - | G12: 0.0548 | H12: - | I12: - | J12: First Loss
A13: Total / Weighted Avg | C13: =SUM(C6:C12) -> 1 | E13: =SUM(E6:E12) -> 390000000
A14: Portfolio WAFF×WAL | C14: =SUMPRODUCT(C6:C11,H6:H11) -> 10.039845 | J14: Σ(% Coll × WAFF×WAL)
A16: NEW STRUCTURE
A17: Class | B17: Rating | C17: % of Coll | D17: CE % | E17: £ Balance | F17: CE Multiple | G17: Margin | H17: WAFF×WAL | I17: Calc CE Mult | J17: Notes
A18: A | B18: AAA | C18: 0.8665 | D18: 0.1335 | E18: 338930000 | F18: 0.0107 | G18: 0.0085 | H18: 12.44 | I18: =D18/H18 -> 0.010731511 | J18: =D18 / H18 -> 0.010731511
A19: B | B19: AA | C19: 0.0535 | D19: 0.08 | E19: 20926000 | F19: 0.0111 | G19: 0.012 | H19: 7.21 | I19: =D19/H19 -> 0.0110957 | J19: =D19 / H19 -> 0.0110957
A20: C | B20: A | C20: 0.044 | D20: 0.036 | E20: 17211000 | F20: 0.009 | G20: 0.015 | H20: 3.99 | I20: =D20/H20 -> 0.0090225564 | J20: =D20 / H20 -> 0.0090225564
A21: D | B21: BBB | C21: 0.018 | D21: 0.018 | E21: 7041000 | F21: 0.0085 | G21: 0.018 | H21: 2.13 | I21: =D21/H21 -> 0.0084507042 | J21: =D21 / H21 -> 0.0084507042
A22: E | B22: BB | C22: 0.012 | D22: 0.006 | E22: 4694000 | F22: 0.0068 | G22: 0.0275 | H22: 0.88 | I22: =D22/H22 -> 0.0068181818 | J22: =D22 / H22 -> 0.0068181818
A23: F | B23: B | C23: 0.006 | D23: 0 | E23: 2347000 | F23: - | G23: 0.05 | H23: 0.54 | I23: =D23/H23 -> 0 | J23: =D23 / H23 -> 0
A24: Total / Weighted Avg | C24: =SUM(C18:C23) -> 1 | E24: =SUM(E18:E23) -> 391149000
A25: Portfolio WAFF×WAL | C25: =SUMPRODUCT(C18:C23,H18:H23) -> 11.392695 | J25: Σ(% Coll × WAFF×WAL)
A26: Risk Ratio (New/Old) | C26: =C25/C14 -> 1.1347481 | J26: New Portfolio Risk / Old Portfolio Risk

Sheet Calculations
A1: INTERACTIVE EFFECTS CALCULATIONS
A2: Using CE Multiple Methodology with Actual Class-Specific WAFF×WAL Values
A4: 1. WEIGHTED AVERAGE COST OF DEBT (WACD)
A5: Structure | B5: WACD (bps) | C5: Formula
A6: Old Structure | B6: =SUMPRODUCT('Input Data'!C6:C12,'Input Data'!G6:G12)*10000 -> 91.5825 | C6: SUMPRODUCT(% of Coll, Margin) × 10000
A7: New Structure | B7: =SUMPRODUCT('Input Data'!C18:C23,'Input Data'!G18:G23)*10000 -> 96.2125 | C7: SUMPRODUCT(% of Coll, Margin) × 10000
A8: Raw Difference | B8: =B7-B6 -> 4.63
A10: 2. PORTFOLIO RISK METRICS
A11: Metric | B11: Old Structure | C11: New Structure | D11: Risk Ratio | E11: Formula
A12: Portfolio WAFF×WAL | B12: ='Input Data'!C14 -> 10.039845 | C12: ='Input Data'!C25 -> 11.392695 | D12: ='Input Data'!C26 -> 1.1347481 | E12: New / Old
A14: 3. SCENARIO 1: CREDIT QUALITY IMPACT (CE Multiple Methodology)
A15: Approach: Apply Old Structure CE Multiples to New Pool's Actual Class-Specific WAFF×WAL
A16: Class | B16: Old CE Multiple | C16: New Class WAFF×WAL | D16: Required CE | E16: Class Size | F16: Old Margin | G16: Contribution | H16: Formula CE | I16: Formula Size
A17: A | B17: ='Input Data'!I6 -> 0.011259191 | C17: ='Input Data'!H18 -> 12.44 | D17: =B17*C17 -> 0.14006434 | E17: =1-D17 -> 0.85993566 | F17: ='Input Data'!G6 -> 0.0082 | G17: =E17*F17*10000 -> 70.514724 | H17: =B17*C17 -> 0.14006434 | I17: =1-D17 -> 0.85993566
A18: B | B18: ='Input Data'!I7 -> 0.010834671 | C18: ='Input Data'!H19 -> 7.21 | D18: =B18*C18 -> 0.078117978 | E18: =D17-D18 -> 0.061946361 | F18: ='Input Data'!G7 -> 0.011 | G18: =E18*F18*10000 -> 6.8140997 | H18: =B18*C18 -> 0.078117978 | I18: =D17-D18 -> 0.061946361
A19: C | B19: ='Input Data'!I8 -> 0.01035503 | C19: ='Input Data'!H20 -> 3.99 | D19: =B19*C19 -> 0.041316568 | E19: =D18-D19 -> 0.036801409 | F19: ='Input Data'!G8 -> 0.014 | G19: =E19*F19*10000 -> 5.1521973 | H19: =B19*C19 -> 0.041316568 | I19: =D18-D19 -> 0.036801409
A20: D | B20: ='Input Data'!I9 -> 0.0098314607 | C20: ='Input Data'!H21 -> 2.13 | D20: =B20*C20 -> 0.020941011 | E20: =D19-D20 -> 0.020375557 | F20: ='Input Data'!G9 -> 0.0165 | G20: =E20*F20*10000 -> 3.3619669 | H20: =B20*C20 -> 0.020941011 | I20: =D19-D20 -> 0.020375557
A21: E | B21: ='Input Data'!I10 -> 0.01369863 | C21: ='Input Data'!H22 -> 0.88 | D21: =B21*C21 -> 0.012054795 | E21: =D20-D21 -> 0.0088862167 | F21: ='Input Data'!G10 -> 0.0248 | G21: =E21*F21*10000 -> 2.2037817 | H21: =B21*C21 -> 0.012054795 | I21: =D20-D21 -> 0.0088862167
A22: F | B22: ='Input Data'!I11 -> 0.0045454545 | C22: ='Input Data'!H23 -> 0.54 | D22: =B22*C22 -> 0.0024545455 | E22: =D21-D22 -> 0.0096002491 | F22: ='Input Data'!G11 -> 0.0398 | G22: =E22*F22*10000 -> 3.8208991 | H22: =B22*C22 -> 0.0024545455 | I22: =D21-D22 -> 0.0096002491
A23: G | B23: ='Input Data'!I12 -> - | C23: 0.00 | D23: 0.00% | E23: =D22 -> 0.0024545455 | F23: ='Input Data'!G12 -> 0.0548 | G23: =E23*F23*10000 -> 1.3450909 | H23: N/A - First Loss | I23: =D22-D23 -> 0.0024545455
A24: TOTAL | E24: =SUM(E17:E23) -> 1 | G24: =SUM(G17:G23) -> 93.21276
A26: 4. SCENARIO 2: CREDIT + PRICING IMPACT
A27: Approach: Apply New Market Pricing to Scenario 1 Structure
A28: Class | B28: Scenario 1 Size | C28: New Margin | D28: Contribution | E28: Formula
A29: A | B29: =E17 -> 0.85993566 | C29: ='Input Data'!G18 -> 0.0085 | D29: =B29*C29*10000 -> 73.094531 | E29: =B29*C29*10000 -> 73.094531
A30: B | B30: =E18 -> 0.061946361 | C30: ='Input Data'!G19 -> 0.012 | D30: =B30*C30*10000 -> 7.4335633 | E30: =B30*C30*10000 -> 7.4335633
A31: C | B31: =E19 -> 0.036801409 | C31: ='Input Data'!G20 -> 0.015 | D31: =B31*C31*10000 -> 5.5202114 | E31: =B31*C31*10000 -> 5.5202114
A32: D | B32: =E20 -> 0.020375557 | C32: ='Input Data'!G21 -> 0.018 | D32: =B32*C32*10000 -> 3.6676002 | E32: =B32*C32*10000 -> 3.6676002
A33: E | B33: =E21 -> 0.0088862167 | C33: ='Input Data'!G22 -> 0.0275 | D33: =B33*C33*10000 -> 2.4437096 | E33: =B33*C33*10000 -> 2.4437096
A34: F | B34: =E22 -> 0.0096002491 | C34: ='Input Data'!G23 -> 0.05 | D34: =B34*C34*10000 -> 4.8001245 | E34: =B34*C34*10000 -> 4.8001245
A35: G | B35: =E23 -> 0.0024545455 | C35: 0.065 | D35: =B35*C35*10000 -> 1.5954545 | E35: =B35*C35*10000 -> 1.5954545
A36: TOTAL | B36: =SUM(B29:B35) -> 1 | D36: =SUM(D29:D35) -> 98.555195
A38: 5. SCENARIO CASCADE SUMMARY
A39: Scenario | B39: Description | C39: Credit | D39: Pricing | E39: Structure | F39: WACD (bps) | G39: Δ Marginal | H39: Δ Cumulative
A40: 0: Baseline | B40: Old structure, old credit, old pricing | C40: Old | D40: Old | E40: Old (7 classes) | F40: =B6 -> 91.5825 | G40: - | H40: -
A41: 1: Credit Δ | B41: Old CE Multiples × New Class WAFF×WAL, old pricing | C41: New | D41: Old | E41: Old (7 cls scaled) | F41: =G24 -> 93.21276 | G41: =F41-F40 -> 1.6302599 | H41: =F41-F40 -> 1.6302599
A42: 2: Credit+Pricing Δ | B42: Scenario 1 structure with new market pricing | C42: New | D42: New | E42: Old (7 cls scaled) | F42: =D36 -> 98.555195 | G42: =F42-F41 -> 5.3424349 | H42: =F42-F40 -> 6.9726949
A43: 3: Actual New | B43: Actual new structure (optimized, 6 classes) | C43: New | D43: New | E43: New (6 classes) | F43: =B7 -> 96.2125 | G43: =F43-F42 -> -2.3426949 | H43: =F43-F40 -> 4.63

Sheet CE Multiple Analysis
A1: CE MULTIPLE EFFICIENCY ANALYSIS
A2: Quantifying Structural Optimization by Rating Level
A4: CE Multiple Comparison
A5: Class | B5: Rating | C5: Old CE Mult | D5: New CE Mult | E5: Efficiency Gain | F5: New WAFF×WAL | G5: Subord. Saved | H5: Interpretation
A6: A | B6: ='Input Data'!B18 -> AAA | C6: ='Input Data'!I6 -> 0.011259191 | D6: ='Input Data'!I18 -> 0.010731511 | E6: =C6-D6 -> 0.00052767992 | F6: ='Input Data'!H18 -> 12.44 | G6: =E6*F6 -> 0.0065643382 | H6: Tighter AAA subordination
A7: B | B7: ='Input Data'!B19 -> AA | C7: ='Input Data'!I7 -> 0.010834671 | D7: ='Input Data'!I19 -> 0.0110957 | E7: =C7-D7 -> -0.00026102947 | F7: ='Input Data'!H19 -> 7.21 | G7: =E7*F7 -> -0.0018820225 | H7: Slight increase needed
A8: C | B8: ='Input Data'!B20 -> A | C8: ='Input Data'!I8 -> 0.01035503 | D8: ='Input Data'!I20 -> 0.0090225564 | E8: =C8-D8 -> 0.0013324732 | F8: ='Input Data'!H20 -> 3.99 | G8: =E8*F8 -> 0.005316568 | H8: Significant efficiency
A9: D | B9: ='Input Data'!B21 -> BBB | C9: ='Input Data'!I9 -> 0.0098314607 | D9: ='Input Data'!I21 -> 0.0084507042 | E9: =C9-D9 -> 0.0013807564 | F9: ='Input Data'!H21 -> 2.13 | G9: =E9*F9 -> 0.0029410112 | H9: Major improvement
A10: E | B10: ='Input Data'!B22 -> BB | C10: ='Input Data'!I10 -> 0.01369863 | D10: ='Input Data'!I22 -> 0.0068181818 | E10: =C10-D10 -> 0.0068804483 | F10: ='Input Data'!H22 -> 0.88 | G10: =E10*F10 -> 0.0060547945 | H10: Massive optimization
A11: F | B11: ='Input Data'!B23 -> B | C11: ='Input Data'!I11 -> 0.0045454545 | D11: ='Input Data'!I23 -> 0 | E11: =C11-D11 -> 0.0045454545 | F11: ='Input Data'!H23 -> 0.54 | G11: =E11*F11 -> 0.0024545455 | H11: 100% improvement
A12: TOTAL STRUCTURAL BENEFIT | G12: =SUM(G6:G11) -> 0.021449235
A14: Key Insights
A15: 1. AAA optimization: Reduced CE Multiple from 1.13% to 1.07% - tighter subordination for better pricing
A16: 2. Mezzanine efficiency: Classes C-E show 10-50% CE Multiple reduction - major structural gains
A17: 3. Class F transformed: From 0.45% CE Multiple to 0% - eliminated inefficient equity-like piece
A18: 4. Class G removed: 100% efficiency gain by eliminating 20bps first-loss piece at 5.48% margin
A19: 5. Total subordination saved: Sum of (Efficiency Gain × WAFF×WAL) = structural benefit in bps

Sheet Summary
A1: EXECUTIVE SUMMARY
A3: Decomposition of Cost Change
A4: Component | B4: Impact (bps) | C4: % of Total Δ | D4: Cumulative (bps) | E4: Formula
A5: Baseline (Old Structure) | B5: =Calculations!F40 -> 91.5825 | C5: - | D5: =B5 -> 91.5825 | E5: Old WACD
A6: Credit Quality Deterioration | B6: =Calculations!G41 -> 1.6302599 | C6: =B6/B9 -> 0.35210798 | D6: =B5+B6 -> 93.21276 | E6: Scen1 - Scen0
A7: Market Pricing Widening | B7: =Calculations!G42 -> 5.3424349 | C7: =B7/B9 -> 1.1538736 | D7: =D6+B7 -> 98.555195 | E7: Scen2 - Scen1
A8: Structural Optimization | B8: =Calculations!G43 -> -2.3426949 | C8: =B8/B9 -> -0.50598161 | D8: =D7+B8 -> 96.2125 | E8: Scen3 - Scen2
A9: Total Change | B9: =Calculations!H43 -> 4.63 | C9: 100.0% | D9: =Calculations!F43 -> 96.2125 | E9: New - Old WACD
A11: Monetary Value of Structural Optimization
A12: Structural Saving (bps) | B12: =ABS(B8) -> 2.3426949 | E12: =ABS(B8) -> 2.3426949
A13: New Structure Collateral (£) | B13: ='Input Data'!E24 -> 391149000 | E13: Total new collateral
A14: Annual Saving (£) | B14: =B13*(B12/10000) -> 91634.275 | E14: Collateral × bps / 10000
