Workbook

Sheet Input Data
A1: RMBS Structural Efficiency Analysis
A2: Interactive Effects Decomposition: Credit Quality × Market Pricing × Structure
A4: OLD STRUCTURE
A5: Class | B5: Target Rating | C5: % of Collateral | D5: CE % | E5: £ Balance | F5: CE Multiple | G5: Margin | H5: WAFF x WAL
A6: A | B6: AAA | C6: 0.8775 | D6: 0.1225 | E6: 342225000 | F6: 0.0113 | G6: 0.0082 | H6: 10.88
A7: B | B7: AA | C7: 0.055 | D7: 0.0675 | E7: 21450000 | F7: 0.0108 | G7: 0.011 | H7: 6.23
A8: C | B8: A | C8: 0.0325 | D8: 0.035 | E8: 12675000 | F8: 0.0104 | G8: 0.014 | H8: 3.38
A9: D | B9: BBB | C9: 0.0175 | D9: 0.0175 | E9: 6825000 | F9: 0.0098 | G9: 0.0165 | H9: 1.78
A10: E | B10: BB | C10: 0.0075 | D10: 0.01 | E10: 2925000 | F10: 0.0137 | G10: 0.0248 | H10: 0.73
A11: F | B11: B | C11: 0.008 | D11: 0.002 | E11: 3120000 | F11: 0.0045 | G11: 0.0398 | H11: 0.44
A12: G | B12: CCC | C12: 0.002 | D12: 0 | E12: 780000 | F12: - | G12: 0.0548 | H12: -
A13: Total / Weighted Avg | C13: =SUM(C6:C12) -> 1 | E13: =SUM(E6:E12) -> 390000000
A15: NEW STRUCTURE
A16: Class | B16: Target Rating | C16: % of Collateral | D16: CE % | E16: £ Balance | F16: CE Multiple | G16: Margin | H16: WAFF x WAL
A17: A | B17: AAA | C17: 0.8665 | D17: 0.1335 | E17: 338930000 | F17: 0.0107 | G17: 0.0085 | H17: 12.44
A18: B | B18: AA | C18: 0.0535 | D18: 0.08 | E18: 20926000 | F18: 0.0111 | G18: 0.012 | H18: 7.21
A19: C | B19: A | C19: 0.044 | D19: 0.036 | E19: 17211000 | F19: 0.009 | G19: 0.015 | H19: 3.99
A20: D | B20: BBB | C20: 0.018 | D20: 0.018 | E20: 7041000 | F20: 0.0085 | G20: 0.018 | H20: 2.13
A21: E | B21: BB | C21: 0.012 | D21: 0.006 | E21: 4694000 | F21: 0.0068 | G21: 0.0275 | H21: 0.88
A22: F | B22: B | C22: 0.006 | D22: 0 | E22: 2347000 | F22: - | G22: 0.05 | H22: 0.54
A23: Total / Weighted Avg | C23: =SUM(C17:C22) -> 1 | E23: =SUM(E17:E22) -> 391149000

Sheet Calculations
A1: INTERACTIVE EFFECTS CALCULATIONS
A3: 1. WEIGHTED AVERAGE COST OF DEBT (WACD)
A4: Structure | B4: WACD (bps) | C4: Formula
A5: Old Structure | B5: =SUMPRODUCT('Input Data'!C6:C12,'Input Data'!G6:G12)*10000 -> 91.5825 | C5: Sum(% of Collateral × Margin) × 10000
A6: New Structure | B6: =SUMPRODUCT('Input Data'!C17:C22,'Input Data'!G17:G22)*10000 -> 96.2125 | C6: Sum(% of Collateral × Margin) × 10000
A7: Raw Difference | B7: =B6-B5 -> 4.63
A9: 2. PORTFOLIO RISK METRIC (WAFF × WAL)
A10: Structure | B10: Portfolio Risk | C10: Risk Ratio
A11: Old Structure | B11: =SUMPRODUCT('Input Data'!C6:C11,'Input Data'!H6:H11) -> 10.039845
A12: New Structure | B12: =SUMPRODUCT('Input Data'!C17:C22,'Input Data'!H17:H22) -> 11.392695 | C12: =B12/B11 -> 1.1347481
A14: 3. SCENARIO CASCADE ANALYSIS
A15: Scenario | B15: Description | C15: Credit Quality | D15: Pricing | E15: Structure | F15: WACD (bps) | G15: Δ from Prior | H15: Cumulative Δ
A16: 0: Baseline | B16: Old structure, old credit, old pricing | C16: Old | D16: Old | E16: Old (7 classes) | F16: =B5 -> 91.5825 | G16: - | H16: -
A17: 1: Credit Δ | B17: Old structure scaled for new credit risk | C17: New | D17: Old | E17: Old (scaled) | F17: =F30 -> 100.49217 | G17: =F17-F16 -> 8.9096693 | H17: =F17-F16 -> 8.9096693
A18: 2: Credit + Pricing Δ | B18: Old structure scaled, new pricing applied | C18: New | D18: New | E18: Old (scaled) | F18: =D41 -> 105.81063 | G18: =F18-F17 -> 5.3184635 | H18: =F18-F16 -> 14.228133
A19: 3: Actual New | B19: Actual new structure (optimized) | C19: New | D19: New | E19: New (6 classes) | F19: =B6 -> 96.2125 | G19: =F19-F18 -> -9.5981328 | H19: =F19-F16 -> 4.63
A21: SCENARIO 1 DETAIL: Old Structure Scaled for New Credit
A22: Class | B22: Old % Collateral | C22: Risk Scaling Factor | D22: Scaled % Collateral | E22: Old Margin | F22: Contribution (bps)
A23: A | B23: ='Input Data'!C6 -> 0.8775 | C23: =$C$12/$B$11 -> 0.11302446 | D23: =1-('Input Data'!D6*C23) -> 0.9861545 | E23: ='Input Data'!G6 -> 0.0082 | F23: =D23*E23*10000 -> 80.864669
A24: B | B24: ='Input Data'!C7 -> 0.055 | C24: =$C$12/$B$11 -> 0.11302446 | D24: ='Input Data'!C7 -> 0.055 | E24: ='Input Data'!G7 -> 0.011 | F24: =D24*E24*10000 -> 6.05
A25: C | B25: ='Input Data'!C8 -> 0.0325 | C25: =$C$12/$B$11 -> 0.11302446 | D25: ='Input Data'!C8 -> 0.0325 | E25: ='Input Data'!G8 -> 0.014 | F25: =D25*E25*10000 -> 4.55
A26: D | B26: ='Input Data'!C9 -> 0.0175 | C26: =$C$12/$B$11 -> 0.11302446 | D26: ='Input Data'!C9 -> 0.0175 | E26: ='Input Data'!G9 -> 0.0165 | F26: =D26*E26*10000 -> 2.8875
A27: E | B27: ='Input Data'!C10 -> 0.0075 | C27: =$C$12/$B$11 -> 0.11302446 | D27: ='Input Data'!C10 -> 0.0075 | E27: ='Input Data'!G10 -> 0.0248 | F27: =D27*E27*10000 -> 1.86
A28: F | B28: ='Input Data'!C11 -> 0.008 | C28: =$C$12/$B$11 -> 0.11302446 | D28: ='Input Data'!C11 -> 0.008 | E28: ='Input Data'!G11 -> 0.0398 | F28: =D28*E28*10000 -> 3.184
A29: G | B29: ='Input Data'!C12 -> 0.002 | C29: =$C$12/$B$11 -> 0.11302446 | D29: ='Input Data'!C12 -> 0.002 | E29: ='Input Data'!G12 -> 0.0548 | F29: =D29*E29*10000 -> 1.096
A30: TOTAL | D30: =SUM(D23:D29) -> 1.1086545 | F30: =SUM(F23:F29) -> 100.49217
A32: SCENARIO 2 DETAIL: Scaled Structure with New Pricing
A33: Class | B33: Scaled % Collateral | C33: New Margin | D33: Contribution (bps)
A34: A | B34: =D23 -> 0.9861545 | C34: ='Input Data'!G17 -> 0.0085 | D34: =B34*C34*10000 -> 83.823133
A35: B | B35: =D24 -> 0.055 | C35: ='Input Data'!G18 -> 0.012 | D35: =B35*C35*10000 -> 6.6
A36: C | B36: =D25 -> 0.0325 | C36: ='Input Data'!G19 -> 0.015 | D36: =B36*C36*10000 -> 4.875
A37: D | B37: =D26 -> 0.0175 | C37: ='Input Data'!G20 -> 0.018 | D37: =B37*C37*10000 -> 3.15
A38: E | B38: =D27 -> 0.0075 | C38: ='Input Data'!G21 -> 0.0275 | D38: =B38*C38*10000 -> 2.0625
A39: F | B39: =D28 -> 0.008 | C39: ='Input Data'!G22 -> 0.05 | D39: =B39*C39*10000 -> 4
A40: G | B40: =D29 -> 0.002 | C40: 0.065 | D40: =B40*C40*10000 -> 1.3
A41: TOTAL | B41: =SUM(B34:B40) -> 1.1086545 | D41: =SUM(D34:D40) -> 105.81063
A43: 4. INTERACTION EFFECTS
A44: Interaction | B44: Calculation | C44: Impact (bps)
A45: Credit × Pricing | B45: Actual Scenario 2 - (Baseline + Pure Credit + Pure Pricing) | C45: =H18-(G17+G18-G17) -> 8.9096693

Sheet Summary
A1: EXECUTIVE SUMMARY
A3: Key Metrics Comparison
A4: Metric | B4: Old Structure | C4: New Structure | D4: Change | E4: % Change
A5: Total Collateral (£m) | B5: ='Input Data'!E13/1000000 -> 390 | C5: ='Input Data'!E24/1000000 -> 0 | D5: =C5-B5 -> -390 | E5: =(C5-B5)/B5 -> -1
A6: WACD (bps) | B6: =Calculations!B5 -> 91.5825 | C6: =Calculations!B6 -> 96.2125 | D6: =C6-B6 -> 4.63 | E6: =(C6-B6)/B6 -> 0.05055551
A7: AAA % of Collateral | B7: ='Input Data'!C6 -> 0.8775 | C7: ='Input Data'!C17 -> 0.8665 | D7: =C7-B7 -> -0.011 | E7: =(C7-B7)/B7 -> -0.012535613
A8: CE to AAA (%) | B8: ='Input Data'!D6 -> 0.1225 | C8: ='Input Data'!D17 -> 0.1335 | D8: =C8-B8 -> 0.011 | E8: =(C8-B8)/B8 -> 0.089795918
A9: Portfolio WAFF×WAL | B9: =Calculations!B11 -> 10.039845 | C9: =Calculations!B12 -> 11.392695 | D9: =C9-B9 -> 1.35285 | E9: =(C9-B9)/B9 -> 0.1347481
A10: Number of Classes | B10: 7 | C10: 6 | D10: =C10-B10 -> -1 | E10: =(C10-B10)/B10 -> -0.14285714
A12: Cost Change Decomposition
A13: Component | B13: Impact (bps) | C13: % of Total Change | D13: Cumulative (bps)
A14: Baseline (Old Structure) | B14: =Calculations!F16 -> 91.5825 | C14: - | D14: =Calculations!F16 -> 91.5825
A15: Credit Quality Deterioration | B15: =Calculations!G17 -> 8.9096693 | C15: =ABS(B15/B19) -> 1.9243346 | D15: =Calculations!H17+B14 -> 100.49217
A16: Market Pricing Widening | B16: =Calculations!G18 -> 5.3184635 | C16: =ABS(B16/B19) -> 1.1486962 | D16: =Calculations!H18+B14 -> 105.81063
A17: Credit × Pricing Interaction | B17: =0 -> 0 | C17: =0% -> 0 | D17: =B16+B17 -> 5.3184635
A18: Structural Optimization | B18: =Calculations!G19 -> -9.5981328 | C18: =ABS(B18/B19) -> 2.0730308 | D18: =Calculations!H19+B14 -> 96.2125
A19: Total Change | B19: =Calculations!H19 -> 4.63 | C19: 100.0% | D19: =Calculations!F19 -> 96.2125
A21: Monetary Value of Structural Optimization
A22: Metric | B22: Value
A23: Structural Saving (bps) | B23: =ABS(B18) -> 9.5981328
A24: New Structure Collateral (£) | B24: ='Input Data'!E24 -> 0
A25: Annual Saving (£) | B25: =B24*(B23/10000) -> 0
A27: Note: Structural optimization delivered £{26} in annual savings

Sheet Sensitivity
A1: SENSITIVITY ANALYSIS
A3: Impact of Credit Quality Changes on Required CE
A4: Credit Quality Factor | B4: Implied WAFF×WAL | C4: Required CE to AAA | D4: AAA % of Collateral | E4: Estimated WACD (bps)
A5: 0.8 | B5: =A5*Calculations!$B$11 -> 8.031876 | C5: ='Input Data'!$D$6*A5 -> 0.098 | D5: =1-C5 -> 0.902 | E5: =(D5*'Input Data'!$G$17 + (1-D5)*0.025)*10000 -> 101.17
A6: 0.9 | B6: =A6*Calculations!$B$11 -> 9.0358605 | C6: ='Input Data'!$D$6*A6 -> 0.11025 | D6: =1-C6 -> 0.88975 | E6: =(D6*'Input Data'!$G$17 + (1-D6)*0.025)*10000 -> 103.19125
A7: 1 | B7: =A7*Calculations!$B$11 -> 10.039845 | C7: ='Input Data'!$D$6*A7 -> 0.1225 | D7: =1-C7 -> 0.8775 | E7: =(D7*'Input Data'!$G$17 + (1-D7)*0.025)*10000 -> 105.2125
A8: 1.1 | B8: =A8*Calculations!$B$11 -> 11.043829 | C8: ='Input Data'!$D$6*A8 -> 0.13475 | D8: =1-C8 -> 0.86525 | E8: =(D8*'Input Data'!$G$17 + (1-D8)*0.025)*10000 -> 107.23375
A9: 1.13 | B9: =A9*Calculations!$B$11 -> 11.345025 | C9: ='Input Data'!$D$6*A9 -> 0.138425 | D9: =1-C9 -> 0.861575 | E9: =(D9*'Input Data'!$G$17 + (1-D9)*0.025)*10000 -> 107.84013
A10: 1.2 | B10: =A10*Calculations!$B$11 -> 12.047814 | C10: ='Input Data'!$D$6*A10 -> 0.147 | D10: =1-C10 -> 0.853 | E10: =(D10*'Input Data'!$G$17 + (1-D10)*0.025)*10000 -> 109.255
A11: 1.3 | B11: =A11*Calculations!$B$11 -> 13.051799 | C11: ='Input Data'!$D$6*A11 -> 0.15925 | D11: =1-C11 -> 0.84075 | E11: =(D11*'Input Data'!$G$17 + (1-D11)*0.025)*10000 -> 111.27625
A12: 1.4 | B12: =A12*Calculations!$B$11 -> 14.055783 | C12: ='Input Data'!$D$6*A12 -> 0.1715 | D12: =1-C12 -> 0.8285 | E12: =(D12*'Input Data'!$G$17 + (1-D12)*0.025)*10000 -> 113.2975
A14: Impact of Market Pricing Changes
A15: AAA Spread Change (bps) | B15: Mezz Spread Multiplier | C15: Estimated New WACD (bps) | D15: Δ from Baseline (bps)
A16: -10 | B16: 0.8 | C16: =('Input Data'!$C$17*('Input Data'!$G$6+A16/10000) + SUMPRODUCT('Input Data'!$C$18:$C$22,'Input Data'!$G$7:$G$11)*B16)*10000 -> 78.6912 | D16: =C16-Calculations!$B$5 -> -12.8913
A17: -5 | B17: 0.9 | C17: =('Input Data'!$C$17*('Input Data'!$G$6+A17/10000) + SUMPRODUCT('Input Data'!$C$18:$C$22,'Input Data'!$G$7:$G$11)*B17)*10000 -> 85.0616 | D17: =C17-Calculations!$B$5 -> -6.5209
A18: 0 | B18: 1 | C18: =('Input Data'!$C$17*('Input Data'!$G$6+A18/10000) + SUMPRODUCT('Input Data'!$C$18:$C$22,'Input Data'!$G$7:$G$11)*B18)*10000 -> 91.432 | D18: =C18-Calculations!$B$5 -> -0.1505
A19: 3 | B19: 1.15 | C19: =('Input Data'!$C$17*('Input Data'!$G$6+A19/10000) + SUMPRODUCT('Input Data'!$C$18:$C$22,'Input Data'!$G$7:$G$11)*B19)*10000 -> 97.08835 | D19: =C19-Calculations!$B$5 -> 5.50585
A20: 5 | B20: 1.2 | C20: =('Input Data'!$C$17*('Input Data'!$G$6+A20/10000) + SUMPRODUCT('Input Data'!$C$18:$C$22,'Input Data'!$G$7:$G$11)*B20)*10000 -> 99.8403 | D20: =C20-Calculations!$B$5 -> 8.2578
A21: 10 | B21: 1.4 | C21: =('Input Data'!$C$17*('Input Data'!$G$6+A21/10000) + SUMPRODUCT('Input Data'!$C$18:$C$22,'Input Data'!$G$7:$G$11)*B21)*10000 -> 108.2486 | D21: =C21-Calculations!$B$5 -> 16.6661
A22: 15 | B22: 1.6 | C22: =('Input Data'!$C$17*('Input Data'!$G$6+A22/10000) + SUMPRODUCT('Input Data'!$C$18:$C$22,'Input Data'!$G$7:$G$11)*B22)*10000 -> 116.6569 | D22: =C22-Calculations!$B$5 -> 25.0744
