Workbook

Sheet Control Panel
A1: S&P WAFF/WALS MODEL - CONTROL PANEL
A2: Version 2.0 - Complete S&P Exclusion Logic | Rating-Driven | BoE Field Mapping
A3: Created: 14-Jan-2026 11:40
A5: MODEL SETTINGS | E5: POOL STATISTICS
A6: Jurisdiction | B6: UK | C6: Select: UK, Ireland, or Netherlands
A7: Parameter | B7: Value | C7: Description | E7: Metric | F7: Value | G7: Note
A8: Target Rating Level | B8: AAA | C8: Drives Base FF, MVD, FSD, Stress Multiple | E8: Loan Count | F8: =COUNTA('Loan Tape (S&P)'!A:A)-1 | G8: After BoE conversion
A9: Analysis Date | B9: 46036.487 | C9: For seasoning and CCJ age calculations | E9: Total Balance | F9: =SUM('Loan Tape (S&P)'!B:B) | G9: £ millions
A10: Portfolio Cutoff Date | B10: 46036.487 | C10: Loan tape as-of date | E10: Avg S&P LTV | F10: =AVERAGE('FF Calculations'!E:E) | G10: Pool average
A11: OLTV Weight | B11: 0.8 | C11: S&P LTV: OLTV weight (typically 80%) | E11: Pool WAFF (%) | F11: =SUMPRODUCT('FF Calculations'!Z5:Z104,'FF Calculations'!B5:B104)/SUM('FF Calculations'!B5:B104) | G11: Balance-weighted FF
A12: CLTV Weight | B12: =VLOOKUP($B$6,'Jurisdiction Parameters'!$A:$B,2,FALSE) | C12: S&P LTV: CLTV weight (typically 20%)
A13: Originator Adjustment | B13: =VLOOKUP($B$6,'Jurisdiction Parameters'!$A:$C,3,FALSE) | C13: Global originator quality (0.70-1.30)
A15: RATING-DRIVEN PARAMETERS (AUTO) | E15: QUICK START GUIDE
A17: Parameter | B17: Value | C17: Source | E17: 1. Input loan data in Loan Tape (BoE) using Bank of England codes
A18: Base FF (%) | B18: =VLOOKUP($B$8,'Rating Parameters'!$A$6:$C$17,2,FALSE) | C18: From Rating Parameters | E18: 2. Data auto-converts to Loan Tape (S&P) format
A19: MVD (%) | B19: =VLOOKUP($B$8,'Rating Parameters'!$A$6:$C$17,3,FALSE) | C19: Market Value Decline | E19: 3. Select target rating level above (drives FF/MVD/FSD)
A20: FSD (%) | B20: =VLOOKUP($B$8,'Rating Parameters'!$A$6:$D$17,4,FALSE) | C20: Forced Sale Discount | E20: 4. Set originator adjustment (0.70-1.30, default 1.00)
A21: Stress Multiple | B21: =VLOOKUP($B$8,'Rating Parameters'!$F$6:$G$17,2,FALSE) | C21: For CE calculation | E21: 5. Review FF Calculations for loan-level results
E22: 6. Check Pool WAFF in statistics panel
E24: CRITICAL NOTES:
E25: • BTL identified from BV27 (Occupancy), not BV29 (Payment Method)
E26: • All S&P exclusion rules automatically applied
E27: • Joint borrower logic uses minimum of joint vs individual
E28: • Self-cert vs income: uses higher (not both)

Sheet BoE Auto-Mapper
A1: BOE AUTO-MAPPER CONFIGURATION
A2: This sheet defines the mapping from Bank of England PRA110 codes to S&P format fields
A4: AR Code | B4: BoE Description | C4: S&P Column | D4: S&P Field Name | E4: Data Type | F4: Conversion Rule
A5: AR1 | B5: Pool Cut-off Date | D5: Pool Cut-off Date | E5: Date | F5: Date
A6: AR2 | B6: Pool Identifier | D6: Pool Identifier | E6: Text/Numeric | F6: Direct
A7: AR3 | B7: Loan Identifier | C7: A | D7: Loan Identifier | E7: Text/Numeric | F7: Direct
A8: AR5 | B8: Originator | C8: B | D8: Originator | E8: Text | F8: Direct
A9: AR19 | B9: Number of Debtors | C9: AA | D9: Number of Debtors | E9: Numeric | F9: Direct
A10: AR21 | B10: Borrower's Employment Status | C10: W | D10: Employment Status | E10: List | F10: Code_Lookup
A11: AR22 | B11: First-time Buyer | C11: U | D11: First Time Buyer | E11: Y / N / ND | F11: YN_Convert
A12: AR23 | B12: Right to Buy | C12: V | D12: Right to Buy | E12: Y / N / ND | F12: YN_Convert
A13: AR26 | B13: Primary Income | C13: Y | D13: Primary Income | E13: Numeric | F13: Direct
A14: AR27 | B14: Income Verification for Primary Income | C14: X | D14: Income Verification | E14: List | F14: Code_Lookup
A15: AR28 | B15: Secondary Income | C15: Z | D15: Secondary Income | E15: Numeric | F15: Direct
A16: AR31 | B16: Number of County Court Judgements or equivalent - Satisfied | C16: AD | D16: CCJ Satisfied | E16: Numeric | F16: Direct
A17: AR33 | B17: Number of County Court Judgements or equivalent - Unsatisfied | C17: AE | D17: CCJ Unsatisfied | E17: Numeric | F17: Direct
A18: AR35 | B18: Last County Court Judgements or equivalent – Date | C18: AF | D18: Last CCJ Date | E18: Date / ND | F18: Date
... A48: AR173 | B48: Performance Arrangement | C48: AR | D48: Performance Arrangement | E48: Date | F48: Date

Sheet Loan Tape (BoE Raw)
A1: AR1 | B1: AR2 | C1: AR3 | D1: AR4 | E1: AR5 | F1: AR6 | G1: AR7 | H1: AR8 | I1: AR9 | J1: AR10 | K1: AR11 | L1: AR12 | M1: AR13 | N1: AR14 | O1: AR15 | P1: AR16 | Q1: AR17 | R1: AR18 | S1: AR19 | T1: AR20 | U1: AR21 | V1: AR22 | W1: AR23 | X1: AR24 | Y1: AR25 | Z1: AR26 | AA1: AR27 | AB1: AR28 | AC1: AR29 | AD1: AR30 | AE1: AR31 | AF1: AR32 | AG1: AR33 | AH1: AR34 | AI1: AR35 | AJ1: AR36 | AK1: AR37 | AL1: AR38 | AM1: AR39 | AN1: AR40 | AO1: AR41 | AP1: AR42 | AQ1: AR43 | AR1: AR44 | AS1: AR45 | AT1: AR46 | AU1: AR47 | AV1: AR48 | AW1: AR49 | AX1: AR50 | AY1: AR51 | AZ1: AR52 | BA1: AR53 | BB1: AR54 | BC1: AR55 | BD1: AR56 | BE1: AR57 | BF1: AR58 | BG1: AR59 | BH1: AR60 | BI1: AR61 | BJ1: AR62 | BK1: AR63 | BL1: AR64 | BM1: AR65 | BN1: AR66 | BO1: AR67 | BP1: AR68 | BQ1: AR69 | BR1: AR70 | BS1: AR71 | BT1: AR72 | BU1: AR73 | BV1: AR74 | BW1: AR75 | BX1: AR76 | BY1: AR77 | BZ1: AR78 | CA1: AR79 | CB1: AR80 | CC1: AR81 | CD1: AR82 | CE1: AR83 | CF1: AR84 | CG1: AR85 | CH1: AR86 | CI1: AR87 | CJ1: AR88 | CK1: AR89 | CL1: AR90 | CM1: AR91 | CN1: AR92 | CO1: AR93 | CP1: AR94 | CQ1: AR95 | CR1: AR96 | CS1: AR97 | CT1: AR98 | CU1: AR99 | CV1: AR100 | CW1: AR101 | CX1: AR102 | CY1: AR103 | CZ1: AR104 | DA1: AR105 | DB1: AR106 | DC1: AR107 | DD1: AR108 | DE1: AR109 | DF1: AR110 | DG1: AR111 | DH1: AR112 | DI1: AR113 | DJ1: AR114 | DK1: AR115 | DL1: AR116 | DM1: AR117 | DN1: AR118 | DO1: AR119 | DP1: AR120 | DQ1: AR121 | DR1: AR122 | DS1: AR123 | DT1: AR124 | DU1: AR125 | DV1: AR126 | DW1: AR127 | DX1: AR128 | DY1: AR129 | DZ1: AR130 | EA1: AR131 | EB1: AR132 | EC1: AR133 | ED1: AR134 | EE1: AR135 | EF1: AR136 | EG1: AR137 | EH1: AR138 | EI1: AR139 | EJ1: AR140 | EK1: AR141 | EL1: AR142 | EM1: AR143 | EN1: AR144 | EO1: AR145 | EP1: AR146 | EQ1: AR147 | ER1: AR148 | ES1: AR149 | ET1: AR150 | EU1: AR151 | EV1: AR152 | EW1: AR153 | EX1: AR154 | EY1: AR155 | EZ1: AR156 | FA1: AR157 | FB1: AR158 | FC1: AR159 | FD1: AR160 | FE1: AR161 | FF1: AR162 | FG1: AR163 | FH1: AR164 | FI1: AR165 | FJ1: AR166 | FK1: AR167 | FL1: AR168 | FM1: AR169 | FN1: AR170 | FO1: AR171 | FP1: AR172 | FQ1: AR173 | FR1: AR174 | FS1: AR175 | FT1: AR176 | FU1: AR177 | FV1: AR178 | FW1: AR179 | FX1: AR180 | FY1: AR181 | FZ1: AR182 | GA1: AR183 | GB1: AR184 | GC1: AR185 | GD1: AR186 | GE1: AR187 | GF1: AR188 | GG1: AR189 | GH1: AR190 | GI1: AR191 | GJ1: AR192 | GK1: AR193 | GL1: AR194 | GM1: AR195 | GN1: AR196 | GO1: AR197 | GP1: AR198 | GQ1: AR199 | GR1: AR200 | GS1: AR201 | GT1: AR202 | GU1: AR203 | GV1: AR204 | GW1: AR205 | GX1: AR206 | GY1: AR207 | GZ1: AR208 | HA1: AR209 | HB1: AR210 | HC1: AR211 | HD1: AR213 | HE1: AR214 | HF1: AR215 | HG1: AR216 | HH1: AR217 | HI1: AR218 | HJ1: AR220 | HK1: AR221 | HL1: AR222 | HM1: AR223 | HN1: AR224 | HO1: AR225 | HP1: AR226 | HQ1: AR227 | HR1: AR228 | HS1: AR230 | HT1: AR231 | HU1: AR232 | HV1: AR233 | HW1: AR234 | HX1: AR235 | HY1: AR236
A2: Pool Cut-off Date | B2: Pool Identifier | C2: Loan Identifier | D2: Regulated Loan | E2: Originator | F2: Servicer Identifier | G2: Borrower Identifier | H2: Property Identifier | I2: Blank | J2: Blank | K2: Blank | L2: Blank | M2: Blank | N2: Blank | O2: Borrower Type | P2: Foreign National | Q2: Borrower Credit Quality | R2: Borrower Year of Birth | S2: Number of Debtors | T2: Second Applicant Year of Birth | U2: Borrower's Employment Status | V2: First-time Buyer | W2: Right to Buy | X2: Right to Buy Price | Y2: Class of Borrower | Z2: Primary Income | AA2: Income Verification for Primary Income | AB2: Secondary Income | AC2: Income Verification for Secondary Income | AD2: Resident | AE2: Number of County Court Judgements or equivalent - Satisfied | AF2: Value of County Court Judgements or equivalent - Satisfied | AG2: Number of County Court Judgements or equivalent - Unsatisfied | AH2: Value of County Court Judgements or equivalent - Unsatisfied | AI2: Last County Court Judgements or equivalent – Date | AJ2: Bankruptcy or Individual Voluntary Arrangement Flag | AK2: Bureau Krediet Registratie 1 to 10 - Credit Type | AL2: Bureau Krediet Registratie 1 to 10- Registration Date | AM2: Bureau Krediet Registratie 1 to 10 - Arrears Code | AN2: Bureau Krediet Registratie 1 to 10 - Credit Amount | AO2: Bureau Krediet Registratie 1 to 10 - Is Coding Cured? | AP2: Bureau Krediet Registratie 1 to 10 - Number of Months Since Cured | AQ2: Bureau Score Provider | AR2: Bureau Score Type | AS2: Bureau Score Date | AT2: Bureau Score Value | AU2: Prior Repossessions | AV2: Previous Mortgage Arrears 0-6 Months | AW2: Previous Mortgage Arrears 6+ Months | AX2: Internal Rating | AY2: Blank | AZ2: Blank | BA2: Blank | BB2: Blank | BC2: Loan Origination Date | BD2: Date of Loan Maturity | BE2: Account Status Date | BF2: Origination Channel / Arranging Bank or Division | BG2: Purpose | BH2: Shared Ownership | BI2: Loan Term | BJ2: Principal Grace Period | BK2: Amount Guaranteed | BL2: Subsidy | BM2: Loan Currency Denomination | BN2: Original Balance | BO2: Current Balance | BP2: Fractioned / Subrogated Loans | BQ2: Repayment Method | BR2: Payment Frequency | BS2: Payment Due | BT2: Payment Type | BU2: Debt to Income | BV2: Type of Guarantee Provider | BW2: Guarantee Provider | BX2: Income Guarantor | BY2: Subsidy Received | BZ2: Mortgage Indemnity Guarantee Provider | CA2: Mortgage Indemnity Guarantee Attachment Point | CB2: Prior Balances | CC2: Other Prior Balances | CD2: Pari Passu Loans | CE2: Subordinated Claims | CF2: Lien | CG2: Retained Amount | CH2: Retained Amount Date | CI2: Maximum Balance | CJ2: Further Loan Advance | CK2: Further Loan Advance Date | CL2: Flexible Loan Amount | CM2: Further Advances | CN2: Length of Payment Holiday | CO2: Subsidy Period | CP2: Mortgage Inscription | CQ2: Mortgage Mandate | CR2: Deed of Postponement? | CS2: Pre-payment Amount | CT2: Pre-payment Date | CU2: Pre-payment Penalties | CV2: Cumulative Pre-payments | CW2: Amount of pre-payments allowed per year | CX2: Offset Savings Balance | CY2: Original Percentage Owned | CZ2: Current Percentage Owned | DA2: Help to Buy Scheme Type | DB2: Blank | DC2: Interest Rate Type | DD2: Current Interest Rate Index | DE2: Current Interest Rate | DF2: Current Interest Rate Margin | DG2: Interest Rate Reset Interval | DH2: Interest Cap Rate | DI2: Interest Revision Date 1 | DJ2: Revision Margin 2 | DK2: Interest Revision Date 2 | DL2: Revision Margin 3 | DM2: Interest Revision Date 3 | DN2: Revised Interest Rate Index | DO2: Revised Interest Rate Margin | DP2: Final Margin | DQ2: Final Step Date | DR2: Restructuring Arrangement | DS2: Forbearance Type | DT2: Blank | DU2: Blank | DV2: Blank | DW2: Blank | DX2: Geographic Region | DY2: Property Postcode | DZ2: Occupancy Type | EA2: Property Type | EB2: New Property | EC2: Construction Year | ED2: Property Rating | EE2: Original Loan to Value | EF2: Valuation Amount | EG2: Original Valuation Type | EH2: Valuation Date | EI2: Confidence Interval for Original Automated Valuation Model Valuation | EJ2: Provider of Original Automated Valuation Model Valuation | EK2: Current Loan to Value | EL2: Purchase Price | EM2: Current Valuation Amount | EN2: Current Valuation Type | EO2: Current Valuation Date | EP2: Confidence Interval for Current Automated Valuation Model Valuation | EQ2: Provider of Current Automated Valuation Model Valuation | ER2: Property Value at Time of Latest Loan Advance | ES2: Indexed Foreclosure Value | ET2: Ipoteca | EU2: Date of Sale | EV2: Additional Collateral | EW2: Additional Collateral Provider | EX2: Gross Annual Rental Income | EY2: Number of Buy to Let Properties | EZ2: Debt Service Coverage Ratio | FA2: Additional Collateral Value | FB2: Real Estate Owned | FC2: Is Property Transferability Limited | FD2: Time Until Declassification | FE2: Blank | FF2: Current Energy Performance Certificate Value | FG2: Potential Energy Performance Certificate Value | FH2: Exemption from Energy Efficiency Regulation | FI2: Blank | FJ2: Account Status | FK2: Date Last Current | FL2: Date Last in Arrears | FM2: Arrears Balance | FN2: Number Months in Arrears | FO2: Arrears 1 Month Ago | FP2: Arrears 2 Months Ago | FQ2: Performance Arrangement | FR2: Litigation | FS2: Redemption Date | FT2: Months in Arrears Prior | FU2: Default or Foreclosure | FV2: Date of Default | FW2: Sale Price | FX2: Loss on Sale | FY2: Cumulative Recoveries | FZ2: Professional Negligence Recoveries | GA2: Loan flagged as Contencioso | GB2: Blank | GC2: Blank | GD2: Blank | GE2: Blank | GF2: Blank | GG2: Second Borrower's Employment Status | GH2: Class of Second Borrower | GI2: Resident (Second Borrower) | GJ2: Number of County Court Judgements or equivalent - Satisfied (Second Borrower) | GK2: Value of County Court Judgements or equivalent - Satisfied (Second Borrower) | GL2: Number of County Court Judgements or equivalent - Unsatisfied (Second Borrower) | GM2: Value of County Court Judgements or equivalent - Unsatisfied (Second Borrower) | GN2: Last County Court Judgements or equivalent – Date (Second Borrower) | GO2: Bankruptcy or Individual Voluntary Arrangement Flag (Second Borrower) | GP2: Bureau Krediet Registratie 1 to 10 - Credit Type (Second Borrower) | GQ2: Bureau Krediet Registratie 1 to 10- Registration Date (Second Borrower) | GR2: Bureau Krediet Registratie 1 to 10 - Arrears Code (Second Borrower) | GS2: Bureau Krediet Registratie 1 to 10 - Credit Amount (Second Borrower) | GT2: Bureau Krediet Registratie 1 to 10 - Is Coding Cured? (Second Borrower) | GU2: Bureau Krediet Registratie 1 to 10 - Number of Months Since Cured (Second Borrower) | GV2: Bureau Score Provider (Second Borrower) | GW2: Bureau Score Type (Second Borrower) | GX2: Bureau Score Date (Second Borrower) | GY2: Bureau Score Value (Second Borrower) | GZ2: Prior Repossessions (Second Borrower) | HA2: Previous Mortgage Arrears 0-6 Months (Second Borrower) | HB2: Previous Mortgage Arrears 6+ Months (Second Borrower) | HC2: Bureau Krediet Registratie 1 to 10 - Credit Type (Primary Borrower - At Origination) | HD2: Bureau Krediet Registratie 1 to 10 - Arrears Code (Primary Borrower - At Origination) | HE2: Bureau Krediet Registratie 1 to 10 - Credit Amount (Primary Borrower - At Origination) | HF2: Bureau Krediet Registratie 1 to 10 - Is Coding Cured? (Primary Borrower - At Origination) | HG2: Bureau Krediet Registratie 1 to 10 - Number of Months Since Cured (Primary Borrower - At Origination) | HH2: Bureau Score Provider (Primary Borrower - At Origination) | HI2: Bureau Score Type (Primary Borrower - At Origination) | HJ2: Bureau Score Value (Primary Borrower - At Origination) | HK2: Bureau Krediet Registratie 1 to 10 - Credit Type (Secondary Borrower - At Origination) | HL2: Bureau Krediet Registratie 1 to 10- Registration Date (Secondary Borrower - At Origination) | HM2: Bureau Krediet Registratie 1 to 10 - Arrears Code (Secondary Borrower - At Origination) | HN2: Bureau Krediet Registratie 1 to 10 - Credit Amount (Secondary Borrower - At Origination) | HO2: Bureau Krediet Registratie 1 to 10 - Is Coding Cured? (Secondary Borrower - At Origination) | HP2: Bureau Krediet Registratie 1 to 10 - Number of Months Since Cured (Secondary Borrower - At Origination) | HQ2: Bureau Score Provider (Secondary Borrower - At Origination) | HR2: Bureau Score Type (Secondary Borrower - At Origination) | HS2: Bureau Score Value (Secondary Borrower - At Origination) | HT2: Borrower Type (Secondary Borrower) | HU2: Foreign National (Secondary Borrower) | HV2: Borrower Credit Quality (Secondary Borrower) | HW2: First-time Buyer (Secondary Borrower) | HX2: Bankruptcy or Individual Voluntary Arrangement Flag | HY2: Bankruptcy or Individual Voluntary Arrangement Flag (Second Borrower)
A10: • Do NOT delete or modify the BoE field codes in your headers
A11: • Dates should be in a recognizable format (DD/MM/YYYY or Excel date serial)
A12: • Numeric codes will be automatically converted to text descriptions
A13: • Empty cells are allowed for optional fields
A16: BV1 (Loan ID) | B16: BV5 (Balance) | C16: BV12 (Property Type) | D16: BV27 (Occupancy) | E16: BV29 (Payment) | F16: BV25 (Rate Type) | G16: BV48 (Perf Arr) | H16: BV49 (Perf Date) | I16: BV50 (Last 90+ Date) | J16: ...more BoE fields...
A17: [Paste your loan tape starting here - replace this sample data]

Sheet AR Data Dictionary
A1: BANK OF ENGLAND AR FIELD DATA DICTIONARY
A2: Complete reference for all 175 AR field codes from BoE PRA110 template
A3: Total AR Fields: 175 | Mapped in Model: 40 | Unmapped: 135
A5: AR Code | B5: Field Name | C5: Category | D5: Priority | E5: Tag | F5: Mapped in Model
A6: AR1 | B6: Pool Cut-off Date | C6: Core | D6: Mandatory | E6: dynamic | F6: NO
A7: AR2 | B7: Pool Identifier | C7: Core | D7: Mandatory | E7: static | F7: NO
A8: AR3 | B8: Loan Identifier | C8: Core | D8: Mandatory | E8: static | F8: YES
A9: AR4 | B9: Regulated Loan | C9: Core | D9: Optional | E9: static | F9: NO
A10: AR5 | B10: Originator | C10: Core | D10: Mandatory | E10: static | F10: YES
A11: AR6 | B11: Servicer Identifier | C11: Core | D11: Mandatory | E11: static | F11: NO
A12: AR7 | B12: Borrower Identifier | C12: Core | D12: Mandatory | E12: static | F12: NO
A13: AR8 | B13: Property Identifier | C13: Core | D13: Mandatory | E13: static | F13: NO
A14: AR9 | B14: Blank | C14: Core | F14: NO
A15: AR10 | B15: Blank | C15: Core | F15: NO
A16: AR11 | B16: Blank | C16: Core | F16: NO
A17: AR12 | B17: Blank | C17: Core | F17: NO
A18: AR13 | B18: Blank | C18: Core | F18: NO
A19: AR14 | B19: Blank | C19: Core | F19: NO
A20: AR15 | B20: Borrower Type | C20: Borrower Information | D20: Optional | E20: static | F20: NO
A21: AR16 | B21: Foreign National | C21: Borrower Information | D21: Optional | E21: static | F21: NO
A22: AR17 | B22: Borrower Credit Quality | C22: Borrower Information | D22: Optional | E22: static | F22: NO
A23: AR18 | B23: Borrower Year of Birth | C23: Borrower Information | D23: Optional | E23: static | F23: NO
A24: AR19 | B24: Number of Debtors | C24: Borrower Information | D24: Mandatory | E24: static | F24: NO
A25: AR20 | B25: Second Applicant Year of Birth | C25: Borrower Information | D25: Optional | E25: static | F25: NO
A26: AR21 | B26: Borrower's Employment Status | C26: Borrower Information | D26: Mandatory | E26: static | F26: NO
A27: AR22 | B27: First-time Buyer | C27: Borrower Information | D27: Optional | E27: static | F27: YES
A28: AR23 | B28: Right to Buy | C28: Borrower Information | D28: Optional | E28: static | F28: YES
A29: AR24 | B29: Right to Buy Price | C29: Borrower Information | D29: Optional | E29: static | F29: NO
A30: AR25 | B30: Class of Borrower | C30: Borrower Information | D30: Optional | E30: static | F30: NO
A31: AR26 | B31: Primary Income | C31: Borrower Information | D31: Mandatory | E31: static | F31: YES
... A55: AR50 | B55: Internal Rating | C55: Borrower Information | D55: Optional | E55: dynamic | F55: NO
A56: AR51 | B56: Blank | C56: Borrower Information | F56: NO
A57: AR52 | B57: Blank | C57: Borrower Information | F57: NO
A58: AR53 | B58: Blank | C58: Borrower Information | F58: NO
A59: AR54 | B59: Blank | C59: Borrower Information | F59: NO
A60: AR55 | B60: Loan Origination Date | C60: Loan Characteristics | D60: Mandatory | E60: static | F60: YES
A61: AR56 | B61: Date of Loan Maturity | C61: Loan Characteristics | D61: Mandatory | E61: dynamic | F61: YES
A62: AR57 | B62: Account Status Date | C62: Loan Characteristics | D62: Mandatory | E62: static | F62: NO
A63: AR58 | B63: Origination Channel / Arranging Bank or Division | C63: Loan Characteristics | D63: Mandatory | E63: static | F63: NO
A64: AR59 | B64: Purpose | C64: Loan Characteristics | D64: Mandatory | E64: static | F64: YES
A65: AR60 | B65: Shared Ownership | C65: Loan Characteristics | D65: Mandatory | E65: static | F65: YES
A66: AR61 | B66: Loan Term | C66: Loan Characteristics | D66: Mandatory | E66: static | F66: NO
A67: AR62 | B67: Principal Grace Period | C67: Loan Characteristics | D67: Optional | E67: static | F67: NO
A68: AR63 | B68: Amount Guaranteed | C68: Loan Characteristics | D68: Optional | E68: static | F68: NO
A69: AR64 | B69: Subsidy | C69: Loan Characteristics | D69: Optional | E69: static | F69: NO
A70: AR65 | B70: Loan Currency Denomination | C70: Loan Characteristics | D70: Mandatory | E70: static | F70: NO
A71: AR66 | B71: Original Balance | C71: Loan Characteristics | D71: Mandatory | E71: static | F71: YES
... A110: AR105 | B110: Help to Buy Scheme Type | C110: Loan Characteristics | D110: Mandatory | E110: static | F110: YES
A111: AR106 | B111: Blank | C111: Loan Characteristics | F111: NO
A112: AR107 | B112: Interest Rate Type | C112: Interest Rate | D112: Mandatory | E112: static | F112: YES
A113: AR108 | B113: Current Interest Rate Index | C113: Interest Rate | D113: Mandatory | E113: dynamic | F113: NO
A114: AR109 | B114: Current Interest Rate | C114: Interest Rate | D114: Mandatory | E114: dynamic | F114: YES
A115: AR110 | B115: Current Interest Rate Margin | C115: Interest Rate | D115: Mandatory | E115: dynamic | F115: NO
A116: AR111 | B116: Interest Rate Reset Interval | C116: Interest Rate | D116: Mandatory | E116: dynamic | F116: NO
A117: AR112 | B117: Interest Cap Rate | C117: Interest Rate | D117: Mandatory | E117: static | F117: NO
A118: AR113 | B118: Interest Revision Date 1 | C118: Interest Rate | D118: Mandatory | E118: dynamic | F118: NO
A119: AR114 | B119: Revision Margin 2 | C119: Interest Rate | D119: Mandatory | E119: dynamic | F119: NO
A120: AR115 | B120: Interest Revision Date 2 | C120: Interest Rate | D120: Mandatory | E120: dynamic | F120: NO
A121: AR116 | B121: Revision Margin 3 | C121: Interest Rate | D121: Mandatory | E121: dynamic | F121: NO
A122: AR117 | B122: Interest Revision Date 3 | C122: Interest Rate | D122: Mandatory | E122: dynamic | F122: NO
A123: AR118 | B123: Revised Interest Rate Index | C123: Interest Rate | D123: Mandatory | E123: dynamic | F123: NO
... A128: AR123 | B128: Forbearance Type | C128: Interest Rate | D128: Mandatory | E128: dynamic | F128: NO
A129: AR124 | B129: Blank | C129: Interest Rate | F129: NO
A130: AR125 | B130: Blank | C130: Interest Rate | F130: NO
A131: AR126 | B131: Blank | C131: Interest Rate | F131: NO
A132: AR127 | B132: Blank | C132: Interest Rate | F132: NO
A133: AR128 | B133: Geographic Region | C133: Property & Collateral | D133: Mandatory | E133: static | F133: YES
A134: AR129 | B134: Property Postcode | C134: Property & Collateral | D134: Optional | E134: static | F134: YES
A135: AR130 | B135: Occupancy Type | C135: Property & Collateral | D135: Mandatory | E135: static | F135: YES
A136: AR131 | B136: Property Type | C136: Property & Collateral | D136: Mandatory | E136: static | F136: YES
A137: AR132 | B137: New Property | C137: Property & Collateral | D137: Optional | E137: static | F137: NO
A138: AR133 | B138: Construction Year | C138: Property & Collateral | D138: Optional | E138: static | F138: NO
A139: AR134 | B139: Property Rating | C139: Property & Collateral | D139: Optional | E139: static | F139: NO
A140: AR135 | B140: Original Loan to Value | C140: Property & Collateral | D140: Mandatory | E140: static | F140: YES
A141: AR136 | B141: Valuation Amount | C141: Property & Collateral | D141: Mandatory | E141: static | F141: YES
A142: AR137 | B142: Original Valuation Type | C142: Property & Collateral | D142: Mandatory | E142: static | F142: NO
A143: AR138 | B143: Valuation Date | C143: Property & Collateral | D143: Mandatory | E143: static | F143: NO
A144: AR139 | B144: Confidence Interval for Original Automated Valuation Model Valuation | C144: Property & Collateral | D144: Optional | E144: static | F144: NO
... A165: AR160 | B165: Time Until Declassification | C165: Property & Collateral | D165: Optional | E165: dynamic | F165: NO
A166: AR161 | B166: Blank | C166: Property & Collateral | F166: NO
A167: AR162 | B167: Current Energy Performance Certificate Value | C167: Property & Collateral | D167: Mandatory | E167: dynamic | F167: NO
A168: AR163 | B168: Potential Energy Performance Certificate Value | C168: Property & Collateral | D168: Mandatory | E168: dynamic | F168: NO
A169: AR164 | B169: Exemption from Energy Efficiency Regulation | C169: Property & Collateral | D169: Mandatory | E169: dynamic | F169: NO
A170: AR165 | B170: Blank | C170: Property & Collateral | F170: NO
A171: AR166 | B171: Account Status | C171: Performance | D171: Mandatory | E171: dynamic | F171: YES
A172: AR167 | B172: Date Last Current | C172: Performance | D172: Optional | E172: dynamic | F172: YES
A173: AR168 | B173: Date Last in Arrears | C173: Performance | D173: Optional | E173: dynamic | F173: YES
A174: AR169 | B174: Arrears Balance | C174: Performance | D174: Mandatory | E174: dynamic | F174: YES
A175: AR170 | B175: Number Months in Arrears | C175: Performance | D175: Mandatory | E175: dynamic | F175: YES
A176: AR171 | B176: Arrears 1 Month Ago | C176: Performance | D176: Mandatory | E176: dynamic | F176: NO
A177: AR172 | B177: Arrears 2 Months Ago | C177: Performance | D177: Mandatory | E177: dynamic | F177: NO
A178: AR173 | B178: Performance Arrangement | C178: Performance | D178: Mandatory | E178: dynamic | F178: YES
A179: AR174 | B179: Litigation | C179: Performance | D179: Mandatory | E179: dynamic | F179: NO
A180: AR175 | B180: Redemption Date | C180: Performance | D180: Mandatory | E180: dynamic | F180: NO

Sheet Jurisdiction Parameters
A1: JURISDICTION-SPECIFIC PARAMETERS
A2: All jurisdiction-specific values - Model references this sheet dynamically
A4: Jurisdiction | B4: OLTV Weight | C4: CLTV Weight | D4: Valuation Haircut | E4: Interest Cost (BTL) | F4: Seasoning Periods | G4: Income Mult Threshold 1 | H4: Income Mult Threshold 2 | I4: Income Mult Joint Threshold 1 | J4: Income Mult Joint Threshold 2 | K4: Arrears 1mo Mult | L4: Arrears 2mo Mult | M4: Arrears 3mo Mult | N4: Foreclosure Cost % | O4: LTV Curve Reference | P4: Regional Adj Enabled | Q4: Reperform Threshold (Years)
A5: UK | B5: 0.8 | C5: 0.2 | D5: 0.05 | E5: 0.055 | F5: 18 | G5: 5 | H5: 3.5 | I5: 3.25 | J5: 2.75 | K5: 2.5 | L5: 5 | M5: 100 | N5: 0.08 | O5: LTV Curve UK | P5: Yes | Q5: 3
A6: Ireland | B6: 0.75 | C6: 0.25 | D6: 0.07 | E6: 0.06 | F6: 24 | G6: 4.5 | H6: 3 | I6: 3 | J6: 2.5 | K6: 3 | L6: 6 | M6: 100 | N6: 0.1 | O6: LTV Curve Ireland | P6: Yes | Q6: 3
A7: Netherlands | B7: 0.8 | C7: 0.2 | D7: 0.04 | E7: 0.05 | F7: 12 | G7: 6 | H7: 4 | I7: 4 | J7: 3 | K7: 2 | L7: 4 | M7: 100 | N7: 0.07 | O7: LTV Curve Netherlands | P7: No | Q7: 3

Sheet Rating Parameters
A1: RATING-DRIVEN PARAMETERS
A3: All parameters that vary by target rating level
A5: Rating | B5: Base FF (%) | C5: MVD (%) | D5: FSD (%) | E5: Source | F5: Rating | G5: Stress Multiple
A6: AAA | B6: 0.12 | C6: 0.45 | D6: 0.15 | E6: Table 72 / S&P MVD assumptions | F6: AAA | G6: 14
A7: AA+ | B7: 0.105 | C7: 0.42 | D7: 0.14 | E7: Interpolated | F7: AA+ | G7: 12
A8: AA | B8: 0.08 | C8: 0.4 | D8: 0.13 | E8: Table 72 | F8: AA | G8: 10.5
A9: AA- | B9: 0.07 | C9: 0.37 | D9: 0.12 | E9: Interpolated | F9: AA- | G9: 9
A10: A+ | B10: 0.065 | C10: 0.34 | D10: 0.11 | E10: Interpolated | F10: A+ | G10: 7.5
A11: A | B11: 0.06 | C11: 0.32 | D11: 0.1 | E11: Table 72 | F11: A | G11: 6.5
A12: A- | B12: 0.055 | C12: 0.3 | D12: 0.1 | E12: Interpolated | F12: A- | G12: 5.5
A13: BBB+ | B13: 0.05 | C13: 0.27 | D13: 0.09 | E13: Interpolated | F13: BBB+ | G13: 4.5
A14: BBB | B14: 0.04 | C14: 0.25 | D14: 0.08 | E14: Table 72 | F14: BBB | G14: 4
A15: BBB- | B15: 0.035 | C15: 0.22 | D15: 0.08 | E15: Interpolated | F15: BBB- | G15: 3.5
A16: BB | B16: 0.02 | C16: 0.2 | D16: 0.07 | E16: Table 72 | F16: BB | G16: 3
A17: B | B17: 0.015 | C17: 0.18 | D17: 0.07 | E17: Table 72 | F17: B | G17: 2.5

Sheet LTV Curve
A1: S&P UK LTV CURVE - TYPE 2 FULL RECOURSE (131 Points)
A3: LTV % | B3: FF Multiplier | C3: Named Range | D3: Notes
A4: 0.2 | B4: 0.2889 | C4: LTV_20 | D4: Minimum LTV in curve
A5: 0.21 | B5: 0.2907 | C5: LTV_21
A6: 0.22 | B6: 0.2925 | C6: LTV_22
A7: 0.23 | B7: 0.2945 | C7: LTV_23
A8: 0.24 | B8: 0.2966 | C8: LTV_24
A9: 0.25 | B9: 0.2988 | C9: LTV_25
A10: 0.26 | B10: 0.3011 | C10: LTV_26
A11: 0.27 | B11: 0.3037 | C11: LTV_27
A12: 0.28 | B12: 0.3063 | C12: LTV_28
A13: 0.29 | B13: 0.3092 | C13: LTV_29
A14: 0.3 | B14: 0.3122 | C14: LTV_30
A15: 0.31 | B15: 0.3155 | C15: LTV_31
A16: 0.32 | B16: 0.3189 | C16: LTV_32
... A53: 0.69 | B53: 0.8368 | C53: LTV_69
A54: 0.7 | B54: 0.8739 | C54: LTV_70 | D54: Archetypal (1.0x multiplier at 73% per curve)
A55: 0.71 | B55: 0.9134 | C55: LTV_71
A56: 0.72 | B56: 0.9553 | C56: LTV_72
A57: 0.73 | B57: 1 | C57: LTV_73
A58: 0.74 | B58: 1.0475 | C58: LTV_74
A59: 0.75 | B59: 1.098 | C59: LTV_75
A60: 0.76 | B60: 1.1518 | C60: LTV_76
A61: 0.77 | B61: 1.2089 | C61: LTV_77
A62: 0.78 | B62: 1.2696 | C62: LTV_78
A63: 0.79 | B63: 1.3341 | C63: LTV_79
A64: 0.8 | B64: 1.4025 | C64: LTV_80
A65: 0.81 | B65: 1.4751 | C65: LTV_81
A66: 0.82 | B66: 1.552 | C66: LTV_82
... A133: 1.49 | B133: 4.02 | C133: LTV_149
A134: 1.5 | B134: 4.02 | C134: LTV_150 | D134: Maximum LTV (cap at 4.02x)

Sheet FF Adj Parameters
A1: FF ADJUSTMENT PARAMETERS - COMPLETE LOOKUP TABLES
A3: SEASONING ADJUSTMENTS
A4: Threshold (Years)
A5: 5 | B5: 1 | C5: <5 years - No credit
A6: 6 | B6: 0.75 | C6: 5-6 years - 25% credit
A7: 7 | B7: 0.7 | C7: 6-7 years - 30% credit
A8: 8 | B8: 0.65 | C8: 7-8 years - 35% credit
A9: 9 | B9: 0.6 | C9: 8-9 years - 40% credit
A10: 10
A11: 999 | B11: 0.5 | C11: >10 years - 50% credit
A13: INCOME MULTIPLE ADJUSTMENTS
A14: Threshold | B14: Multiplier | C14: Description
A15: 3.5 | B15: 1 | C15: ≤3.5 single or ≤2.75 joint
A16: 5 | B16: 1.2 | C16: >3.5 to 5.0 single or >2.75 to 3.25 joint
A17: 999 | B17: 1.5 | C17: >5.0 single or >3.25 joint
A19: BTL DSCR ADJUSTMENTS
A20: DSCR Threshold | B20: Multiplier | C20: Description
A21: 0 | B21: 1.7 | C21: No rental income
A22: 1 | B22: 1.55 | C22: <1.00 - Inadequate
A23: 1.2 | B23: 1.45 | C23: 1.00-1.20 - Minimal
A24: 1.35
A25: 999 | B25: 1.25 | C25: ≥1.35 - Strong
A27: INTEREST ONLY ADJUSTMENTS (NON-BTL)
A28: Years to Maturity | B28: Multiplier | C28: Description
A29: 5 | B29: 1.25 | C29: <5 years
A30: 15
A31: 25 | B31: 1.2 | C31: 15-25 years
A32: 999 | B32: 1.1 | C32: >25 years
A34: FIXED ADJUSTMENT MULTIPLIERS
A35: Adjustment Type | B35: Multiplier | C35: Notes
A36: First Time Buyer | B36: 1.1 | C36: If seasoning <18 months
A37: Help to Buy | B37: 1 | C37: No adjustment per S&P
A38: Shared Ownership | B38: 1.15 | C38: Complexity premium
A39: Right to Buy | B39: 1.2 | C39: Discount unwind risk
A40: Self-Certification
A41: Payment Shock | B41: 1.1 | C41: Fixed rate <60mo to maturity
A42: Self-Employed | B42: 1.15 | C42: Income stability risk
A43: Commercial Property | B43: 1.85 | C43: Commercial use risk
A44: CCJ | B44: 1.3 | C44: County Court Judgment
A45: Bankruptcy | B45: 4 | C45: Floor at 0.50
A46: IVA | B46: 3.5 | C46: Floor at 0.50
A47: Repossession | B47: 5 | C47: Floor at 0.50
A48: Lien 1st | B48: 1 | C48: First lien baseline
A49: Lien 2nd
A50: Lien 3rd+ | B50: 1.7 | C50: Third+ lien
A51: Purpose Purchase | B51: 1 | C51: Baseline
A52: Purpose Remortgage | B52: 1 | C52: No adjustment
A53: Purpose Cash-out | B53: 1.2 | C53: Increased risk
A54: Arrears Current | B54: 1 | C54: No arrears
A55: Arrears 1-2 months | B55: 1.15 | C55: Minor arrears
A56: Arrears 3+ months
A87: PROPERTY TYPE CODES
A88: Code | B88: Description
A89: 1 | B89: House
A90: 2 | B90: Flat
A91: 3 | B91: Bungalow
A92: 4 | B92: Maisonette
A94: OCCUPANCY TYPE CODES
A95: Code | B95: Description
A96: 1 | B96: Owner Occupied
A97: 2 | B97: Buy to Let
A98: 3 | B98: Second Home
A99: 4 | B99: Investment
A101: INTEREST RATE TYPE CODES
A102: Code | B102: Description
A103: 1 | B103: Fixed
A104: 2 | B104: Variable
A105: 3 | B105: Tracker
A107: PAYMENT METHOD CODES
A108: Code | B108: Description
A109: 1 | B109: Repayment
A110: 2 | B110: Interest Only
A111: 3 | B111: Part and Part
A113: VALUATION TYPE CODES
A114: Code | B114: Description
A115: 1 | B115: Full
A116: 2 | B116: Desktop
A117: 3 | B117: Drive-by
A118: 4 | B118: AVM
A124: FTB Seasoning Threshold (months) | B124: 18
A125: Payment Shock Months Threshold | B125: 60
A126: Bankruptcy Floor Multiplier | B126: 0.5
A129: BASE FORECLOSURE FREQUENCY BY RATING LEVEL
A130: Rating Level | B130: Base FF (%)
A131: AAA | B131: 0.36
A132: AA+ | B132: 0.45
A133: AA | B133: 0.57
A134: AA- | B134: 0.71
A135: A+ | B135: 0.9
A136: A | B136: 1.13
A137: A- | B137: 1.42
A138: BBB+ | B138: 1.78
A139: BBB | B139: 2.24
A140: BBB- | B140: 2.82
A141: BB+ | B141: 3.55
A142: BB | B142: 4.47
... A146: B- | B146: 11.2
A149: SPECIAL ADJUSTMENT PARAMETERS
A150: Occupancy Unknown Adjustment | B150: 1.7
A151: CCJ >6 Years Old Adjustment | B151: 1.075

Sheet LS Parameters
A1: LOSS SEVERITY ADJUSTMENT PARAMETERS
A2: S&P Table 78 & 79: Property Type and Regional Adjustments for MVD
A4: PROPERTY TYPE MVD ADJUSTMENTS (S&P Table 78)
A5: Property Type | B5: MVD Adjustment | C5: Notes
A6: House | B6: 0 | C6: Baseline - no adjustment
A7: Flat | B7: 0.05 | C7: +5% MVD for flats (higher volatility)
A8: Bungalow | B8: -0.02 | C8: -2% MVD for bungalows (stable)
A9: Maisonette | B9: 0.03 | C9: +3% MVD for maisonettes
A10: Other | B10: 0.05 | C10: +5% MVD for other property types
A12: REGIONAL MVD ADJUSTMENTS (S&P Table 79 - Optional)
A13: Region | B13: MVD Adjustment | C13: Notes
A14: London | B14: -0.03 | C14: -3% MVD (more liquid market)
A15: South East | B15: -0.02 | C15: -2% MVD
A16: East | B16: -0.01 | C16: -1% MVD
A17: South West | B17: 0 | C17: Baseline
A18: West Midlands | B18: 0.01 | C18: +1% MVD
A19: East Midlands | B19: 0.01 | C19: +1% MVD
A20: North West | B20: 0.02 | C20: +2% MVD
A21: Yorkshire | B21: 0.02 | C21: +2% MVD
A22: North East | B22: 0.03 | C22: +3% MVD (less liquid)
A23: Wales | B23: 0.02 | C23: +2% MVD
A24: Scotland | B24: 0.01 | C24: +1% MVD
A25: Northern Ireland | B25: 0.03 | C25: +3% MVD
A28: FORECLOSURE COSTS
A29: Cost Component | B29: % of Property Value | C29: Notes
A30: Legal & Professional Fees | B30: 0.03 | C30: Solicitors, surveyors, court costs
A31: Maintenance & Repairs | B31: 0.02 | C31: Property upkeep during foreclosure
A32: Sales Costs | B32: 0.02 | C32: Estate agent, marketing
A33: Holding Costs | B33: 0.01 | C33: Utilities, insurance, security
A34: TOTAL Foreclosure Costs | B34: 0.08 | C34: Sum of all components

Sheet BoE Mapping
A1: AR Code | B1: BoE Field Name | C1: S&P Field Name | D1: Conversion Notes
A2: AR3 | B2: Loan Identifier | C2: Loan ID | D2: Direct mapping
A3: AR5 | B3: Originator | C3: Originator | D3: Direct mapping
A4: AR55 | B4: Loan Origination Date | C4: Origination Date | D4: Date format
A5: AR56 | B5: Date of Loan Maturity | C5: Maturity Date | D5: Date format
A6: AR66 | B6: Original Balance | C6: Original Balance | D6: Currency
A7: AR67 | B7: Current Balance | C7: Current Balance | D7: Currency
A8: AR131 | B8: Property Type | C8: Property Type | D8: Code: 1=House, 2=Flat, 3=Bungalow, 4=Maisonette
A9: AR130 | B9: Occupancy Type | C9: Occupancy Status | D9: Code: 1=Owner Occ, 2=BTL, 3=Second Home, 4=Investment
A10: AR107 | B10: Interest Rate Type | C10: Interest Rate Type | D10: Code: 1=Fixed, 2=Variable, 3=Tracker
A11: AR109 | B11: Current Interest Rate | C11: Interest Rate | D11: Percentage
A12: AR69 | B12: Repayment Method | C12: Payment Method | D12: Code: 1=Repayment, 2=IO, 3=Part & Part
... A30: AR173 | B30: Performance Arrangement | C30: Performance Arrangement | D30: Code: 1,2=Yes, other=No

Sheet Loan Tape (BoE)
A1: LOAN TAPE - BANK OF ENGLAND PRA110 FORMAT (INPUT SHEET)
A2: Enter loan data in yellow cells using Bank of England field codes and values
A3: AR3 | B3: AR5 | C3: AR131 | D3: AR66 | E3: AR136 | F3: AR143 | G3: AR128 | H3: AR129 | I3: AR135 | J3: AR141 | K3: AR55 | L3: AR56 | M3: AR67 | N3: AR130 | O3: AR109 | P3: AR69 | Q3: AR84 | R3: AR59 | S3: AR60 | T3: AR105 | U3: AR22 | V3: AR23 | W3: AR21 | X3: AR27 | Y3: AR26 | Z3: AR28 | AA3: AR73 | AB3: AR31 | AC3: AR33 | AD3: AR35 | AE3: AR36 | AF3: AR47 | AG3: AR166 | AH3: AR154 | AI3: AR156 | AJ3: AR169 | AK3: AR170 | AL3: AR167 | AM3: AR168 | AN3: AR107 | AO3: AR173
A4: Loan ID | B4: Originator | C4: Property Type | D4: Original Balance | E4: Orig Property Val | F4: Curr Property Val | G4: Region | H4: Postcode | I4: Orig LTV % | J4: Curr LTV % | K4: Orig Date | L4: Maturity Date | M4: Current Balance | N4: Occupancy | O4: Interest Rate | P4: Payment Method | Q4: Lien | R4: Purpose | S4: Shared Own | T4: Help to Buy | U4: FTB | V4: Right to Buy | W4: Employment | X4: Income Verif | Y4: Primary Income | Z4: Secondary Income | AA4: DTI | AB4: CCJ Sat | AC4: CCJ Unsat | AD4: CCJ Date | AE4: Bankruptcy | AF4: Prior Repos | AG4: Account Status | AH4: Rental Income | AI4: DSCR | AJ4: Arrears Bal | AK4: Mths Arrears | AL4: Date Last Curr | AM4: Date Last Arr | AN4: Rate Type | AO4: Perf Arrange | AP4: BV85 | AQ4: BV90 | AR4: BV91
A5: Loan ID | B5: Current Balance (£) | C5: Original Balance (£) | D5: Current Property Value (£) | E5: Original Property Value (£) | F5: Origination Date | G5: Maturity Date | H5: Current Interest Rate (%) | I5: Property Type (1-4) | J5: Region | K5: Postcode | L5: Occupancy Status (1-4) | M5: Loan Purpose (1-4) | N5: Payment Method (1-3) | O5: Right to Buy (1-2) | P5: Shared Ownership (1-2) | Q5: Help to Buy (1-2) | R5: Borrower 1 Income (£) | S5: Borrower 2 Income (£) | T5: Number of Borrowers (1-2) | U5: Employ Status Borr1 (1-4) | V5: Employ Status Borr2 (1-4) | W5: Credit Score Borr1 | X5: Credit Score Borr2 | Y5: CCJ Count Borr1 | Z5: CCJ Count Borr2 | AA5: CCJ Value Borr1 (£) | AB5: CCJ Value Borr2 (£) | AC5: CCJ Date Borr1 | AD5: CCJ Date Borr2 | AE5: Arrears Balance (£) | AF5: Bankruptcy Flag (1-2) | AG5: Bankruptcy Date | AH5: IVA Flag (1-2) | AI5: Prior Repossession (1-2) | AJ5: Self-Certified (1-2) | AK5: First Time Buyer (1-2) | AL5: Payment Shock (1-2) | AM5: Reperforming (1-2) | AN5: Date Last 90+ dpd | AO5: Lien Position (1/2/3+) | AP5: Valuation Method (1-3) | AQ5: Commercial Property (1-2) | AR5: Rental Income Annual (£)

Sheet Loan Tape (S&P)
A1: LOAN TAPE - S&P FORMAT (AUTO-CONVERTED FROM BoE)
A2: Auto-populated from Loan Tape (BoE) using conversion formulas - DO NOT EDIT
A3: AR3 | B3: AR5 | C3: AR131 | D3: AR66 | E3: AR136 | F3: AR143 | G3: AR128 | H3: AR129 | I3: AR135 | J3: AR141 | K3: AR55 | L3: AR56 | M3: AR67 | N3: AR130 | O3: AR109 | P3: AR69 | Q3: AR84 | R3: AR59 | S3: AR60 | T3: AR105 | U3: AR22 | V3: AR23 | W3: AR21 | X3: AR27 | Y3: AR26 | Z3: AR28 | AA3: AR19 | AC3: AR73 | AD3: AR31 | AE3: AR33 | AF3: AR35 | AH3: AR36 | AI3: AR47 | AJ3: AR166 | AK3: AR154 | AL3: AR156 | AM3: AR169 | AN3: AR170 | AO3: AR167 | AP3: AR168 | AQ3: AR107 | AR3: AR173
A4: Loan Identifier | B4: Originator | C4: Property Type | D4: Original Balance | E4: Original Property Value | F4: Current Property Value | G4: Geographic Region | H4: Property Postcode | I4: Original LTV % | J4: Current LTV % | K4: Origination Date | L4: Maturity Date | M4: Current Balance | N4: Occupancy Type | O4: Interest Rate % | P4: Payment Method | Q4: Lien Position | R4: Loan Purpose | S4: Shared Ownership | T4: Help to Buy | U4: First Time Buyer | V4: Right to Buy | W4: Employment Status | X4: Income Verification | Y4: Primary Income | Z4: Secondary Income | AA4: Number of Debtors | AC4: Debt to Income | AD4: CCJ Satisfied | AE4: CCJ Unsatisfied | AF4: Last CCJ Date | AH4: Bankruptcy/IVA | AI4: Prior Repossession | AJ4: Account Status | AK4: Rental Income | AL4: DSCR | AM4: Arrears Balance | AN4: Months in Arrears | AO4: Date Last Current | AP4: Date Last in Arrears | AQ4: Interest Rate Type | AR4: Performance Arrangement
A5: ='Loan Tape (BoE)'!A6 | B5: =IFERROR(INDEX('FF Adj Parameters'!$A$89:$B$92,MATCH('Loan Tape (BoE)'!C5,INDEX('FF Adj Parameters'!$A$89:$B$92,,1),0),2),"Unknown") | C5: ='Loan Tape (BoE)'!C6 | D5: ='Loan Tape (BoE)'!D6 | E5: ='Loan Tape (BoE)'!E6 | F5: ='Loan Tape (BoE)'!F6 | G5: ='Loan Tape (BoE)'!G6 | H5: ='Loan Tape (BoE)'!H6/100 | I5: =IFERROR(IFS('Loan Tape (BoE)'!I6=1,"House",'Loan Tape (BoE)'!I6=2,"Flat",'Loan Tape (BoE)'!I6=3,"Bungalow",'Loan Tape (BoE)'!I6=4,"Maisonette"),"") | J5: ='Loan Tape (BoE)'!J6 | K5: ='Loan Tape (BoE)'!K6 | L5: =IFERROR(IFS('Loan Tape (BoE)'!L6=1,"Owner Occupied",'Loan Tape (BoE)'!L6=2,"BTL",'Loan Tape (BoE)'!L6=3,"Second Home",'Loan Tape (BoE)'!L6=4,"Investment"),"") | M5: =IFERROR(IFS('Loan Tape (BoE)'!M6=1,"Purchase",'Loan Tape (BoE)'!M6=2,"Remortgage",OR('Loan Tape (BoE)'!M6=3,'Loan Tape (BoE)'!M6=4),"Cash-out"),"") | N5: =IFERROR(INDEX('FF Adj Parameters'!$A$96:$B$99,MATCH('Loan Tape (BoE)'!R5,INDEX('FF Adj Parameters'!$A$96:$B$99,,1),0),2),"Unknown") | O5: =IF('Loan Tape (BoE)'!O6=1,"Yes","No") | P5: =IF('Loan Tape (BoE)'!P5=1,"Yes",IF('Loan Tape (BoE)'!P5=0,"No","")) | Q5: =IF('Loan Tape (BoE)'!Q5=1,"Yes",IF('Loan Tape (BoE)'!Q5=0,"No","")) | R5: =IF('Loan Tape (BoE)'!R5=1,"Yes",IF('Loan Tape (BoE)'!R5=0,"No","")) | S5: =IF('Loan Tape (BoE)'!S5=1,"Yes",IF('Loan Tape (BoE)'!S5=0,"No","")) | T5: =IF('Loan Tape (BoE)'!T5=1,"Yes",IF('Loan Tape (BoE)'!T5=0,"No","")) | U5: =R5+S5 | V5: =IFERROR(IFS('Loan Tape (BoE)'!U6=1,"Employed",'Loan Tape (BoE)'!U6=2,"Self-Employed",'Loan Tape (BoE)'!U6=3,"Unemployed",'Loan Tape (BoE)'!U6=4,"Retired"),"") | W5: =IFERROR(IFS('Loan Tape (BoE)'!V6=1,"Employed",'Loan Tape (BoE)'!V6=2,"Self-Employed",'Loan Tape (BoE)'!V6=3,"Unemployed",'Loan Tape (BoE)'!V6=4,"Retired"),"") | X5: =IF(OR(V5="Self-Employed",W5="Self-Employed"),"Yes","No") | Y5: ='Loan Tape (BoE)'!W6 | Z5: ='Loan Tape (BoE)'!X6 | AA5: =IF(T5=1,Y5,MIN(Y5,Z5)) | AB5: ='Loan Tape (BoE)'!Y6 | AC5: ='Loan Tape (BoE)'!Z6 | AD5: =AB5+AC5 | AE5: ='Loan Tape (BoE)'!AA6 | AF5: ='Loan Tape (BoE)'!AB6 | AG5: =AE5+AF5 | AH5: =MAX('Loan Tape (BoE)'!AC6,'Loan Tape (BoE)'!AD6) | AI5: ='Loan Tape (BoE)'!AE6 | AJ5: =B5*H5/12 | AK5: =IF(AJ5>0,AI5/AJ5,0) | AL5: =IF('Loan Tape (BoE)'!AF6=1,"Yes","No") | AM5: =IF('Loan Tape (BoE)'!AH6=1,"Yes","No") | AN5: =IF('Loan Tape (BoE)'!AI6=1,"Yes","No") | AO5: =IF('Loan Tape (BoE)'!AJ6=1,"Yes","No") | AP5: =IF(OR('Loan Tape (BoE)'!AQ5=1,'Loan Tape (BoE)'!AQ5=2),"Yes",IF('Loan Tape (BoE)'!AQ5=0,"No","")) | AQ5: =IF('Loan Tape (BoE)'!BV49_5<>"",'Loan Tape (BoE)'!BV49_5,"") | AR5: =IF('Loan Tape (BoE)'!BV50_5<>"",'Loan Tape (BoE)'!BV50_5,"") | AS5: =IFERROR(INDEX('FF Adj Parameters'!$A$103:$B$105,MATCH('Loan Tape (BoE)'!P5,INDEX('FF Adj Parameters'!$A$103:$B$105,,1),0),2),"Unknown") | AT5: =IF(N5="Interest Only",M5*O5/12,IF(AND(O5>0,ISNUMBER(O5),ISNUMBER(M5)),ABS(PMT(O5/12,AU5,-M5)),0)) | AU5: =IF(ISNUMBER(L5),MAX(0,(L5-'Control Panel'!$B$10)*12/365.25),0) | AV5: =IF(ISNUMBER(L5),IF(L5>'Control Panel'!$B$10,"Valid","Past Maturity"),"No Date") | AW5: =IF(ISNUMBER(K5),MAX(0,('Control Panel'!$B$10-K5)*12/365.25),0)
A6: ='Loan Tape (BoE)'!A7 | B6: =IFERROR(INDEX('FF Adj Parameters'!$A$89:$B$92,MATCH('Loan Tape (BoE)'!C6,INDEX('FF Adj Parameters'!$A$89:$B$92,,1),0),2),"Unknown") | C6: ='Loan Tape (BoE)'!C7 | D6: ='Loan Tape (BoE)'!D7 | E6: ='Loan Tape (BoE)'!E7 | F6: ='Loan Tape (BoE)'!F7 | G6: ='Loan Tape (BoE)'!G7 | H6: ='Loan Tape (BoE)'!H7/100 | I6: =IFERROR(IFS('Loan Tape (BoE)'!I7=1,"House",'Loan Tape (BoE)'!I7=2,"Flat",'Loan Tape (BoE)'!I7=3,"Bungalow",'Loan Tape (BoE)'!I7=4,"Maisonette"),"") | J6: ='Loan Tape (BoE)'!J7 | K6: ='Loan Tape (BoE)'!K7 | L6: =IFERROR(IFS('Loan Tape (BoE)'!L7=1,"Owner Occupied",'Loan Tape (BoE)'!L7=2,"BTL",'Loan Tape (BoE)'!L7=3,"Second Home",'Loan Tape (BoE)'!L7=4,"Investment"),"") | M6: =IFERROR(IFS('Loan Tape (BoE)'!M7=1,"Purchase",'Loan Tape (BoE)'!M7=2,"Remortgage",OR('Loan Tape (BoE)'!M7=3,'Loan Tape (BoE)'!M7=4),"Cash-out"),"") | N6: =IFERROR(INDEX('FF Adj Parameters'!$A$96:$B$99,MATCH('Loan Tape (BoE)'!R6,INDEX('FF Adj Parameters'!$A$96:$B$99,,1),0),2),"Unknown") | O6: =IF('Loan Tape (BoE)'!O7=1,"Yes","No") | P6: =IF('Loan Tape (BoE)'!P6=1,"Yes",IF('Loan Tape (BoE)'!P6=0,"No","")) | Q6: =IF('Loan Tape (BoE)'!Q6=1,"Yes",IF('Loan Tape (BoE)'!Q6=0,"No","")) | R6: =IF('Loan Tape (BoE)'!R6=1,"Yes",IF('Loan Tape (BoE)'!R6=0,"No","")) | S6: =IF('Loan Tape (BoE)'!S6=1,"Yes",IF('Loan Tape (BoE)'!S6=0,"No","")) | T6: =IF('Loan Tape (BoE)'!T6=1,"Yes",IF('Loan Tape (BoE)'!T6=0,"No","")) | U6: =R6+S6 | V6: =IFERROR(IFS('Loan Tape (BoE)'!U7=1,"Employed",'Loan Tape (BoE)'!U7=2,"Self-Employed",'Loan Tape (BoE)'!U7=3,"Unemployed",'Loan Tape (BoE)'!U7=4,"Retired"),"") | W6: =IFERROR(IFS('Loan Tape (BoE)'!V7=1,"Employed",'Loan Tape (BoE)'!V7=2,"Self-Employed",'Loan Tape (BoE)'!V7=3,"Unemployed",'Loan Tape (BoE)'!V7=4,"Retired"),"") | X6: =IF(OR(V6="Self-Employed",W6="Self-Employed"),"Yes","No") | Y6: ='Loan Tape (BoE)'!W7 | Z6: ='Loan Tape (BoE)'!X7 | AA6: =IF(T6=1,Y6,MIN(Y6,Z6)) | AB6: ='Loan Tape (BoE)'!Y7 | AC6: ='Loan Tape (BoE)'!Z7 | AD6: =AB6+AC6 | AE6: ='Loan Tape (BoE)'!AA7 | AF6: ='Loan Tape (BoE)'!AB7 | AG6: =AE6+AF6 | AH6: =MAX('Loan Tape (BoE)'!AC7,'Loan Tape (BoE)'!AD7) | AI6: ='Loan Tape (BoE)'!AE7 | AJ6: =B6*H6/12 | AK6: =IF(AJ6>0,AI6/AJ6,0) | AL6: =IF('Loan Tape (BoE)'!AF7=1,"Yes","No") | AM6: =IF('Loan Tape (BoE)'!AH7=1,"Yes","No") | AN6: =IF('Loan Tape (BoE)'!AI7=1,"Yes","No") | AO6: =IF('Loan Tape (BoE)'!AJ7=1,"Yes","No") | AP6: =IF(OR('Loan Tape (BoE)'!AQ6=1,'Loan Tape (BoE)'!AQ6=2),"Yes",IF('Loan Tape (BoE)'!AQ6=0,"No","")) | AQ6: =IF('Loan Tape (BoE)'!BV49_6<>"",'Loan Tape (BoE)'!BV49_6,"") | AR6: =IF('Loan Tape (BoE)'!BV60_6<>"",'Loan Tape (BoE)'!BV50_6,"") | AS6: =IFERROR(INDEX('FF Adj Parameters'!$A$103:$B$106,MATCH('Loan Tape (BoE)'!P6,INDEX('FF Adj Parameters'!$A$103:$B$106,,1),0),2),"Unknown") | AT6: =IF(N6="Interest Only",M5*O5/12,IF(AND(O5>0,ISNUMBER(O5),ISNUMBER(M5)),ABS(PMT(O5/12,AU5,-M5)),0)) | AU6: =IF(ISNUMBER(L6),MAX(0,(L5-'Control Panel'!$B$10)*12/365.25),0) | AV6: =IF(ISNUMBER(L6),IF(L5>'Control Panel'!$B$10,"Valid","Past Maturity"),"No Date") | AW6: =IF(ISNUMBER(K6),MAX(0,('Control Panel'!$B$10-K5)*12/365.25),0)
A7: ='Loan Tape (BoE)'!A8 | B7: =IFERROR(INDEX('FF Adj Parameters'!$A$89:$B$92,MATCH('Loan Tape (BoE)'!C7,INDEX('FF Adj Parameters'!$A$89:$B$92,,1),0),2),"Unknown") | C7: ='Loan Tape (BoE)'!C8 | D7: ='Loan Tape (BoE)'!D8 | E7: ='Loan Tape (BoE)'!E8 | F7: ='Loan Tape (BoE)'!F8 | G7: ='Loan Tape (BoE)'!G8 | H7: ='Loan Tape (BoE)'!H8/100 | I7: =IFERROR(IFS('Loan Tape (BoE)'!I8=1,"House",'Loan Tape (BoE)'!I8=2,"Flat",'Loan Tape (BoE)'!I8=3,"Bungalow",'Loan Tape (BoE)'!I8=4,"Maisonette"),"") | J7: ='Loan Tape (BoE)'!J8 | K7: ='Loan Tape (BoE)'!K8 | L7: =IFERROR(IFS('Loan Tape (BoE)'!L8=1,"Owner Occupied",'Loan Tape (BoE)'!L8=2,"BTL",'Loan Tape (BoE)'!L8=3,"Second Home",'Loan Tape (BoE)'!L8=4,"Investment"),"") | M7: =IFERROR(IFS('Loan Tape (BoE)'!M8=1,"Purchase",'Loan Tape (BoE)'!M8=2,"Remortgage",OR('Loan Tape (BoE)'!M8=3,'Loan Tape (BoE)'!M8=4),"Cash-out"),"") | N7: =IFERROR(INDEX('FF Adj Parameters'!$A$96:$B$99,MATCH('Loan Tape (BoE)'!R7,INDEX('FF Adj Parameters'!$A$96:$B$99,,1),0),2),"Unknown") | O7: =IF('Loan Tape (BoE)'!O8=1,"Yes","No") | P7: =IF('Loan Tape (BoE)'!P7=1,"Yes",IF('Loan Tape (BoE)'!P7=0,"No","")) | Q7: =IF('Loan Tape (BoE)'!Q7=1,"Yes",IF('Loan Tape (BoE)'!Q7=0,"No","")) | R7: =IF('Loan Tape (BoE)'!R7=1,"Yes",IF('Loan Tape (BoE)'!R7=0,"No","")) | S7: =IF('Loan Tape (BoE)'!S7=1,"Yes",IF('Loan Tape (BoE)'!S7=0,"No","")) | T7: =IF('Loan Tape (BoE)'!T7=1,"Yes",IF('Loan Tape (BoE)'!T7=0,"No","")) | U7: =R7+S7 | V7: =IFERROR(IFS('Loan Tape (BoE)'!U8=1,"Employed",'Loan Tape (BoE)'!U8=2,"Self-Employed",'Loan Tape (BoE)'!U8=3,"Unemployed",'Loan Tape (BoE)'!U8=4,"Retired"),"") | W7: =IFERROR(IFS('Loan Tape (BoE)'!V8=1,"Employed",'Loan Tape (BoE)'!V8=2,"Self-Employed",'Loan Tape (BoE)'!V8=3,"Unemployed",'Loan Tape (BoE)'!V8=4,"Retired"),"") | X7: =IF(OR(V7="Self-Employed",W7="Self-Employed"),"Yes","No") | Y7: ='Loan Tape (BoE)'!W8 | Z7: ='Loan Tape (BoE)'!X8 | AA7: =IF(T7=1,Y7,MIN(Y7,Z7)) | AB7: ='Loan Tape (BoE)'!Y8 | AC7: ='Loan Tape (BoE)'!Z8 | AD7: =AB7+AC7 | AE7: ='Loan Tape (BoE)'!AA8 | AF7: ='Loan Tape (BoE)'!AB8 | AG7: =AE7+AF7 | AH7: =MAX('Loan Tape (BoE)'!AC8,'Loan Tape (BoE)'!AD8) | AI7: ='Loan Tape (BoE)'!AE8 | AJ7: =B7*H7/12 | AK7: =IF(AJ7>0,AI7/AJ7,0) | AL7: =IF('Loan Tape (BoE)'!AF8=1,"Yes","No") | AM7: =IF('Loan Tape (BoE)'!AH8=1,"Yes","No") | AN7: =IF('Loan Tape (BoE)'!AI8=1,"Yes","No") | AO7: =IF('Loan Tape (BoE)'!AJ8=1,"Yes","No") | AP7: =IF(OR('Loan Tape (BoE)'!AQ7=1,'Loan Tape (BoE)'!AQ7=2),"Yes",IF('Loan Tape (BoE)'!AQ7=0,"No","")) | AQ7: =IF('Loan Tape (BoE)'!BV49_7<>"",'Loan Tape (BoE)'!BV49_7,"") | AR7: =IF('Loan Tape (BoE)'!BV70_7<>"",'Loan Tape (BoE)'!BV50_7,"") | AS7: =IFERROR(INDEX('FF Adj Parameters'!$A$103:$B$107,MATCH('Loan Tape (BoE)'!P7,INDEX('FF Adj Parameters'!$A$103:$B$107,,1),0),2),"Unknown") | AT7: =IF(N7="Interest Only",M5*O5/12,IF(AND(O5>0,ISNUMBER(O5),ISNUMBER(M5)),ABS(PMT(O5/12,AU5,-M5)),0)) | AU7: =IF(ISNUMBER(L7),MAX(0,(L5-'Control Panel'!$B$10)*12/365.25),0) | AV7: =IF(ISNUMBER(L7),IF(L5>'Control Panel'!$B$10,"Valid","Past Maturity"),"No Date") | AW7: =IF(ISNUMBER(K7),MAX(0,('Control Panel'!$B$10-K5)*12/365.25),0)
A8: ='Loan Tape (BoE)'!A9 | B8: =IFERROR(INDEX('FF Adj Parameters'!$A$89:$B$92,MATCH('Loan Tape (BoE)'!C8,INDEX('FF Adj Parameters'!$A$89:$B$92,,1),0),2),"Unknown") | C8: ='Loan Tape (BoE)'!C9 | D8: ='Loan Tape (BoE)'!D9 | E8: ='Loan Tape (BoE)'!E9 | F8: ='Loan Tape (BoE)'!F9 | G8: ='Loan Tape (BoE)'!G9 | H8: ='Loan Tape (BoE)'!H9/100 | I8: =IFERROR(IFS('Loan Tape (BoE)'!I9=1,"House",'Loan Tape (BoE)'!I9=2,"Flat",'Loan Tape (BoE)'!I9=3,"Bungalow",'Loan Tape (BoE)'!I9=4,"Maisonette"),"") | J8: ='Loan Tape (BoE)'!J9 | K8: ='Loan Tape (BoE)'!K9 | L8: =IFERROR(IFS('Loan Tape (BoE)'!L9=1,"Owner Occupied",'Loan Tape (BoE)'!L9=2,"BTL",'Loan Tape (BoE)'!L9=3,"Second Home",'Loan Tape (BoE)'!L9=4,"Investment"),"") | M8: =IFERROR(IFS('Loan Tape (BoE)'!M9=1,"Purchase",'Loan Tape (BoE)'!M9=2,"Remortgage",OR('Loan Tape (BoE)'!M9=3,'Loan Tape (BoE)'!M9=4),"Cash-out"),"") | N8: =IFERROR(INDEX('FF Adj Parameters'!$A$96:$B$99,MATCH('Loan Tape (BoE)'!R8,INDEX('FF Adj Parameters'!$A$96:$B$99,,1),0),2),"Unknown") | O8: =IF('Loan Tape (BoE)'!O9=1,"Yes","No") | P8: =IF('Loan Tape (BoE)'!P8=1,"Yes",IF('Loan Tape (BoE)'!P8=0,"No","")) | Q8: =IF('Loan Tape (BoE)'!Q8=1,"Yes",IF('Loan Tape (BoE)'!Q8=0,"No","")) | R8: =IF('Loan Tape (BoE)'!R8=1,"Yes",IF('Loan Tape (BoE)'!R8=0,"No","")) | S8: =IF('Loan Tape (BoE)'!S8=1,"Yes",IF('Loan Tape (BoE)'!S8=0,"No","")) | T8: =IF('Loan Tape (BoE)'!T8=1,"Yes",IF('Loan Tape (BoE)'!T8=0,"No","")) | U8: =R8+S8 | V8: =IFERROR(IFS('Loan Tape (BoE)'!U9=1,"Employed",'Loan Tape (BoE)'!U9=2,"Self-Employed",'Loan Tape (BoE)'!U9=3,"Unemployed",'Loan Tape (BoE)'!U9=4,"Retired"),"") | W8: =IFERROR(IFS('Loan Tape (BoE)'!V9=1,"Employed",'Loan Tape (BoE)'!V9=2,"Self-Employed",'Loan Tape (BoE)'!V9=3,"Unemployed",'Loan Tape (BoE)'!V9=4,"Retired"),"") | X8: =IF(OR(V8="Self-Employed",W8="Self-Employed"),"Yes","No") | Y8: ='Loan Tape (BoE)'!W9 | Z8: ='Loan Tape (BoE)'!X9 | AA8: =IF(T8=1,Y8,MIN(Y8,Z8)) | AB8: ='Loan Tape (BoE)'!Y9 | AC8: ='Loan Tape (BoE)'!Z9 | AD8: =AB8+AC8 | AE8: ='Loan Tape (BoE)'!AA9 | AF8: ='Loan Tape (BoE)'!AB9 | AG8: =AE8+AF8 | AH8: =MAX('Loan Tape (BoE)'!AC9,'Loan Tape (BoE)'!AD9) | AI8: ='Loan Tape (BoE)'!AE9 | AJ8: =B8*H8/12 | AK8: =IF(AJ8>0,AI8/AJ8,0) | AL8: =IF('Loan Tape (BoE)'!AF9=1,"Yes","No") | AM8: =IF('Loan Tape (BoE)'!AH9=1,"Yes","No") | AN8: =IF('Loan Tape (BoE)'!AI9=1,"Yes","No") | AO8: =IF('Loan Tape (BoE)'!AJ9=1,"Yes","No") | AP8: =IF(OR('Loan Tape (BoE)'!AQ8=1,'Loan Tape (BoE)'!AQ8=2),"Yes",IF('Loan Tape (BoE)'!AQ8=0,"No","")) | AQ8: =IF('Loan Tape (BoE)'!BV49_8<>"",'Loan Tape (BoE)'!BV49_8,"") | AR8: =IF('Loan Tape (BoE)'!BV80_8<>"",'Loan Tape (BoE)'!BV50_8,"") | AS8: =IFERROR(INDEX('FF Adj Parameters'!$A$103:$B$108,MATCH('Loan Tape (BoE)'!P8,INDEX('FF Adj Parameters'!$A$103:$B$108,,1),0),2),"Unknown") | AT8: =IF(N8="Interest Only",M5*O5/12,IF(AND(O5>0,ISNUMBER(O5),ISNUMBER(M5)),ABS(PMT(O5/12,AU5,-M5)),0)) | AU8: =IF(ISNUMBER(L8),MAX(0,(L5-'Control Panel'!$B$10)*12/365.25),0) | AV8: =IF(ISNUMBER(L8),IF(L5>'Control Panel'!$B$10,"Valid","Past Maturity"),"No Date") | AW8: =IF(ISNUMBER(K8),MAX(0,('Control Panel'!$B$10-K5)*12/365.25),0)
A9: ='Loan Tape (BoE)'!A10 | B9: =IFERROR(INDEX('FF Adj Parameters'!$A$89:$B$92,MATCH('Loan Tape (BoE)'!C9,INDEX('FF Adj Parameters'!$A$89:$B$92,,1),0),2),"Unknown") | C9: ='Loan Tape (BoE)'!C10 | D9: ='Loan Tape (BoE)'!D10 | E9: ='Loan Tape (BoE)'!E10 | F9: ='Loan Tape (BoE)'!F10 | G9: ='Loan Tape (BoE)'!G10 | H9: ='Loan Tape (BoE)'!H10/100 | I9: =IFERROR(IFS('Loan Tape (BoE)'!I10=1,"House",'Loan Tape (BoE)'!I10=2,"Flat",'Loan Tape (BoE)'!I10=3,"Bungalow",'Loan Tape (BoE)'!I10=4,"Maisonette"),"") | J9: ='Loan Tape (BoE)'!J10 | K9: ='Loan Tape (BoE)'!K10 | L9: =IFERROR(IFS('Loan Tape (BoE)'!L10=1,"Owner Occupied",'Loan Tape (BoE)'!L10=2,"BTL",'Loan Tape (BoE)'!L10=3,"Second Home",'Loan Tape (BoE)'!L10=4,"Investment"),"") | M9: =IFERROR(IFS('Loan Tape (BoE)'!M10=1,"Purchase",'Loan Tape (BoE)'!M10=2,"Remortgage",OR('Loan Tape (BoE)'!M10=3,'Loan Tape (BoE)'!M10=4),"Cash-out"),"") | N9: =IFERROR(INDEX('FF Adj Parameters'!$A$96:$B$99,MATCH('Loan Tape (BoE)'!R9,INDEX('FF Adj Parameters'!$A$96:$B$99,,1),0),2),"Unknown") | O9: =IF('Loan Tape (BoE)'!O10=1,"Yes","No") | P9: =IF('Loan Tape (BoE)'!P9=1,"Yes",IF('Loan Tape (BoE)'!P9=0,"No","")) | Q9: =IF('Loan Tape (BoE)'!Q9=1,"Yes",IF('Loan Tape (BoE)'!Q9=0,"No","")) | R9: =IF('Loan Tape (BoE)'!R9=1,"Yes",IF('Loan Tape (BoE)'!R9=0,"No","")) | S9: =IF('Loan Tape (BoE)'!S9=1,"Yes",IF('Loan Tape (BoE)'!S9=0,"No","")) | T9: =IF('Loan Tape (BoE)'!T9=1,"Yes",IF('Loan Tape (BoE)'!T9=0,"No","")) | U9: =R9+S9 | V9: =IFERROR(IFS('Loan Tape (BoE)'!U10=1,"Employed",'Loan Tape (BoE)'!U10=2,"Self-Employed",'Loan Tape (BoE)'!U10=3,"Unemployed",'Loan Tape (BoE)'!U10=4,"Retired"),"") | W9: =IFERROR(IFS('Loan Tape (BoE)'!V10=1,"Employed",'Loan Tape (BoE)'!V10=2,"Self-Employed",'Loan Tape (BoE)'!V10=3,"Unemployed",'Loan Tape (BoE)'!V10=4,"Retired"),"") | X9: =IF(OR(V9="Self-Employed",W9="Self-Employed"),"Yes","No") | Y9: ='Loan Tape (BoE)'!W10 | Z9: ='Loan Tape (BoE)'!X10 | AA9: =IF(T9=1,Y9,MIN(Y9,Z9)) | AB9: ='Loan Tape (BoE)'!Y10 | AC9: ='Loan Tape (BoE)'!Z10 | AD9: =AB9+AC9 | AE9: ='Loan Tape (BoE)'!AA10 | AF9: ='Loan Tape (BoE)'!AB10 | AG9: =AE9+AF9 | AH9: =MAX('Loan Tape (BoE)'!AC10,'Loan Tape (BoE)'!AD10) | AI9: ='Loan Tape (BoE)'!AE10 | AJ9: =B9*H9/12 | AK9: =IF(AJ9>0,AI9/AJ9,0) | AL9: =IF('Loan Tape (BoE)'!AF10=1,"Yes","No") | AM9: =IF('Loan Tape (BoE)'!AH10=1,"Yes","No") | AN9: =IF('Loan Tape (BoE)'!AI10=1,"Yes","No") | AO9: =IF('Loan Tape (BoE)'!AJ10=1,"Yes","No") | AP9: =IF(OR('Loan Tape (BoE)'!AQ9=1,'Loan Tape (BoE)'!AQ9=2),"Yes",IF('Loan Tape (BoE)'!AQ9=0,"No","")) | AQ9: =IF('Loan Tape (BoE)'!BV49_9<>"",'Loan Tape (BoE)'!BV49_9,"") | AR9: =IF('Loan Tape (BoE)'!BV90_9<>"",'Loan Tape (BoE)'!BV50_9,"") | AS9: =IFERROR(INDEX('FF Adj Parameters'!$A$103:$B$109,MATCH('Loan Tape (BoE)'!P9,INDEX('FF Adj Parameters'!$A$103:$B$109,,1),0),2),"Unknown") | AT9: =IF(N9="Interest Only",M5*O5/12,IF(AND(O5>0,ISNUMBER(O5),ISNUMBER(M5)),ABS(PMT(O5/12,AU5,-M5)),0)) | AU9: =IF(ISNUMBER(L9),MAX(0,(L5-'Control Panel'!$B$10)*12/365.25),0) | AV9: =IF(ISNUMBER(L9),IF(L5>'Control Panel'!$B$10,"Valid","Past Maturity"),"No Date") | AW9: =IF(ISNUMBER(K9),MAX(0,('Control Panel'!$B$10-K5)*12/365.25),0)
A10: ='Loan Tape (BoE)'!A11 | B10: =IFERROR(INDEX('FF Adj Parameters'!$A$89:$B$92,MATCH('Loan Tape (BoE)'!C10,INDEX('FF Adj Parameters'!$A$89:$B$92,,1),0),2),"Unknown") | C10: ='Loan Tape (BoE)'!C11 | D10: ='Loan Tape (BoE)'!D11 | E10: ='Loan Tape (BoE)'!E11 | F10: ='Loan Tape (BoE)'!F11 | G10: ='Loan Tape (BoE)'!G11 | H10: ='Loan Tape (BoE)'!H11/100 | I10: =IFERROR(IFS('Loan Tape (BoE)'!I11=1,"House",'Loan Tape (BoE)'!I11=2,"Flat",'Loan Tape (BoE)'!I11=3,"Bungalow",'Loan Tape (BoE)'!I11=4,"Maisonette"),"") | J10: ='Loan Tape (BoE)'!J11 | K10: ='Loan Tape (BoE)'!K11 | L10: =IFERROR(IFS('Loan Tape (BoE)'!L11=1,"Owner Occupied",'Loan Tape (BoE)'!L11=2,"BTL",'Loan Tape (BoE)'!L11=3,"Second Home",'Loan Tape (BoE)'!L11=4,"Investment"),"") | M10: =IFERROR(IFS('Loan Tape (BoE)'!M11=1,"Purchase",'Loan Tape (BoE)'!M11=2,"Remortgage",OR('Loan Tape (BoE)'!M11=3,'Loan Tape (BoE)'!M11=4),"Cash-out"),"") | N10: =IFERROR(INDEX('FF Adj Parameters'!$A$96:$B$99,MATCH('Loan Tape (BoE)'!R10,INDEX('FF Adj Parameters'!$A$96:$B$99,,1),0),2),"Unknown") | O10: =IF('Loan Tape (BoE)'!O11=1,"Yes","No") | P10: =IF('Loan Tape (BoE)'!P10=1,"Yes",IF('Loan Tape (BoE)'!P10=0,"No","")) | Q10: =IF('Loan Tape (BoE)'!Q10=1,"Yes",IF('Loan Tape (BoE)'!Q10=0,"No","")) | R10: =IF('Loan Tape (BoE)'!R10=1,"Yes",IF('Loan Tape (BoE)'!R10=0,"No","")) | S10: =IF('Loan Tape (BoE)'!S10=1,"Yes",IF('Loan Tape (BoE)'!S10=0,"No","")) | T10: =IF('Loan Tape (BoE)'!T10=1,"Yes",IF('Loan Tape (BoE)'!T10=0,"No","")) | U10: =R10+S10 | V10: =IFERROR(IFS('Loan Tape (BoE)'!U11=1,"Employed",'Loan Tape (BoE)'!U11=2,"Self-Employed",'Loan Tape (BoE)'!U11=3,"Unemployed",'Loan Tape (BoE)'!U11=4,"Retired"),"") | W10: =IFERROR(IFS('Loan Tape (BoE)'!V11=1,"Employed",'Loan Tape (BoE)'!V11=2,"Self-Employed",'Loan Tape (BoE)'!V11=3,"Unemployed",'Loan Tape (BoE)'!V11=4,"Retired"),"") | X10: =IF(OR(V10="Self-Employed",W10="Self-Employed"),"Yes","No") | Y10: ='Loan Tape (BoE)'!W11 | Z10: ='Loan Tape (BoE)'!X11 | AA10: =IF(T10=1,Y10,MIN(Y10,Z10)) | AB10: ='Loan Tape (BoE)'!Y11 | AC10: ='Loan Tape (BoE)'!Z11 | AD10: =AB10+AC10 | AE10: ='Loan Tape (BoE)'!AA11 | AF10: ='Loan Tape (BoE)'!AB11 | AG10: =AE10+AF10 | AH10: =MAX('Loan Tape (BoE)'!AC11,'Loan Tape (BoE)'!AD11) | AI10: ='Loan Tape (BoE)'!AE11 | AJ10: =B10*H10/12 | AK10: =IF(AJ10>0,AI10/AJ10,0) | AL10: =IF('Loan Tape (BoE)'!AF11=1,"Yes","No") | AM10: =IF('Loan Tape (BoE)'!AH11=1,"Yes","No") | AN10: =IF('Loan Tape (BoE)'!AI11=1,"Yes","No") | AO10: =IF('Loan Tape (BoE)'!AJ11=1,"Yes","No") | AP10: =IF(OR('Loan Tape (BoE)'!AQ10=1,'Loan Tape (BoE)'!AQ10=2),"Yes",IF('Loan Tape (BoE)'!AQ10=0,"No","")) | AQ10: =IF('Loan Tape (BoE)'!BV49_10<>"",'Loan Tape (BoE)'!BV49_10,"") | AR10: =IF('Loan Tape (BoE)'!BV100_10<>"",'Loan Tape (BoE)'!BV50_10,"") | AS10: =IFERROR(INDEX('FF Adj Parameters'!$A$103:$B$1010,MATCH('Loan Tape (BoE)'!P10,INDEX('FF Adj Parameters'!$A$103:$B$1010,,1),0),2),"Unknown") | AT10: =IF(N10="Interest Only",M5*O5/12,IF(AND(O5>0,ISNUMBER(O5),ISNUMBER(M5)),ABS(PMT(O5/12,AU5,-M5)),0)) | AU10: =IF(ISNUMBER(L10),MAX(0,(L5-'Control Panel'!$B$10)*12/365.25),0) | AV10: =IF(ISNUMBER(L10),IF(L5>'Control Panel'!$B$10,"Valid","Past Maturity"),"No Date") | AW10: =IF(ISNUMBER(K10),MAX(0,('Control Panel'!$B$10-K5)*12/365.25),0)
A11: ='Loan Tape (BoE)'!A12 | B11: =IFERROR(INDEX('FF Adj Parameters'!$A$89:$B$92,MATCH('Loan Tape (BoE)'!C11,INDEX('FF Adj Parameters'!$A$89:$B$92,,1),0),2),"Unknown") | C11: ='Loan Tape (BoE)'!C12 | D11: ='Loan Tape (BoE)'!D12 | E11: ='Loan Tape (BoE)'!E12 | F11: ='Loan Tape (BoE)'!F12 | G11: ='Loan Tape (BoE)'!G12 | H11: ='Loan Tape (BoE)'!H12/100 | I11: =IFERROR(IFS('Loan Tape (BoE)'!I12=1,"House",'Loan Tape (BoE)'!I12=2,"Flat",'Loan Tape (BoE)'!I12=3,"Bungalow",'Loan Tape (BoE)'!I12=4,"Maisonette"),"") | J11: ='Loan Tape (BoE)'!J12 | K11: ='Loan Tape (BoE)'!K12 | L11: =IFERROR(IFS('Loan Tape (BoE)'!L12=1,"Owner Occupied",'Loan Tape (BoE)'!L12=2,"BTL",'Loan Tape (BoE)'!L12=3,"Second Home",'Loan Tape (BoE)'!L12=4,"Investment"),"") | M11: =IFERROR(IFS('Loan Tape (BoE)'!M12=1,"Purchase",'Loan Tape (BoE)'!M12=2,"Remortgage",OR('Loan Tape (BoE)'!M12=3,'Loan Tape (BoE)'!M12=4),"Cash-out"),"") | N11: =IFERROR(INDEX('FF Adj Parameters'!$A$96:$B$99,MATCH('Loan Tape (BoE)'!R11,INDEX('FF Adj Parameters'!$A$96:$B$99,,1),0),2),"Unknown") | O11: =IF('Loan Tape (BoE)'!O12=1,"Yes","No") | P11: =IF('Loan Tape (BoE)'!P11=1,"Yes",IF('Loan Tape (BoE)'!P11=0,"No","")) | Q11: =IF('Loan Tape (BoE)'!Q11=1,"Yes",IF('Loan Tape (BoE)'!Q11=0,"No","")) | R11: =IF('Loan Tape (BoE)'!R11=1,"Yes",IF('Loan Tape (BoE)'!R11=0,"No","")) | S11: =IF('Loan Tape (BoE)'!S11=1,"Yes",IF('Loan Tape (BoE)'!S11=0,"No","")) | T11: =IF('Loan Tape (BoE)'!T11=1,"Yes",IF('Loan Tape (BoE)'!T11=0,"No","")) | U11: =R11+S11 | V11: =IFERROR(IFS('Loan Tape (BoE)'!U12=1,"Employed",'Loan Tape (BoE)'!U12=2,"Self-Employed",'Loan Tape (BoE)'!U12=3,"Unemployed",'Loan Tape (BoE)'!U12=4,"Retired"),"") | W11: =IFERROR(IFS('Loan Tape (BoE)'!V12=1,"Employed",'Loan Tape (BoE)'!V12=2,"Self-Employed",'Loan Tape (BoE)'!V12=3,"Unemployed",'Loan Tape (BoE)'!V12=4,"Retired"),"") | X11: =IF(OR(V11="Self-Employed",W11="Self-Employed"),"Yes","No") | Y11: ='Loan Tape (BoE)'!W12 | Z11: ='Loan Tape (BoE)'!X12 | AA11: =IF(T11=1,Y11,MIN(Y11,Z11)) | AB11: ='Loan Tape (BoE)'!Y12 | AC11: ='Loan Tape (BoE)'!Z12 | AD11: =AB11+AC11 | AE11: ='Loan Tape (BoE)'!AA12 | AF11: ='Loan Tape (BoE)'!AB12 | AG11: =AE11+AF11 | AH11: =MAX('Loan Tape (BoE)'!AC12,'Loan Tape (BoE)'!AD12) | AI11: ='Loan Tape (BoE)'!AE12 | AJ11: =B11*H11/12 | AK11: =IF(AJ11>0,AI11/AJ11,0) | AL11: =IF('Loan Tape (BoE)'!AF12=1,"Yes","No") | AM11: =IF('Loan Tape (BoE)'!AH12=1,"Yes","No") | AN11: =IF('Loan Tape (BoE)'!AI12=1,"Yes","No") | AO11: =IF('Loan Tape (BoE)'!AJ12=1,"Yes","No") | AP11: =IF(OR('Loan Tape (BoE)'!AQ11=1,'Loan Tape (BoE)'!AQ11=2),"Yes",IF('Loan Tape (BoE)'!AQ11=0,"No","")) | AQ11: =IF('Loan Tape (BoE)'!BV49_11<>"",'Loan Tape (BoE)'!BV49_11,"") | AR11: =IF('Loan Tape (BoE)'!BV110_11<>"",'Loan Tape (BoE)'!BV50_11,"") | AS11: =IFERROR(INDEX('FF Adj Parameters'!$A$103:$B$1011,MATCH('Loan Tape (BoE)'!P11,INDEX('FF Adj Parameters'!$A$103:$B$1011,,1),0),2),"Unknown") | AT11: =IF(N11="Interest Only",M5*O5/12,IF(AND(O5>0,ISNUMBER(O5),ISNUMBER(M5)),ABS(PMT(O5/12,AU5,-M5)),0)) | AU11: =IF(ISNUMBER(L11),MAX(0,(L5-'Control Panel'!$B$10)*12/365.25),0) | AV11: =IF(ISNUMBER(L11),IF(L5>'Control Panel'!$B$10,"Valid","Past Maturity"),"No Date") | AW11: =IF(ISNUMBER(K11),MAX(0,('Control Panel'!$B$10-K5)*12/365.25),0)
A12: ='Loan Tape (BoE)'!A13 | B12: =IFERROR(INDEX('FF Adj Parameters'!$A$89:$B$92,MATCH('Loan Tape (BoE)'!C12,INDEX('FF Adj Parameters'!$A$89:$B$92,,1),0),2),"Unknown") | C12: ='Loan Tape (BoE)'!C13 | D12: ='Loan Tape (BoE)'!D13 | E12: ='Loan Tape (BoE)'!E13 | F12: ='Loan Tape (BoE)'!F13 | G12: ='Loan Tape (BoE)'!G13 | H12: ='Loan Tape (BoE)'!H13/100 | I12: =IFERROR(IFS('Loan Tape (BoE)'!I13=1,"House",'Loan Tape (BoE)'!I13=2,"Flat",'Loan Tape (BoE)'!I13=3,"Bungalow",'Loan Tape (BoE)'!I13=4,"Maisonette"),"") | J12: ='Loan Tape (BoE)'!J13 | K12: ='Loan Tape (BoE)'!K13 | L12: =IFERROR(IFS('Loan Tape (BoE)'!L13=1,"Owner Occupied",'Loan Tape (BoE)'!L13=2,"BTL",'Loan Tape (BoE)'!L13=3,"Second Home",'Loan Tape (BoE)'!L13=4,"Investment"),"") | M12: =IFERROR(IFS('Loan Tape (BoE)'!M13=1,"Purchase",'Loan Tape (BoE)'!M13=2,"Remortgage",OR('Loan Tape (BoE)'!M13=3,'Loan Tape (BoE)'!M13=4),"Cash-out"),"") | N12: =IFERROR(INDEX('FF Adj Parameters'!$A$96:$B$99,MATCH('Loan Tape (BoE)'!R12,INDEX('FF Adj Parameters'!$A$96:$B$99,,1),0),2),"Unknown") | O12: =IF('Loan Tape (BoE)'!O13=1,"Yes","No") | P12: =IF('Loan Tape (BoE)'!P12=1,"Yes",IF('Loan Tape (BoE)'!P12=0,"No","")) | Q12: =IF('Loan Tape (BoE)'!Q12=1,"Yes",IF('Loan Tape (BoE)'!Q12=0,"No","")) | R12: =IF('Loan Tape (BoE)'!R12=1,"Yes",IF('Loan Tape (BoE)'!R12=0,"No","")) | S12: =IF('Loan Tape (BoE)'!S12=1,"Yes",IF('Loan Tape (BoE)'!S12=0,"No","")) | T12: =IF('Loan Tape (BoE)'!T12=1,"Yes",IF('Loan Tape (BoE)'!T12=0,"No","")) | U12: =R12+S12 | V12: =IFERROR(IFS('Loan Tape (BoE)'!U13=1,"Employed",'Loan Tape (BoE)'!U13=2,"Self-Employed",'Loan Tape (BoE)'!U13=3,"Unemployed",'Loan Tape (BoE)'!U13=4,"Retired"),"") | W12: =IFERROR(IFS('Loan Tape (BoE)'!V13=1,"Employed",'Loan Tape (BoE)'!V13=2,"Self-Employed",'Loan Tape (BoE)'!V13=3,"Unemployed",'Loan Tape (BoE)'!V13=4,"Retired"),"") | X12: =IF(OR(V12="Self-Employed",W12="Self-Employed"),"Yes","No") | Y12: ='Loan Tape (BoE)'!W13 | Z12: ='Loan Tape (BoE)'!X13 | AA12: =IF(T12=1,Y12,MIN(Y12,Z12)) | AB12: ='Loan Tape (BoE)'!Y13 | AC12: ='Loan Tape (BoE)'!Z13 | AD12: =AB12+AC12 | AE12: ='Loan Tape (BoE)'!AA13 | AF12: ='Loan Tape (BoE)'!AB13 | AG12: =AE12+AF12 | AH12: =MAX('Loan Tape (BoE)'!AC13,'Loan Tape (BoE)'!AD13) | AI12: ='Loan Tape (BoE)'!AE13 | AJ12: =B12*H12/12 | AK12: =IF(AJ12>0,AI12/AJ12,0) | AL12: =IF('Loan Tape (BoE)'!AF13=1,"Yes","No") | AM12: =IF('Loan Tape (BoE)'!AH13=1,"Yes","No") | AN12: =IF('Loan Tape (BoE)'!AI13=1,"Yes","No") | AO12: =IF('Loan Tape (BoE)'!AJ13=1,"Yes","No") | AP12: =IF(OR('Loan Tape (BoE)'!AQ12=1,'Loan Tape (BoE)'!AQ12=2),"Yes",IF('Loan Tape (BoE)'!AQ12=0,"No","")) | AQ12: =IF('Loan Tape (BoE)'!BV49_12<>"",'Loan Tape (BoE)'!BV49_12,"") | AR12: =IF('Loan Tape (BoE)'!BV120_12<>"",'Loan Tape (BoE)'!BV50_12,"") | AS12: =IFERROR(INDEX('FF Adj Parameters'!$A$103:$B$1012,MATCH('Loan Tape (BoE)'!P12,INDEX('FF Adj Parameters'!$A$103:$B$1012,,1),0),2),"Unknown") | AT12: =IF(N12="Interest Only",M5*O5/12,IF(AND(O5>0,ISNUMBER(O5),ISNUMBER(M5)),ABS(PMT(O5/12,AU5,-M5)),0)) | AU12: =IF(ISNUMBER(L12),MAX(0,(L5-'Control Panel'!$B$10)*12/365.25),0) | AV12: =IF(ISNUMBER(L12),IF(L5>'Control Panel'!$B$10,"Valid","Past Maturity"),"No Date") | AW12: =IF(ISNUMBER(K12),MAX(0,('Control Panel'!$B$10-K5)*12/365.25),0)
A13: ='Loan Tape (BoE)'!A14 | B13: =IFERROR(INDEX('FF Adj Parameters'!$A$89:$B$92,MATCH('Loan Tape (BoE)'!C13,INDEX('FF Adj Parameters'!$A$89:$B$92,,1),0),2),"Unknown") | C13: ='Loan Tape (BoE)'!C14 | D13: ='Loan Tape (BoE)'!D14 | E13: ='Loan Tape (BoE)'!E14 | F13: ='Loan Tape (BoE)'!F14 | G13: ='Loan Tape (BoE)'!G14 | H13: ='Loan Tape (BoE)'!H14/100 | I13: =IFERROR(IFS('Loan Tape (BoE)'!I14=1,"House",'Loan Tape (BoE)'!I14=2,"Flat",'Loan Tape (BoE)'!I14=3,"Bungalow",'Loan Tape (BoE)'!I14=4,"Maisonette"),"") | J13: ='Loan Tape (BoE)'!J14 | K13: ='Loan Tape (BoE)'!K14 | L13: =IFERROR(IFS('Loan Tape (BoE)'!L14=1,"Owner Occupied",'Loan Tape (BoE)'!L14=2,"BTL",'Loan Tape (BoE)'!L14=3,"Second Home",'Loan Tape (BoE)'!L14=4,"Investment"),"") | M13: =IFERROR(IFS('Loan Tape (BoE)'!M14=1,"Purchase",'Loan Tape (BoE)'!M14=2,"Remortgage",OR('Loan Tape (BoE)'!M14=3,'Loan Tape (BoE)'!M14=4),"Cash-out"),"") | N13: =IFERROR(INDEX('FF Adj Parameters'!$A$96:$B$99,MATCH('Loan Tape (BoE)'!R13,INDEX('FF Adj Parameters'!$A$96:$B$99,,1),0),2),"Unknown") | O13: =IF('Loan Tape (BoE)'!O14=1,"Yes","No") | P13: =IF('Loan Tape (BoE)'!P13=1,"Yes",IF('Loan Tape (BoE)'!P13=0,"No","")) | Q13: =IF('Loan Tape (BoE)'!Q13=1,"Yes",IF('Loan Tape (BoE)'!Q13=0,"No","")) | R13: =IF('Loan Tape (BoE)'!R13=1,"Yes",IF('Loan Tape (BoE)'!R13=0,"No","")) | S13: =IF('Loan Tape (BoE)'!S13=1,"Yes",IF('Loan Tape (BoE)'!S13=0,"No","")) | T13: =IF('Loan Tape (BoE)'!T13=1,"Yes",IF('Loan Tape (BoE)'!T13=0,"No","")) | U13: =R13+S13 | V13: =IFERROR(IFS('Loan Tape (BoE)'!U14=1,"Employed",'Loan Tape (BoE)'!U14=2,"Self-Employed",'Loan Tape (BoE)'!U14=3,"Unemployed",'Loan Tape (BoE)'!U14=4,"Retired"),"") | W13: =IFERROR(IFS('Loan Tape (BoE)'!V14=1,"Employed",'Loan Tape (BoE)'!V14=2,"Self-Employed",'Loan Tape (BoE)'!V14=3,"Unemployed",'Loan Tape (BoE)'!V14=4,"Retired"),"") | X13: =IF(OR(V13="Self-Employed",W13="Self-Employed"),"Yes","No") | Y13: ='Loan Tape (BoE)'!W14 | Z13: ='Loan Tape (BoE)'!X14 | AA13: =IF(T13=1,Y13,MIN(Y13,Z13)) | AB13: ='Loan Tape (BoE)'!Y14 | AC13: ='Loan Tape (BoE)'!Z14 | AD13: =AB13+AC13 | AE13: ='Loan Tape (BoE)'!AA14 | AF13: ='Loan Tape (BoE)'!AB14 | AG13: =AE13+AF13 | AH13: =MAX('Loan Tape (BoE)'!AC14,'Loan Tape (BoE)'!AD14) | AI13: ='Loan Tape (BoE)'!AE14 | AJ13: =B13*H13/12 | AK13: =IF(AJ13>0,AI13/AJ13,0) | AL13: =IF('Loan Tape (BoE)'!AF14=1,"Yes","No") | AM13: =IF('Loan Tape (BoE)'!AH14=1,"Yes","No") | AN13: =IF('Loan Tape (BoE)'!AI14=1,"Yes","No") | AO13: =IF('Loan Tape (BoE)'!AJ14=1,"Yes","No") | AP13: =IF(OR('Loan Tape (BoE)'!AQ13=1,'Loan Tape (BoE)'!AQ13=2),"Yes",IF('Loan Tape (BoE)'!AQ13=0,"No","")) | AQ13: =IF('Loan Tape (BoE)'!BV49_13<>"",'Loan Tape (BoE)'!BV49_13,"") | AR13: =IF('Loan Tape (BoE)'!BV130_13<>"",'Loan Tape (BoE)'!BV50_13,"") | AS13: =IFERROR(INDEX('FF Adj Parameters'!$A$103:$B$1013,MATCH('Loan Tape (BoE)'!P13,INDEX('FF Adj Parameters'!$A$103:$B$1013,,1),0),2),"Unknown") | AT13: =IF(N13="Interest Only",M5*O5/12,IF(AND(O5>0,ISNUMBER(O5),ISNUMBER(M5)),ABS(PMT(O5/12,AU5,-M5)),0)) | AU13: =IF(ISNUMBER(L13),MAX(0,(L5-'Control Panel'!$B$10)*12/365.25),0) | AV13: =IF(ISNUMBER(L13),IF(L5>'Control Panel'!$B$10,"Valid","Past Maturity"),"No Date") | AW13: =IF(ISNUMBER(K13),MAX(0,('Control Panel'!$B$10-K5)*12/365.25),0)
A14: ='Loan Tape (BoE)'!A15 | B14: =IFERROR(INDEX('FF Adj Parameters'!$A$89:$B$92,MATCH('Loan Tape (BoE)'!C14,INDEX('FF Adj Parameters'!$A$89:$B$92,,1),0),2),"Unknown") | C14: ='Loan Tape (BoE)'!C15 | D14: ='Loan Tape (BoE)'!D15 | E14: ='Loan Tape (BoE)'!E15 | F14: ='Loan Tape (BoE)'!F15 | G14: ='Loan Tape (BoE)'!G15 | H14: ='Loan Tape (BoE)'!H15/100 | I14: =IFERROR(IFS('Loan Tape (BoE)'!I15=1,"House",'Loan Tape (BoE)'!I15=2,"Flat",'Loan Tape (BoE)'!I15=3,"Bungalow",'Loan Tape (BoE)'!I15=4,"Maisonette"),"") | J14: ='Loan Tape (BoE)'!J15 | K14: ='Loan Tape (BoE)'!K15 | L14: =IFERROR(IFS('Loan Tape (BoE)'!L15=1,"Owner Occupied",'Loan Tape (BoE)'!L15=2,"BTL",'Loan Tape (BoE)'!L15=3,"Second Home",'Loan Tape (BoE)'!L15=4,"Investment"),"") | M14: =IFERROR(IFS('Loan Tape (BoE)'!M15=1,"Purchase",'Loan Tape (BoE)'!M15=2,"Remortgage",OR('Loan Tape (BoE)'!M15=3,'Loan Tape (BoE)'!M15=4),"Cash-out"),"") | N14: =IFERROR(INDEX('FF Adj Parameters'!$A$96:$B$99,MATCH('Loan Tape (BoE)'!R14,INDEX('FF Adj Parameters'!$A$96:$B$99,,1),0),2),"Unknown") | O14: =IF('Loan Tape (BoE)'!O15=1,"Yes","No") | P14: =IF('Loan Tape (BoE)'!P14=1,"Yes",IF('Loan Tape (BoE)'!P14=0,"No","")) | Q14: =IF('Loan Tape (BoE)'!Q14=1,"Yes",IF('Loan Tape (BoE)'!Q14=0,"No","")) | R14: =IF('Loan Tape (BoE)'!R14=1,"Yes",IF('Loan Tape (BoE)'!R14=0,"No","")) | S14: =IF('Loan Tape (BoE)'!S14=1,"Yes",IF('Loan Tape (BoE)'!S14=0,"No","")) | T14: =IF('Loan Tape (BoE)'!T14=1,"Yes",IF('Loan Tape (BoE)'!T14=0,"No","")) | U14: =R14+S14 | V14: =IFERROR(IFS('Loan Tape (BoE)'!U15=1,"Employed",'Loan Tape (BoE)'!U15=2,"Self-Employed",'Loan Tape (BoE)'!U15=3,"Unemployed",'Loan Tape (BoE)'!U15=4,"Retired"),"") | W14: =IFERROR(IFS('Loan Tape (BoE)'!V15=1,"Employed",'Loan Tape (BoE)'!V15=2,"Self-Employed",'Loan Tape (BoE)'!V15=3,"Unemployed",'Loan Tape (BoE)'!V15=4,"Retired"),"") | X14: =IF(OR(V14="Self-Employed",W14="Self-Employed"),"Yes","No") | Y14: ='Loan Tape (BoE)'!W15 | Z14: ='Loan Tape (BoE)'!X15 | AA14: =IF(T14=1,Y14,MIN(Y14,Z14)) | AB14: ='Loan Tape (BoE)'!Y15 | AC14: ='Loan Tape (BoE)'!Z15 | AD14: =AB14+AC14 | AE14: ='Loan Tape (BoE)'!AA15 | AF14: ='Loan Tape (BoE)'!AB15 | AG14: =AE14+AF14 | AH14: =MAX('Loan Tape (BoE)'!AC15,'Loan Tape (BoE)'!AD15) | AI14: ='Loan Tape (BoE)'!AE15 | AJ14: =B14*H14/12 | AK14: =IF(AJ14>0,AI14/AJ14,0) | AL14: =IF('Loan Tape (BoE)'!AF15=1,"Yes","No") | AM14: =IF('Loan Tape (BoE)'!AH15=1,"Yes","No") | AN14: =IF('Loan Tape (BoE)'!AI15=1,"Yes","No") | AO14: =IF('Loan Tape (BoE)'!AJ15=1,"Yes","No") | AP14: =IF(OR('Loan Tape (BoE)'!AQ14=1,'Loan Tape (BoE)'!AQ14=2),"Yes",IF('Loan Tape (BoE)'!AQ14=0,"No","")) | AQ14: =IF('Loan Tape (BoE)'!BV49_14<>"",'Loan Tape (BoE)'!BV49_14,"") | AR14: =IF('Loan Tape (BoE)'!BV140_14<>"",'Loan Tape (BoE)'!BV50_14,"") | AS14: =IFERROR(INDEX('FF Adj Parameters'!$A$103:$B$1014,MATCH('Loan Tape (BoE)'!P14,INDEX('FF Adj Parameters'!$A$103:$B$1014,,1),0),2),"Unknown") | AT14: =IF(N14="Interest Only",M5*O5/12,IF(AND(O5>0,ISNUMBER(O5),ISNUMBER(M5)),ABS(PMT(O5/12,AU5,-M5)),0)) | AU14: =IF(ISNUMBER(L14),MAX(0,(L5-'Control Panel'!$B$10)*12/365.25),0) | AV14: =IF(ISNUMBER(L14),IF(L5>'Control Panel'!$B$10,"Valid","Past Maturity"),"No Date") | AW14: =IF(ISNUMBER(K14),MAX(0,('Control Panel'!$B$10-K5)*12/365.25),0)
A15: ='Loan Tape (BoE)'!A16 | B15: =IFERROR(INDEX('FF Adj Parameters'!$A$89:$B$92,MATCH('Loan Tape (BoE)'!C15,INDEX('FF Adj Parameters'!$A$89:$B$92,,1),0),2),"Unknown") | C15: ='Loan Tape (BoE)'!C16 | D15: ='Loan Tape (BoE)'!D16 | E15: ='Loan Tape (BoE)'!E16 | F15: ='Loan Tape (BoE)'!F16 | G15: ='Loan Tape (BoE)'!G16 | H15: ='Loan Tape (BoE)'!H16/100 | I15: =IFERROR(IFS('Loan Tape (BoE)'!I16=1,"House",'Loan Tape (BoE)'!I16=2,"Flat",'Loan Tape (BoE)'!I16=3,"Bungalow",'Loan Tape (BoE)'!I16=4,"Maisonette"),"") | J15: ='Loan Tape (BoE)'!J16 | K15: ='Loan Tape (BoE)'!K16 | L15: =IFERROR(IFS('Loan Tape (BoE)'!L16=1,"Owner Occupied",'Loan Tape (BoE)'!L16=2,"BTL",'Loan Tape (BoE)'!L16=3,"Second Home",'Loan Tape (BoE)'!L16=4,"Investment"),"") | M15: =IFERROR(IFS('Loan Tape (BoE)'!M16=1,"Purchase",'Loan Tape (BoE)'!M16=2,"Remortgage",OR('Loan Tape (BoE)'!M16=3,'Loan Tape (BoE)'!M16=4),"Cash-out"),"") | N15: =IFERROR(INDEX('FF Adj Parameters'!$A$96:$B$99,MATCH('Loan Tape (BoE)'!R15,INDEX('FF Adj Parameters'!$A$96:$B$99,,1),0),2),"Unknown") | O15: =IF('Loan Tape (BoE)'!O16=1,"Yes","No") | P15: =IF('Loan Tape (BoE)'!P15=1,"Yes",IF('Loan Tape (BoE)'!P15=0,"No","")) | Q15: =IF('Loan Tape (BoE)'!Q15=1,"Yes",IF('Loan Tape (BoE)'!Q15=0,"No","")) | R15: =IF('Loan Tape (BoE)'!R15=1,"Yes",IF('Loan Tape (BoE)'!R15=0,"No","")) | S15: =IF('Loan Tape (BoE)'!S15=1,"Yes",IF('Loan Tape (BoE)'!S15=0,"No","")) | T15: =IF('Loan Tape (BoE)'!T15=1,"Yes",IF('Loan Tape (BoE)'!T15=0,"No","")) | U15: =R15+S15 | V15: =IFERROR(IFS('Loan Tape (BoE)'!U16=1,"Employed",'Loan Tape (BoE)'!U16=2,"Self-Employed",'Loan Tape (BoE)'!U16=3,"Unemployed",'Loan Tape (BoE)'!U16=4,"Retired"),"") | W15: =IFERROR(IFS('Loan Tape (BoE)'!V16=1,"Employed",'Loan Tape (BoE)'!V16=2,"Self-Employed",'Loan Tape (BoE)'!V16=3,"Unemployed",'Loan Tape (BoE)'!V16=4,"Retired"),"") | X15: =IF(OR(V15="Self-Employed",W15="Self-Employed"),"Yes","No") | Y15: ='Loan Tape (BoE)'!W16 | Z15: ='Loan Tape (BoE)'!X16 | AA15: =IF(T15=1,Y15,MIN(Y15,Z15)) | AB15: ='Loan Tape (BoE)'!Y16 | AC15: ='Loan Tape (BoE)'!Z16 | AD15: =AB15+AC15 | AE15: ='Loan Tape (BoE)'!AA16 | AF15: ='Loan Tape (BoE)'!AB16 | AG15: =AE15+AF15 | AH15: =MAX('Loan Tape (BoE)'!AC16,'Loan Tape (BoE)'!AD16) | AI15: ='Loan Tape (BoE)'!AE16 | AJ15: =B15*H15/12 | AK15: =IF(AJ15>0,AI15/AJ15,0) | AL15: =IF('Loan Tape (BoE)'!AF16=1,"Yes","No") | AM15: =IF('Loan Tape (BoE)'!AH16=1,"Yes","No") | AN15: =IF('Loan Tape (BoE)'!AI16=1,"Yes","No") | AO15: =IF('Loan Tape (BoE)'!AJ16=1,"Yes","No") | AP15: =IF(OR('Loan Tape (BoE)'!AQ15=1,'Loan Tape (BoE)'!AQ15=2),"Yes",IF('Loan Tape (BoE)'!AQ15=0,"No","")) | AQ15: =IF('Loan Tape (BoE)'!BV49_115<>"",'Loan Tape (BoE)'!BV49_15,"") | AR15: =IF('Loan Tape (BoE)'!BV150_15<>"",'Loan Tape (BoE)'!BV50_15,"") | AS15: =IFERROR(INDEX('FF Adj Parameters'!$A$103:$B$1015,MATCH('Loan Tape (BoE)'!P15,INDEX('FF Adj Parameters'!$A$103:$B$1015,,1),0),2),"Unknown") | AT15: =IF(N15="Interest Only",M5*O5/12,IF(AND(O5>0,ISNUMBER(O5),ISNUMBER(M5)),ABS(PMT(O5/12,AU5,-M5)),0)) | AU15: =IF(ISNUMBER(L15),MAX(0,(L5-'Control Panel'!$B$10)*12/365.25),0) | AV15: =IF(ISNUMBER(L15),IF(L5>'Control Panel'!$B$10,"Valid","Past Maturity"),"No Date") | AW15: =IF(ISNUMBER(K15),MAX(0,('Control Panel'!$B$10-K5)*12/365.25),0)
A16: ='Loan Tape (BoE)'!A17 | B16: =IFERROR(INDEX('FF Adj Parameters'!$A$89:$B$92,MATCH('Loan Tape (BoE)'!C16,INDEX('FF Adj Parameters'!$A$89:$B$92,,1),0),2),"Unknown") | C16: ='Loan Tape (BoE)'!C17 | D16: ='Loan Tape (BoE)'!D17 | E16: ='Loan Tape (BoE)'!E17 | F16: ='Loan Tape (BoE)'!F17 | G16: ='Loan Tape (BoE)'!G17 | H16: ='Loan Tape (BoE)'!H17/100 | I16: =IFERROR(IFS('Loan Tape (BoE)'!I17=1,"House",'Loan Tape (BoE)'!I17=2,"Flat",'Loan Tape (BoE)'!I17=3,"Bungalow",'Loan Tape (BoE)'!I17=4,"Maisonette"),"") | J16: ='Loan Tape (BoE)'!J17 | K16: ='Loan Tape (BoE)'!K17 | L16: =IFERROR(IFS('Loan Tape (BoE)'!L17=1,"Owner Occupied",'Loan Tape (BoE)'!L17=2,"BTL",'Loan Tape (BoE)'!L17=3,"Second Home",'Loan Tape (BoE)'!L17=4,"Investment"),"") | M16: =IFERROR(IFS('Loan Tape (BoE)'!M17=1,"Purchase",'Loan Tape (BoE)'!M17=2,"Remortgage",OR('Loan Tape (BoE)'!M17=3,'Loan Tape (BoE)'!M17=4),"Cash-out"),"") | N16: =IFERROR(INDEX('FF Adj Parameters'!$A$96:$B$99,MATCH('Loan Tape (BoE)'!R16,INDEX('FF Adj Parameters'!$A$96:$B$99,,1),0),2),"Unknown") | O16: =IF('Loan Tape (BoE)'!O17=1,"Yes","No") | P16: =IF('Loan Tape (BoE)'!P16=1,"Yes",IF('Loan Tape (BoE)'!P16=0,"No","")) | Q16: =IF('Loan Tape (BoE)'!Q16=1,"Yes",IF('Loan Tape (BoE)'!Q16=0,"No","")) | R16: =IF('Loan Tape (BoE)'!R16=1,"Yes",IF('Loan Tape (BoE)'!R16=0,"No","")) | S16: =IF('Loan Tape (BoE)'!S16=1,"Yes",IF('Loan Tape (BoE)'!S16=0,"No","")) | T16: =IF('Loan Tape (BoE)'!T16=1,"Yes",IF('Loan Tape (BoE)'!T16=0,"No","")) | U16: =R16+S16 | V16: =IFERROR(IFS('Loan Tape (BoE)'!U17=1,"Employed",'Loan Tape (BoE)'!U17=2,"Self-Employed",'Loan Tape (BoE)'!U17=3,"Unemployed",'Loan Tape (BoE)'!U17=4,"Retired"),"") | W16: =IFERROR(IFS('Loan Tape (BoE)'!V17=1,"Employed",'Loan Tape (BoE)'!V17=2,"Self-Employed",'Loan Tape (BoE)'!V17=3,"Unemployed",'Loan Tape (BoE)'!V17=4,"Retired"),"") | X16: =IF(OR(V16="Self-Employed",W16="Self-Employed"),"Yes","No") | Y16: ='Loan Tape (BoE)'!W17 | Z16: ='Loan Tape (BoE)'!X17 | AA16: =IF(T16=1,Y16,MIN(Y16,Z16)) | AB16: ='Loan Tape (BoE)'!Y17 | AC16: ='Loan Tape (BoE)'!Z17 | AD16: =AB16+AC16 | AE16: ='Loan Tape (BoE)'!AA17 | AF16: ='Loan Tape (BoE)'!AB17 | AG16: =AE16+AF16 | AH16: =MAX('Loan Tape (BoE)'!AC17,'Loan Tape (BoE)'!AD17) | AI16: ='Loan Tape (BoE)'!AE17 | AJ16: =B16*H16/12 | AK16: =IF(AJ16>0,AI16/AJ16,0) | AL16: =IF('Loan Tape (BoE)'!AF17=1,"Yes","No") | AM16: =IF('Loan Tape (BoE)'!AH17=1,"Yes","No") | AN16: =IF('Loan Tape (BoE)'!AI17=1,"Yes","No") | AO16: =IF('Loan Tape (BoE)'!AJ17=1,"Yes","No") | AP16: =IF(OR('Loan Tape (BoE)'!AQ16=1,'Loan Tape (BoE)'!AQ16=2),"Yes",IF('Loan Tape (BoE)'!AQ16=0,"No","")) | AQ16: =IF('Loan Tape (BoE)'!BV49_16<>"",'Loan Tape (BoE)'!BV49_16,"") | AR16: =IF('Loan Tape (BoE)'!BV160_16<>"",'Loan Tape (BoE)'!BV50_16,"") | AS16: =IFERROR(INDEX('FF Adj Parameters'!$A$103:$B$1016,MATCH('Loan Tape (BoE)'!P16,INDEX('FF Adj Parameters'!$A$103:$B$1016,,1),0),2),"Unknown") | AT16: =IF(N16="Interest Only",M5*O5/12,IF(AND(O5>0,ISNUMBER(O5),ISNUMBER(M5)),ABS(PMT(O5/12,AU5,-M5)),0)) | AU16: =IF(ISNUMBER(L16),MAX(0,(L5-'Control Panel'!$B$10)*12/365.25),0) | AV16: =IF(ISNUMBER(L16),IF(L5>'Control Panel'!$B$10,"Valid","Past Maturity"),"No Date") | AW16: =IF(ISNUMBER(K16),MAX(0,('Control Panel'!$B$10-K5)*12/365.25),0)
A17: ='Loan Tape (BoE)'!A18 | B17: =IFERROR(INDEX('FF Adj Parameters'!$A$89:$B$92,MATCH('Loan Tape (BoE)'!C17,INDEX('FF Adj Parameters'!$A$89:$B$92,,1),0),2),"Unknown") | C17: ='Loan Tape (BoE)'!C18 | D17: ='Loan Tape (BoE)'!D18 | E17: ='Loan Tape (BoE)'!E18 | F17: ='Loan Tape (BoE)'!F18 | G17: ='Loan Tape (BoE)'!G18 | H17: ='Loan Tape (BoE)'!H18/100 | I17: =IFERROR(IFS('Loan Tape (BoE)'!I18=1,"House",'Loan Tape (BoE)'!I18=2,"Flat",'Loan Tape (BoE)'!I18=3,"Bungalow",'Loan Tape (BoE)'!I18=4,"Maisonette"),"") | J17: ='Loan Tape (BoE)'!J18 | K17: ='Loan Tape (BoE)'!K18 | L17: =IFERROR(IFS('Loan Tape (BoE)'!L18=1,"Owner Occupied",'Loan Tape (BoE)'!L18=2,"BTL",'Loan Tape (BoE)'!L18=3,"Second Home",'Loan Tape (BoE)'!L18=4,"Investment"),"") | M17: =IFERROR(IFS('Loan Tape (BoE)'!M18=1,"Purchase",'Loan Tape (BoE)'!M18=2,"Remortgage",OR('Loan Tape (BoE)'!M18=3,'Loan Tape (BoE)'!M18=4),"Cash-out"),"") | N17: =IFERROR(INDEX('FF Adj Parameters'!$A$96:$B$99,MATCH('Loan Tape (BoE)'!R17,INDEX('FF Adj Parameters'!$A$96:$B$99,,1),0),2),"Unknown") | O17: =IF('Loan Tape (BoE)'!O18=1,"Yes","No") | P17: =IF('Loan Tape (BoE)'!P17=1,"Yes",IF('Loan Tape (BoE)'!P17=0,"No","")) | Q17: =IF('Loan Tape (BoE)'!Q17=1,"Yes",IF('Loan Tape (BoE)'!Q17=0,"No","")) | R17: =IF('Loan Tape (BoE)'!R17=1,"Yes",IF('Loan Tape (BoE)'!R17=0,"No","")) | S17: =IF('Loan Tape (BoE)'!S17=1,"Yes",IF('Loan Tape (BoE)'!S17=0,"No","")) | T17: =IF('Loan Tape (BoE)'!T17=1,"Yes",IF('Loan Tape (BoE)'!T17=0,"No","")) | U17: =R17+S17 | V17: =IFERROR(IFS('Loan Tape (BoE)'!U18=1,"Employed",'Loan Tape (BoE)'!U18=2,"Self-Employed",'Loan Tape (BoE)'!U18=3,"Unemployed",'Loan Tape (BoE)'!U18=4,"Retired"),"") | W17: =IFERROR(IFS('Loan Tape (BoE)'!V18=1,"Employed",'Loan Tape (BoE)'!V18=2,"Self-Employed",'Loan Tape (BoE)'!V18=3,"Unemployed",'Loan Tape (BoE)'!V18=4,"Retired"),"") | X17: =IF(OR(V17="Self-Employed",W17="Self-Employed"),"Yes","No") | Y17: ='Loan Tape (BoE)'!W18 | Z17: ='Loan Tape (BoE)'!X18 | AA17: =IF(T17=1,Y17,MIN(Y17,Z17)) | AB17: ='Loan Tape (BoE)'!Y18 | AC17: ='Loan Tape (BoE)'!Z18 | AD17: =AB17+AC17 | AE17: ='Loan Tape (BoE)'!AA18 | AF17: ='Loan Tape (BoE)'!AB18 | AG17: =AE17+AF17 | AH17: =MAX('Loan Tape (BoE)'!AC18,'Loan Tape (BoE)'!AD18) | AI17: ='Loan Tape (BoE)'!AE18 | AJ17: =B17*H17/12 | AK17: =IF(AJ17>0,AI17/AJ17,0) | AL17: =IF('Loan Tape (BoE)'!AF18=1,"Yes","No") | AM17: =IF('Loan Tape (BoE)'!AH18=1,"Yes","No") | AN17: =IF('Loan Tape (BoE)'!AI18=1,"Yes","No") | AO17: =IF('Loan Tape (BoE)'!AJ18=1,"Yes","No") | AP17: =IF(OR('Loan Tape (BoE)'!AQ17=1,'Loan Tape (BoE)'!AQ17=2),"Yes",IF('Loan Tape (BoE)'!AQ17=0,"No","")) | AQ17: =IF('Loan Tape (BoE)'!BV49_17<>"",'Loan Tape (BoE)'!BV49_17,"") | AR17: =IF('Loan Tape (BoE)'!BV170_17<>"",'Loan Tape (BoE)'!BV50_17,"") | AS17: =IFERROR(INDEX('FF Adj Parameters'!$A$103:$B$1017,MATCH('Loan Tape (BoE)'!P17,INDEX('FF Adj Parameters'!$A$103:$B$1017,,1),0),2),"Unknown") | AT17: =IF(N17="Interest Only",M5*O5/12,IF(AND(O5>0,ISNUMBER(O5),ISNUMBER(M5)),ABS(PMT(O5/12,AU5,-M5)),0)) | AU17: =IF(ISNUMBER(L17),MAX(0,(L5-'Control Panel'!$B$10)*12/365.25),0) | AV17: =IF(ISNUMBER(L17),IF(L5>'Control Panel'!$B$10,"Valid","Past Maturity"),"No Date") | AW17: =IF(ISNUMBER(K17),MAX(0,('Control Panel'!$B$10-K5)*12/365.25),0)
A18: ='Loan Tape (BoE)'!A19 | B18: =IFERROR(INDEX('FF Adj Parameters'!$A$89:$B$92,MATCH('Loan Tape (BoE)'!C18,INDEX('FF Adj Parameters'!$A$89:$B$92,,1),0),2),"Unknown") | C18: ='Loan Tape (BoE)'!C19 | D18: ='Loan Tape (BoE)'!D19 | E18: ='Loan Tape (BoE)'!E19 | F18: ='Loan Tape (BoE)'!F19 | G18: ='Loan Tape (BoE)'!G19 | H18: ='Loan Tape (BoE)'!H19/100 | I18: =IFERROR(IFS('Loan Tape (BoE)'!I19=1,"House",'Loan Tape (BoE)'!I19=2,"Flat",'Loan Tape (BoE)'!I19=3,"Bungalow",'Loan Tape (BoE)'!I19=4,"Maisonette"),"") | J18: ='Loan Tape (BoE)'!J19 | K18: ='Loan Tape (BoE)'!K19 | L18: =IFERROR(IFS('Loan Tape (BoE)'!L19=1,"Owner Occupied",'Loan Tape (BoE)'!L19=2,"BTL",'Loan Tape (BoE)'!L19=3,"Second Home",'Loan Tape (BoE)'!L19=4,"Investment"),"") | M18: =IFERROR(IFS('Loan Tape (BoE)'!M19=1,"Purchase",'Loan Tape (BoE)'!M19=2,"Remortgage",OR('Loan Tape (BoE)'!M19=3,'Loan Tape (BoE)'!M19=4),"Cash-out"),"") | N18: =IFERROR(INDEX('FF Adj Parameters'!$A$96:$B$99,MATCH('Loan Tape (BoE)'!R18,INDEX('FF Adj Parameters'!$A$96:$B$99,,1),0),2),"Unknown") | O18: =IF('Loan Tape (BoE)'!O19=1,"Yes","No") | P18: =IF('Loan Tape (BoE)'!P18=1,"Yes",IF('Loan Tape (BoE)'!P18=0,"No","")) | Q18: =IF('Loan Tape (BoE)'!Q18=1,"Yes",IF('Loan Tape (BoE)'!Q18=0,"No","")) | R18: =IF('Loan Tape (BoE)'!R18=1,"Yes",IF('Loan Tape (BoE)'!R18=0,"No","")) | S18: =IF('Loan Tape (BoE)'!S18=1,"Yes",IF('Loan Tape (BoE)'!S18=0,"No","")) | T18: =IF('Loan Tape (BoE)'!T18=1,"Yes",IF('Loan Tape (BoE)'!T18=0,"No","")) | U18: =R18+S18 | V18: =IFERROR(IFS('Loan Tape (BoE)'!U19=1,"Employed",'Loan Tape (BoE)'!U19=2,"Self-Employed",'Loan Tape (BoE)'!U19=3,"Unemployed",'Loan Tape (BoE)'!U19=4,"Retired"),"") | W18: =IFERROR(IFS('Loan Tape (BoE)'!V19=1,"Employed",'Loan Tape (BoE)'!V19=2,"Self-Employed",'Loan Tape (BoE)'!V19=3,"Unemployed",'Loan Tape (BoE)'!V19=4,"Retired"),"") | X18: =IF(OR(V18="Self-Employed",W18="Self-Employed"),"Yes","No") | Y18: ='Loan Tape (BoE)'!W19 | Z18: ='Loan Tape (BoE)'!X19 | AA18: =IF(T18=1,Y18,MIN(Y18,Z18)) | AB18: ='Loan Tape (BoE)'!Y19 | AC18: ='Loan Tape (BoE)'!Z19 | AD18: =AB18+AC18 | AE18: ='Loan Tape (BoE)'!AA19 | AF18: ='Loan Tape (BoE)'!AB19 | AG18: =AE18+AF18 | AH18: =MAX('Loan Tape (BoE)'!AC19,'Loan Tape (BoE)'!AD19) | AI18: ='Loan Tape (BoE)'!AE19 | AJ18: =B18*H18/12 | AK18: =IF(AJ18>0,AI18/AJ18,0) | AL18: =IF('Loan Tape (BoE)'!AF19=1,"Yes","No") | AM18: =IF('Loan Tape (BoE)'!AH19=1,"Yes","No") | AN18: =IF('Loan Tape (BoE)'!AI19=1,"Yes","No") | AO18: =IF('Loan Tape (BoE)'!AJ19=1,"Yes","No") | AP18: =IF(OR('Loan Tape (BoE)'!AQ18=1,'Loan Tape (BoE)'!AQ18=2),"Yes",IF('Loan Tape (BoE)'!AQ18=0,"No","")) | AQ18: =IF('Loan Tape (BoE)'!BV49_18<>"",'Loan Tape (BoE)'!BV49_18,"") | AR18: =IF('Loan Tape (BoE)'!BV180_18<>"",'Loan Tape (BoE)'!BV50_18,"") | AS18: =IFERROR(INDEX('FF Adj Parameters'!$A$103:$B$1018,MATCH('Loan Tape (BoE)'!P18,INDEX('FF Adj Parameters'!$A$103:$B$1018,,1),0),2),"Unknown") | AT18: =IF(N18="Interest Only",M5*O5/12,IF(AND(O5>0,ISNUMBER(O5),ISNUMBER(M5)),ABS(PMT(O5/12,AU5,-M5)),0)) | AU18: =IF(ISNUMBER(L18),MAX(0,(L5-'Control Panel'!$B$10)*12/365.25),0) | AV18: =IF(ISNUMBER(L18),IF(L5>'Control Panel'!$B$10,"Valid","Past Maturity"),"No Date") | AW18: =IF(ISNUMBER(K18),MAX(0,('Control Panel'!$B$10-K5)*12/365.25),0)
A19: ='Loan Tape (BoE)'!A20 | B19: =IFERROR(INDEX('FF Adj Parameters'!$A$89:$B$92,MATCH('Loan Tape (BoE)'!C19,INDEX('FF Adj Parameters'!$A$89:$B$92,,1),0),2),"Unknown") | C19: ='Loan Tape (BoE)'!C20 | D19: ='Loan Tape (BoE)'!D20 | E19: ='Loan Tape (BoE)'!E20 | F19: ='Loan Tape (BoE)'!F20 | G19: ='Loan Tape (BoE)'!G20 | H19: ='Loan Tape (BoE)'!H20/100 | I19: =IFERROR(IFS('Loan Tape (BoE)'!I20=1,"House",'Loan Tape (BoE)'!I20=2,"Flat",'Loan Tape (BoE)'!I20=3,"Bungalow",'Loan Tape (BoE)'!I20=4,"Maisonette"),"") | J19: ='Loan Tape (BoE)'!J20 | K19: ='Loan Tape (BoE)'!K20 | L19: =IFERROR(IFS('Loan Tape (BoE)'!L20=1,"Owner Occupied",'Loan Tape (BoE)'!L20=2,"BTL",'Loan Tape (BoE)'!L20=3,"Second Home",'Loan Tape (BoE)'!L20=4,"Investment"),"") | M19: =IFERROR(IFS('Loan Tape (BoE)'!M20=1,"Purchase",'Loan Tape (BoE)'!M20=2,"Remortgage",OR('Loan Tape (BoE)'!M20=3,'Loan Tape (BoE)'!M20=4),"Cash-out"),"") | N19: =IFERROR(INDEX('FF Adj Parameters'!$A$96:$B$99,MATCH('Loan Tape (BoE)'!R19,INDEX('FF Adj Parameters'!$A$96:$B$99,,1),0),2),"Unknown") | O19: =IF('Loan Tape (BoE)'!O20=1,"Yes","No") | P19: =IF('Loan Tape (BoE)'!P19=1,"Yes",IF('Loan Tape (BoE)'!P19=0,"No","")) | Q19: =IF('Loan Tape (BoE)'!Q19=1,"Yes",IF('Loan Tape (BoE)'!Q19=0,"No","")) | R19: =IF('Loan Tape (BoE)'!R19=1,"Yes",IF('Loan Tape (BoE)'!R19=0,"No","")) | S19: =IF('Loan Tape (BoE)'!S19=1,"Yes",IF('Loan Tape (BoE)'!S19=0,"No","")) | T19: =IF('Loan Tape (BoE)'!T19=1,"Yes",IF('Loan Tape (BoE)'!T19=0,"No","")) | U19: =R19+S19 | V19: =IFERROR(IFS('Loan Tape (BoE)'!U20=1,"Employed",'Loan Tape (BoE)'!U20=2,"Self-Employed",'Loan Tape (BoE)'!U20=3,"Unemployed",'Loan Tape (BoE)'!U20=4,"Retired"),"") | W19: =IFERROR(IFS('Loan Tape (BoE)'!V20=1,"Employed",'Loan Tape (BoE)'!V20=2,"Self-Employed",'Loan Tape (BoE)'!V20=3,"Unemployed",'Loan Tape (BoE)'!V20=4,"Retired"),"") | X19: =IF(OR(V19="Self-Employed",W19="Self-Employed"),"Yes","No") | Y19: ='Loan Tape (BoE)'!W20 | Z19: ='Loan Tape (BoE)'!X20 | AA19: =IF(T19=1,Y19,MIN(Y19,Z19)) | AB19: ='Loan Tape (BoE)'!Y20 | AC19: ='Loan Tape (BoE)'!Z20 | AD19: =AB19+AC19 | AE19: ='Loan Tape (BoE)'!AA20 | AF19: ='Loan Tape (BoE)'!AB20 | AG19: =AE19+AF19 | AH19: =MAX('Loan Tape (BoE)'!AC20,'Loan Tape (BoE)'!AD20) | AI19: ='Loan Tape (BoE)'!AE20 | AJ19: =B19*H19/12 | AK19: =IF(AJ19>0,AI19/AJ19,0) | AL19: =IF('Loan Tape (BoE)'!AF20=1,"Yes","No") | AM19: =IF('Loan Tape (BoE)'!AH20=1,"Yes","No") | AN19: =IF('Loan Tape (BoE)'!AI20=1,"Yes","No") | AO19: =IF('Loan Tape (BoE)'!AJ20=1,"Yes","No") | AP19: =IF(OR('Loan Tape (BoE)'!AQ19=1,'Loan Tape (BoE)'!AQ19=2),"Yes",IF('Loan Tape (BoE)'!AQ19=0,"No","")) | AQ19: =IF('Loan Tape (BoE)'!BV49_19<>"",'Loan Tape (BoE)'!BV49_19,"") | AR19: =IF('Loan Tape (BoE)'!BV190_19<>"",'Loan Tape (BoE)'!BV50_19,"") | AS19: =IFERROR(INDEX('FF Adj Parameters'!$A$103:$B$1019,MATCH('Loan Tape (BoE)'!P19,INDEX('FF Adj Parameters'!$A$103:$B$1019,,1),0),2),"Unknown") | AT19: =IF(N19="Interest Only",M5*O5/12,IF(AND(O5>0,ISNUMBER(O5),ISNUMBER(M5)),ABS(PMT(O5/12,AU5,-M5)),0)) | AU19: =IF(ISNUMBER(L19),MAX(0,(L5-'Control Panel'!$B$10)*12/365.25),0) | AV19: =IF(ISNUMBER(L19),IF(L5>'Control Panel'!$B$10,"Valid","Past Maturity"),"No Date") | AW19: =IF(ISNUMBER(K19),MAX(0,('Control Panel'!$B$10-K5)*12/365.25),0)
A20: ='Loan Tape (BoE)'!A21 | B20: =IFERROR(INDEX('FF Adj Parameters'!$A$89:$B$92,MATCH('Loan Tape (BoE)'!C20,INDEX('FF Adj Parameters'!$A$89:$B$92,,1),0),2),"Unknown") | C20: ='Loan Tape (BoE)'!C21 | D20: ='Loan Tape (BoE)'!D21 | E20: ='Loan Tape (BoE)'!E21 | F20: ='Loan Tape (BoE)'!F21 | G20: ='Loan Tape (BoE)'!G21 | H20: ='Loan Tape (BoE)'!H21/100 | I20: =IFERROR(IFS('Loan Tape (BoE)'!I21=1,"House",'Loan Tape (BoE)'!I21=2,"Flat",'Loan Tape (BoE)'!I21=3,"Bungalow",'Loan Tape (BoE)'!I21=4,"Maisonette"),"") | J20: ='Loan Tape (BoE)'!J21 | K20: ='Loan Tape (BoE)'!K21 | L20: =IFERROR(IFS('Loan Tape (BoE)'!L21=1,"Owner Occupied",'Loan Tape (BoE)'!L21=2,"BTL",'Loan Tape (BoE)'!L21=3,"Second Home",'Loan Tape (BoE)'!L21=4,"Investment"),"") | M20: =IFERROR(IFS('Loan Tape (BoE)'!M21=1,"Purchase",'Loan Tape (BoE)'!M21=2,"Remortgage",OR('Loan Tape (BoE)'!M21=3,'Loan Tape (BoE)'!M21=4),"Cash-out"),"") | N20: =IFERROR(INDEX('FF Adj Parameters'!$A$96:$B$99,MATCH('Loan Tape (BoE)'!R20,INDEX('FF Adj Parameters'!$A$96:$B$99,,1),0),2),"Unknown") | O20: =IF('Loan Tape (BoE)'!O21=1,"Yes","No") | P20: =IF('Loan Tape (BoE)'!P20=1,"Yes",IF('Loan Tape (BoE)'!P20=0,"No","")) | Q20: =IF('Loan Tape (BoE)'!Q20=1,"Yes",IF('Loan Tape (BoE)'!Q20=0,"No","")) | R20: =IF('Loan Tape (BoE)'!R20=1,"Yes",IF('Loan Tape (BoE)'!R20=0,"No","")) | S20: =IF('Loan Tape (BoE)'!S20=1,"Yes",IF('Loan Tape (BoE)'!S20=0,"No","")) | T20: =IF('Loan Tape (BoE)'!T20=1,"Yes",IF('Loan Tape (BoE)'!T20=0,"No","")) | U20: =R20+S20 | V20: =IFERROR(IFS('Loan Tape (BoE)'!U21=1,"Employed",'Loan Tape (BoE)'!U21=2,"Self-Employed",'Loan Tape (BoE)'!U21=3,"Unemployed",'Loan Tape (BoE)'!U21=4,"Retired"),"") | W20: =IFERROR(IFS('Loan Tape (BoE)'!V21=1,"Employed",'Loan Tape (BoE)'!V21=2,"Self-Employed",'Loan Tape (BoE)'!V21=3,"Unemployed",'Loan Tape (BoE)'!V21=4,"Retired"),"") | X20: =IF(OR(V20="Self-Employed",W20="Self-Employed"),"Yes","No") | Y20: ='Loan Tape (BoE)'!W21 | Z20: ='Loan Tape (BoE)'!X21 | AA20: =IF(T20=1,Y20,MIN(Y20,Z20)) | AB20: ='Loan Tape (BoE)'!Y21 | AC20: ='Loan Tape (BoE)'!Z21 | AD20: =AB20+AC20 | AE20: ='Loan Tape (BoE)'!AA21 | AF20: ='Loan Tape (BoE)'!AB21 | AG20: =AE20+AF20 | AH20: =MAX('Loan Tape (BoE)'!AC21,'Loan Tape (BoE)'!AD21) | AI20: ='Loan Tape (BoE)'!AE21 | AJ20: =B20*H20/12 | AK20: =IF(AJ20>0,AI20/AJ20,0) | AL20: =IF('Loan Tape (BoE)'!AF21=1,"Yes","No") | AM20: =IF('Loan Tape (BoE)'!AH21=1,"Yes","No") | AN20: =IF('Loan Tape (BoE)'!AI21=1,"Yes","No") | AO20: =IF('Loan Tape (BoE)'!AJ21=1,"Yes","No") | AP20: =IF(OR('Loan Tape (BoE)'!AQ20=1,'Loan Tape (BoE)'!AQ20=2),"Yes",IF('Loan Tape (BoE)'!AQ20=0,"No","")) | AQ20: =IF('Loan Tape (BoE)'!BV49_20<>"",'Loan Tape (BoE)'!BV49_20,"") | AR20: =IF('Loan Tape (BoE)'!BV200_20<>"",'Loan Tape (BoE)'!BV50_20,"") | AS20: =IFERROR(INDEX('FF Adj Parameters'!$A$103:$B$1020,MATCH('Loan Tape (BoE)'!P20,INDEX('FF Adj Parameters'!$A$103:$B$1020,,1),0),2),"Unknown") | AT20: =IF(N20="Interest Only",M5*O5/12,IF(AND(O5>0,ISNUMBER(O5),ISNUMBER(M5)),ABS(PMT(O5/12,AU5,-M5)),0)) | AU20: =IF(ISNUMBER(L20),MAX(0,(L5-'Control Panel'!$B$10)*12/365.25),0) | AV20: =IF(ISNUMBER(L20),IF(L5>'Control Panel'!$B$10,"Valid","Past Maturity"),"No Date") | AW20: =IF(ISNUMBER(K20),MAX(0,('Control Panel'!$B$10-K5)*12/365.25),0)
A21: ='Loan Tape (BoE)'!A22 | B21: =IFERROR(INDEX('FF Adj Parameters'!$A$89:$B$92,MATCH('Loan Tape (BoE)'!C21,INDEX('FF Adj Parameters'!$A$89:$B$92,,1),0),2),"Unknown") | C21: ='Loan Tape (BoE)'!C22 | D21: ='Loan Tape (BoE)'!D22 | E21: ='Loan Tape (BoE)'!E22 | F21: ='Loan Tape (BoE)'!F22 | G21: ='Loan Tape (BoE)'!G22 | H21: ='Loan Tape (BoE)'!H22/100 | I21: =IFERROR(IFS('Loan Tape (BoE)'!I22=1,"House",'Loan Tape (BoE)'!I22=2,"Flat",'Loan Tape (BoE)'!I22=3,"Bungalow",'Loan Tape (BoE)'!I22=4,"Maisonette"),"") | J21: ='Loan Tape (BoE)'!J22 | K21: ='Loan Tape (BoE)'!K22 | L21: =IFERROR(IFS('Loan Tape (BoE)'!L22=1,"Owner Occupied",'Loan Tape (BoE)'!L22=2,"BTL",'Loan Tape (BoE)'!L22=3,"Second Home",'Loan Tape (BoE)'!L22=4,"Investment"),"") | M21: =IFERROR(IFS('Loan Tape (BoE)'!M22=1,"Purchase",'Loan Tape (BoE)'!M22=2,"Remortgage",OR('Loan Tape (BoE)'!M22=3,'Loan Tape (BoE)'!M22=4),"Cash-out"),"") | N21: =IFERROR(INDEX('FF Adj Parameters'!$A$96:$B$99,MATCH('Loan Tape (BoE)'!R21,INDEX('FF Adj Parameters'!$A$96:$B$99,,1),0),2),"Unknown") | O21: =IF('Loan Tape (BoE)'!O22=1,"Yes","No") | P21: =IF('Loan Tape (BoE)'!P21=1,"Yes",IF('Loan Tape (BoE)'!P21=0,"No","")) | Q21: =IF('Loan Tape (BoE)'!Q21=1,"Yes",IF('Loan Tape (BoE)'!Q21=0,"No","")) | R21: =IF('Loan Tape (BoE)'!R21=1,"Yes",IF('Loan Tape (BoE)'!R21=0,"No","")) | S21: =IF('Loan Tape (BoE)'!S21=1,"Yes",IF('Loan Tape (BoE)'!S21=0,"No","")) | T21: =IF('Loan Tape (BoE)'!T21=1,"Yes",IF('Loan Tape (BoE)'!T21=0,"No","")) | U21: =R21+S21 | V21: =IFERROR(IFS('Loan Tape (BoE)'!U22=1,"Employed",'Loan Tape (BoE)'!U22=2,"Self-Employed",'Loan Tape (BoE)'!U22=3,"Unemployed",'Loan Tape (BoE)'!U22=4,"Retired"),"") | W21: =IFERROR(IFS('Loan Tape (BoE)'!V22=1,"Employed",'Loan Tape (BoE)'!V22=2,"Self-Employed",'Loan Tape (BoE)'!V22=3,"Unemployed",'Loan Tape (BoE)'!V22=4,"Retired"),"") | X21: =IF(OR(V21="Self-Employed",W21="Self-Employed"),"Yes","No") | Y21: ='Loan Tape (BoE)'!W22 | Z21: ='Loan Tape (BoE)'!X22 | AA21: =IF(T21=1,Y21,MIN(Y21,Z21)) | AB21: ='Loan Tape (BoE)'!Y22 | AC21: ='Loan Tape (BoE)'!Z22 | AD21: =AB21+AC21 | AE21: ='Loan Tape (BoE)'!AA22 | AF21: ='Loan Tape (BoE)'!AB22 | AG21: =AE21+AF21 | AH21: =MAX('Loan Tape (BoE)'!AC22,'Loan Tape (BoE)'!AD22) | AI21: ='Loan Tape (BoE)'!AE22 | AJ21: =B21*H21/12 | AK21: =IF(AJ21>0,AI21/AJ21,0) | AL21: =IF('Loan Tape (BoE)'!AF22=1,"Yes","No") | AM21: =IF('Loan Tape (BoE)'!AH22=1,"Yes","No") | AN21: =IF('Loan Tape (BoE)'!AI22=1,"Yes","No") | AO21: =IF('Loan Tape (BoE)'!AJ22=1,"Yes","No") | AP21: =IF(OR('Loan Tape (BoE)'!AQ21=1,'Loan Tape (BoE)'!AQ21=2),"Yes",IF('Loan Tape (BoE)'!AQ21=0,"No","")) | AQ21: =IF('Loan Tape (BoE)'!BV49_21<>"",'Loan Tape (BoE)'!BV49_21,"") | AR21: =IF('Loan Tape (BoE)'!BV210_21<>"",'Loan Tape (BoE)'!BV50_21,"") | AS21: =IFERROR(INDEX('FF Adj Parameters'!$A$103:$B$1021,MATCH('Loan Tape (BoE)'!P21,INDEX('FF Adj Parameters'!$A$103:$B$1021,,1),0),2),"Unknown") | AT21: =IF(N21="Interest Only",M5*O5/12,IF(AND(O5>0,ISNUMBER(O5),ISNUMBER(M5)),ABS(PMT(O5/12,AU5,-M5)),0)) | AU21: =IF(ISNUMBER(L21),MAX(0,(L5-'Control Panel'!$B$10)*12/365.25),0) | AV21: =IF(ISNUMBER(L21),IF(L5>'Control Panel'!$B$10,"Valid","Past Maturity"),"No Date") | AW21: =IF(ISNUMBER(K21),MAX(0,('Control Panel'!$B$10-K5)*12/365.25),0)
A22: ='Loan Tape (BoE)'!A23 | B22: =IFERROR(INDEX('FF Adj Parameters'!$A$89:$B$92,MATCH('Loan Tape (BoE)'!C22,INDEX('FF Adj Parameters'!$A$89:$B$92,,1),0),2),"Unknown") | C22: ='Loan Tape (BoE)'!C23 | D22: ='Loan Tape (BoE)'!D23 | E22: ='Loan Tape (BoE)'!E23 | F22: ='Loan Tape (BoE)'!F23 | G22: ='Loan Tape (BoE)'!G23 | H22: ='Loan Tape (BoE)'!H23/100 | I22: =IFERROR(IFS('Loan Tape (BoE)'!I23=1,"House",'Loan Tape (BoE)'!I23=2,"Flat",'Loan Tape (BoE)'!I23=3,"Bungalow",'Loan Tape (BoE)'!I23=4,"Maisonette"),"") | J22: ='Loan Tape (BoE)'!J23 | K22: ='Loan Tape (BoE)'!K23 | L22: =IFERROR(IFS('Loan Tape (BoE)'!L23=1,"Owner Occupied",'Loan Tape (BoE)'!L23=2,"BTL",'Loan Tape (BoE)'!L23=3,"Second Home",'Loan Tape (BoE)'!L23=4,"Investment"),"") | M22: =IFERROR(IFS('Loan Tape (BoE)'!M23=1,"Purchase",'Loan Tape (BoE)'!M23=2,"Remortgage",OR('Loan Tape (BoE)'!M23=3,'Loan Tape (BoE)'!M23=4),"Cash-out"),"") | N22: =IFERROR(INDEX('FF Adj Parameters'!$A$96:$B$99,MATCH('Loan Tape (BoE)'!R22,INDEX('FF Adj Parameters'!$A$96:$B$99,,1),0),2),"Unknown") | O22: =IF('Loan Tape (BoE)'!O23=1,"Yes","No") | P22: =IF('Loan Tape (BoE)'!P22=1,"Yes",IF('Loan Tape (BoE)'!P22=0,"No","")) | Q22: =IF('Loan Tape (BoE)'!Q22=1,"Yes",IF('Loan Tape (BoE)'!Q22=0,"No","")) | R22: =IF('Loan Tape (BoE)'!R22=1,"Yes",IF('Loan Tape (BoE)'!R22=0,"No","")) | S22: =IF('Loan Tape (BoE)'!S22=1,"Yes",IF('Loan Tape (BoE)'!S22=0,"No","")) | T22: =IF('Loan Tape (BoE)'!T22=1,"Yes",IF('Loan Tape (BoE)'!T22=0,"No","")) | U22: =R22+S22 | V22: =IFERROR(IFS('Loan Tape (BoE)'!U23=1,"Employed",'Loan Tape (BoE)'!U23=2,"Self-Employed",'Loan Tape (BoE)'!U23=3,"Unemployed",'Loan Tape (BoE)'!U23=4,"Retired"),"") | W22: =IFERROR(IFS('Loan Tape (BoE)'!V23=1,"Employed",'Loan Tape (BoE)'!V23=2,"Self-Employed",'Loan Tape (BoE)'!V23=3,"Unemployed",'Loan Tape (BoE)'!V23=4,"Retired"),"") | X22: =IF(OR(V22="Self-Employed",W22="Self-Employed"),"Yes","No") | Y22: ='Loan Tape (BoE)'!W23 | Z22: ='Loan Tape (BoE)'!X23 | AA22: =IF(T22=1,Y22,MIN(Y22,Z22)) | AB22: ='Loan Tape (BoE)'!Y23 | AC22: ='Loan Tape (BoE)'!Z23 | AD22: =AB22+AC22 | AE22: ='Loan Tape (BoE)'!AA23 | AF22: ='Loan Tape (BoE)'!AB23 | AG22: =AE22+AF22 | AH22: =MAX('Loan Tape (BoE)'!AC23,'Loan Tape (BoE)'!AD23) | AI22: ='Loan Tape (BoE)'!AE23 | AJ22: =B22*H22/12 | AK22: =IF(AJ22>0,AI22/AJ22,0) | AL22: =IF('Loan Tape (BoE)'!AF23=1,"Yes","No") | AM22: =IF('Loan Tape (BoE)'!AH23=1,"Yes","No") | AN22: =IF('Loan Tape (BoE)'!AI23=1,"Yes","No") | AO22: =IF('Loan Tape (BoE)'!AJ23=1,"Yes","No") | AP22: =IF(OR('Loan Tape (BoE)'!AQ22=1,'Loan Tape (BoE)'!AQ22=2),"Yes",IF('Loan Tape (BoE)'!AQ22=0,"No","")) | AQ22: =IF('Loan Tape (BoE)'!BV49_22<>"",'Loan Tape (BoE)'!BV49_22,"") | AR22: =IF('Loan Tape (BoE)'!BV220_22<>"",'Loan Tape (BoE)'!BV50_22,"") | AS22: =IFERROR(INDEX('FF Adj Parameters'!$A$103:$B$1022,MATCH('Loan Tape (BoE)'!P22,INDEX('FF Adj Parameters'!$A$103:$B$1022,,1),0),2),"Unknown") | AT22: =IF(N22="Interest Only",M5*O5/12,IF(AND(O5>0,ISNUMBER(O5),ISNUMBER(M5)),ABS(PMT(O5/12,AU5,-M5)),0)) | AU22: =IF(ISNUMBER(L22),MAX(0,(L5-'Control Panel'!$B$10)*12/365.25),0) | AV22: =IF(ISNUMBER(L22),IF(L5>'Control Panel'!$B$10,"Valid","Past Maturity"),"No Date") | AW22: =IF(ISNUMBER(K22),MAX(0,('Control Panel'!$B$10-K5)*12/365.25),0)
A23: ='Loan Tape (BoE)'!A24 | B23: =IFERROR(INDEX('FF Adj Parameters'!$A$89:$B$92,MATCH('Loan Tape (BoE)'!C23,INDEX('FF Adj Parameters'!$A$89:$B$92,,1),0),2),"Unknown") | C23: ='Loan Tape (BoE)'!C24 | D23: ='Loan Tape (BoE)'!D24 | E23: ='Loan Tape (BoE)'!E24 | F23: ='Loan Tape (BoE)'!F24 | G23: ='Loan Tape (BoE)'!G24 | H23: ='Loan Tape (BoE)'!H24/100 | I23: =IFERROR(IFS('Loan Tape (BoE)'!I24=1,"House",'Loan Tape (BoE)'!I24=2,"Flat",'Loan Tape (BoE)'!I24=3,"Bungalow",'Loan Tape (BoE)'!I24=4,"Maisonette"),"") | J23: ='Loan Tape (BoE)'!J24 | K23: ='Loan Tape (BoE)'!K24 | L23: =IFERROR(IFS('Loan Tape (BoE)'!L24=1,"Owner Occupied",'Loan Tape (BoE)'!L24=2,"BTL",'Loan Tape (BoE)'!L24=3,"Second Home",'Loan Tape (BoE)'!L24=4,"Investment"),"") | M23: =IFERROR(IFS('Loan Tape (BoE)'!M24=1,"Purchase",'Loan Tape (BoE)'!M24=2,"Remortgage",OR('Loan Tape (BoE)'!M24=3,'Loan Tape (BoE)'!M24=4),"Cash-out"),"") | N23: =IFERROR(INDEX('FF Adj Parameters'!$A$96:$B$99,MATCH('Loan Tape (BoE)'!R23,INDEX('FF Adj Parameters'!$A$96:$B$99,,1),0),2),"Unknown") | O23: =IF('Loan Tape (BoE)'!O24=1,"Yes","No") | P23: =IF('Loan Tape (BoE)'!P23=1,"Yes",IF('Loan Tape (BoE)'!P23=0,"No","")) | Q23: =IF('Loan Tape (BoE)'!Q23=1,"Yes",IF('Loan Tape (BoE)'!Q23=0,"No","")) | R23: =IF('Loan Tape (BoE)'!R23=1,"Yes",IF('Loan Tape (BoE)'!R23=0,"No","")) | S23: =IF('Loan Tape (BoE)'!S23=1,"Yes",IF('Loan Tape (BoE)'!S23=0,"No","")) | T23: =IF('Loan Tape (BoE)'!T23=1,"Yes",IF('Loan Tape (BoE)'!T23=0,"No","")) | U23: =R23+S23 | V23: =IFERROR(IFS('Loan Tape (BoE)'!U24=1,"Employed",'Loan Tape (BoE)'!U24=2,"Self-Employed",'Loan Tape (BoE)'!U24=3,"Unemployed",'Loan Tape (BoE)'!U24=4,"Retired"),"") | W23: =IFERROR(IFS('Loan Tape (BoE)'!V24=1,"Employed",'Loan Tape (BoE)'!V24=2,"Self-Employed",'Loan Tape (BoE)'!V24=3,"Unemployed",'Loan Tape (BoE)'!V24=4,"Retired"),"") | X23: =IF(OR(V23="Self-Employed",W23="Self-Employed"),"Yes","No") | Y23: ='Loan Tape (BoE)'!W24 | Z23: ='Loan Tape (BoE)'!X24 | AA23: =IF(T23=1,Y23,MIN(Y23,Z23)) | AB23: ='Loan Tape (BoE)'!Y24 | AC23: ='Loan Tape (BoE)'!Z24 | AD23: =AB23+AC23 | AE23: ='Loan Tape (BoE)'!AA24 | AF23: ='Loan Tape (BoE)'!AB24 | AG23: =AE23+AF23 | AH23: =MAX('Loan Tape (BoE)'!AC24,'Loan Tape (BoE)'!AD24) | AI23: ='Loan Tape (BoE)'!AE24 | AJ23: =B23*H23/12 | AK23: =IF(AJ23>0,AI23/AJ23,0) | AL23: =IF('Loan Tape (BoE)'!AF24=1,"Yes","No") | AM23: =IF('Loan Tape (BoE)'!AH24=1,"Yes","No") | AN23: =IF('Loan Tape (BoE)'!AI24=1,"Yes","No") | AO23: =IF('Loan Tape (BoE)'!AJ24=1,"Yes","No") | AP23: =IF(OR('Loan Tape (BoE)'!AQ23=1,'Loan Tape (BoE)'!AQ23=2),"Yes",IF('Loan Tape (BoE)'!AQ23=0,"No","")) | AQ23: =IF('Loan Tape (BoE)'!BV49_23<>"",'Loan Tape (BoE)'!BV49_23,"") | AR23: =IF('Loan Tape (BoE)'!BV230_23<>"",'Loan Tape (BoE)'!BV50_23,"") | AS23: =IFERROR(INDEX('FF Adj Parameters'!$A$103:$B$1023,MATCH('Loan Tape (BoE)'!P23,INDEX('FF Adj Parameters'!$A$103:$B$1023,,1),0),2),"Unknown") | AT23: =IF(N23="Interest Only",M5*O5/12,IF(AND(O5>0,ISNUMBER(O5),ISNUMBER(M5)),ABS(PMT(O5/12,AU5,-M5)),0)) | AU23: =IF(ISNUMBER(L23),MAX(0,(L5-'Control Panel'!$B$10)*12/365.25),0) | AV23: =IF(ISNUMBER(L23),IF(L5>'Control Panel'!$B$10,"Valid","Past Maturity"),"No Date") | AW23: =IF(ISNUMBER(K23),MAX(0,('Control Panel'!$B$10-K5)*12/365.25),0)
A24: ='Loan Tape (BoE)'!A25 | B24: =IFERROR(INDEX('FF Adj Parameters'!$A$89:$B$92,MATCH('Loan Tape (BoE)'!C24,INDEX('FF Adj Parameters'!$A$89:$B$92,,1),0),2),"Unknown") | C24: ='Loan Tape (BoE)'!C25 | D24: ='Loan Tape (BoE)'!D25 | E24: ='Loan Tape (BoE)'!E25 | F24: ='Loan Tape (BoE)'!F25 | G24: ='Loan Tape (BoE)'!G25 | H24: ='Loan Tape (BoE)'!H25/100 | I24: =IFERROR(IFS('Loan Tape (BoE)'!I25=1,"House",'Loan Tape (BoE)'!I25=2,"Flat",'Loan Tape (BoE)'!I25=3,"Bungalow",'Loan Tape (BoE)'!I25=4,"Maisonette"),"") | J24: ='Loan Tape (BoE)'!J25 | K24: ='Loan Tape (BoE)'!K25 | L24: =IFERROR(IFS('Loan Tape (BoE)'!L25=1,"Owner Occupied",'Loan Tape (BoE)'!L25=2,"BTL",'Loan Tape (BoE)'!L25=3,"Second Home",'Loan Tape (BoE)'!L25=4,"Investment"),"") | M24: =IFERROR(IFS('Loan Tape (BoE)'!M25=1,"Purchase",'Loan Tape (BoE)'!M25=2,"Remortgage",OR('Loan Tape (BoE)'!M25=3,'Loan Tape (BoE)'!M25=4),"Cash-out"),"") | N24: =IFERROR(INDEX('FF Adj Parameters'!$A$96:$B$99,MATCH('Loan Tape (BoE)'!R24,INDEX('FF Adj Parameters'!$A$96:$B$99,,1),0),2),"Unknown") | O24: =IF('Loan Tape (BoE)'!O25=1,"Yes","No") | P24: =IF('Loan Tape (BoE)'!P24=1,"Yes",IF('Loan Tape (BoE)'!P24=0,"No","")) | Q24: =IF('Loan Tape (BoE)'!Q24=1,"Yes",IF('Loan Tape (BoE)'!Q24=0,"No","")) | R24: =IF('Loan Tape (BoE)'!R24=1,"Yes",IF('Loan Tape (BoE)'!R24=0,"No","")) | S24: =IF('Loan Tape (BoE)'!S24=1,"Yes",IF('Loan Tape (BoE)'!S24=0,"No","")) | T24: =IF('Loan Tape (BoE)'!T24=1,"Yes",IF('Loan Tape (BoE)'!T24=0,"No","")) | U24: =R24+S24 | V24: =IFERROR(IFS('Loan Tape (BoE)'!U25=1,"Employed",'Loan Tape (BoE)'!U25=2,"Self-Employed",'Loan Tape (BoE)'!U25=3,"Unemployed",'Loan Tape (BoE)'!U25=4,"Retired"),"") | W24: =IFERROR(IFS('Loan Tape (BoE)'!V25=1,"Employed",'Loan Tape (BoE)'!V25=2,"Self-Employed",'Loan Tape (BoE)'!V25=3,"Unemployed",'Loan Tape (BoE)'!V25=4,"Retired"),"") | X24: =IF(OR(V24="Self-Employed",W24="Self-Employed"),"Yes","No") | Y24: ='Loan Tape (BoE)'!W25 | Z24: ='Loan Tape (BoE)'!X25 | AA24: =IF(T24=1,Y24,MIN(Y24,Z24)) | AB24: ='Loan Tape (BoE)'!Y25 | AC24: ='Loan Tape (BoE)'!Z25 | AD24: =AB24+AC24 | AE24: ='Loan Tape (BoE)'!AA25 | AF24: ='Loan Tape (BoE)'!AB25 | AG24: =AE24+AF24 | AH24: =MAX('Loan Tape (BoE)'!AC25,'Loan Tape (BoE)'!AD25) | AI24: ='Loan Tape (BoE)'!AE25 | AJ24: =B24*H24/12 | AK24: =IF(AJ24>0,AI24/AJ24,0) | AL24: =IF('Loan Tape (BoE)'!AF25=1,"Yes","No") | AM24: =IF('Loan Tape (BoE)'!AH25=1,"Yes","No") | AN24: =IF('Loan Tape (BoE)'!AI25=1,"Yes","No") | AO24: =IF('Loan Tape (BoE)'!AJ25=1,"Yes","No") | AP24: =IF(OR('Loan Tape (BoE)'!AQ24=1,'Loan Tape (BoE)'!AQ24=2),"Yes",IF('Loan Tape (BoE)'!AQ24=0,"No","")) | AQ24: =IF('Loan Tape (BoE)'!BV49_24<>"",'Loan Tape (BoE)'!BV49_24,"") | AR24: =IF('Loan Tape (BoE)'!BV240_24<>"",'Loan Tape (BoE)'!BV50_24,"") | AS24: =IFERROR(INDEX('FF Adj Parameters'!$A$103:$B$1024,MATCH('Loan Tape (BoE)'!P24,INDEX('FF Adj Parameters'!$A$103:$B$1024,,1),0),2),"Unknown") | AT24: =IF(N24="Interest Only",M5*O5/12,IF(AND(O5>0,ISNUMBER(O5),ISNUMBER(M5)),ABS(PMT(O5/12,AU5,-M5)),0)) | AU24: =IF(ISNUMBER(L24),MAX(0,(L5-'Control Panel'!$B$10)*12/365.25),0) | AV24: =IF(ISNUMBER(L24),IF(L5>'Control Panel'!$B$10,"Valid","Past Maturity"),"No Date") | AW24: =IF(ISNUMBER(K24),MAX(0,('Control Panel'!$B$10-K5)*12/365.25),0)
A25: ='Loan Tape (BoE)'!A26 | B25: =IFERROR(INDEX('FF Adj Parameters'!$A$89:$B$92,MATCH('Loan Tape (BoE)'!C25,INDEX('FF Adj Parameters'!$A$89:$B$92,,1),0),2),"Unknown") | C25: ='Loan Tape (BoE)'!C26 | D25: ='Loan Tape (BoE)'!D26 | E25: ='Loan Tape (BoE)'!E26 | F25: ='Loan Tape (BoE)'!F26 | G25: ='Loan Tape (BoE)'!G26 | H25: ='Loan Tape (BoE)'!H26/100 | I25: =IFERROR(IFS('Loan Tape (BoE)'!I26=1,"House",'Loan Tape (BoE)'!I26=2,"Flat",'Loan Tape (BoE)'!I26=3,"Bungalow",'Loan Tape (BoE)'!I26=4,"Maisonette"),"") | J25: ='Loan Tape (BoE)'!J26 | K25: ='Loan Tape (BoE)'!K26 | L25: =IFERROR(IFS('Loan Tape (BoE)'!L26=1,"Owner Occupied",'Loan Tape (BoE)'!L26=2,"BTL",'Loan Tape (BoE)'!L26=3,"Second Home",'Loan Tape (BoE)'!L26=4,"Investment"),"") | M25: =IFERROR(IFS('Loan Tape (BoE)'!M26=1,"Purchase",'Loan Tape (BoE)'!M26=2,"Remortgage",OR('Loan Tape (BoE)'!M26=3,'Loan Tape (BoE)'!M26=4),"Cash-out"),"") | N25: =IFERROR(INDEX('FF Adj Parameters'!$A$96:$B$99,MATCH('Loan Tape (BoE)'!R25,INDEX('FF Adj Parameters'!$A$96:$B$99,,1),0),2),"Unknown") | O25: =IF('Loan Tape (BoE)'!O26=1,"Yes","No") | P25: =IF('Loan Tape (BoE)'!P25=1,"Yes",IF('Loan Tape (BoE)'!P25=0,"No","")) | Q25: =IF('Loan Tape (BoE)'!Q25=1,"Yes",IF('Loan Tape (BoE)'!Q25=0,"No","")) | R25: =IF('Loan Tape (BoE)'!R25=1,"Yes",IF('Loan Tape (BoE)'!R25=0,"No","")) | S25: =IF('Loan Tape (BoE)'!S25=1,"Yes",IF('Loan Tape (BoE)'!S25=0,"No","")) | T25: =IF('Loan Tape (BoE)'!T25=1,"Yes",IF('Loan Tape (BoE)'!T25=0,"No","")) | U25: =R25+S25 | V25: =IFERROR(IFS('Loan Tape (BoE)'!U26=1,"Employed",'Loan Tape (BoE)'!U26=2,"Self-Employed",'Loan Tape (BoE)'!U26=3,"Unemployed",'Loan Tape (BoE)'!U26=4,"Retired"),"") | W25: =IFERROR(IFS('Loan Tape (BoE)'!V26=1,"Employed",'Loan Tape (BoE)'!V26=2,"Self-Employed",'Loan Tape (BoE)'!V26=3,"Unemployed",'Loan Tape (BoE)'!V26=4,"Retired"),"") | X25: =IF(OR(V25="Self-Employed",W25="Self-Employed"),"Yes","No") | Y25: ='Loan Tape (BoE)'!W26 | Z25: ='Loan Tape (BoE)'!X26 | AA25: =IF(T25=1,Y25,MIN(Y25,Z25)) | AB25: ='Loan Tape (BoE)'!Y26 | AC25: ='Loan Tape (BoE)'!Z26 | AD25: =AB25+AC25 | AE25: ='Loan Tape (BoE)'!AA26 | AF25: ='Loan Tape (BoE)'!AB26 | AG25: =AE25+AF25 | AH25: =MAX('Loan Tape (BoE)'!AC26,'Loan Tape (BoE)'!AD26) | AI25: ='Loan Tape (BoE)'!AE26 | AJ25: =B25*H25/12 | AK25: =IF(AJ25>0,AI25/AJ25,0) | AL25: =IF('Loan Tape (BoE)'!AF26=1,"Yes","No") | AM25: =IF('Loan Tape (BoE)'!AH26=1,"Yes","No") | AN25: =IF('Loan Tape (BoE)'!AI26=1,"Yes","No") | AO25: =IF('Loan Tape (BoE)'!AJ26=1,"Yes","No") | AP25: =IF(OR('Loan Tape (BoE)'!AQ25=1,'Loan Tape (BoE)'!AQ25=2),"Yes",IF('Loan Tape (BoE)'!AQ25=0,"No","")) | AQ25: =IF('Loan Tape (BoE)'!BV49_225<>"",'Loan Tape (BoE)'!BV49_25,"") | AR25: =IF('Loan Tape (BoE)'!BV250_25<>"",'Loan Tape (BoE)'!BV50_25,"") | AS25: =IFERROR(INDEX('FF Adj Parameters'!$A$103:$B$1025,MATCH('Loan Tape (BoE)'!P25,INDEX('FF Adj Parameters'!$A$103:$B$1025,,1),0),2),"Unknown") | AT25: =IF(N25="Interest Only",M5*O5/12,IF(AND(O5>0,ISNUMBER(O5),ISNUMBER(M5)),ABS(PMT(O5/12,AU5,-M5)),0)) | AU25: =IF(ISNUMBER(L25),MAX(0,(L5-'Control Panel'!$B$10)*12/365.25),0) | AV25: =IF(ISNUMBER(L25),IF(L5>'Control Panel'!$B$10,"Valid","Past Maturity"),"No Date") | AW25: =IF(ISNUMBER(K25),MAX(0,('Control Panel'!$B$10-K5)*12/365.25),0)
A26: ='Loan Tape (BoE)'!A27 | B26: =IFERROR(INDEX('FF Adj Parameters'!$A$89:$B$92,MATCH('Loan Tape (BoE)'!C26,INDEX('FF Adj Parameters'!$A$89:$B$92,,1),0),2),"Unknown") | C26: ='Loan Tape (BoE)'!C27 | D26: ='Loan Tape (BoE)'!D27 | E26: ='Loan Tape (BoE)'!E27 | F26: ='Loan Tape (BoE)'!F27 | G26: ='Loan Tape (BoE)'!G27 | H26: ='Loan Tape (BoE)'!H27/100 | I26: =IFERROR(IFS('Loan Tape (BoE)'!I27=1,"House",'Loan Tape (BoE)'!I27=2,"Flat",'Loan Tape (BoE)'!I27=3,"Bungalow",'Loan Tape (BoE)'!I27=4,"Maisonette"),"") | J26: ='Loan Tape (BoE)'!J27 | K26: ='Loan Tape (BoE)'!K27 | L26: =IFERROR(IFS('Loan Tape (BoE)'!L27=1,"Owner Occupied",'Loan Tape (BoE)'!L27=2,"BTL",'Loan Tape (BoE)'!L27=3,"Second Home",'Loan Tape (BoE)'!L27=4,"Investment"),"") | M26: =IFERROR(IFS('Loan Tape (BoE)'!M27=1,"Purchase",'Loan Tape (BoE)'!M27=2,"Remortgage",OR('Loan Tape (BoE)'!M27=3,'Loan Tape (BoE)'!M27=4),"Cash-out"),"") | N26: =IFERROR(INDEX('FF Adj Parameters'!$A$96:$B$99,MATCH('Loan Tape (BoE)'!R26,INDEX('FF Adj Parameters'!$A$96:$B$99,,1),0),2),"Unknown") | O26: =IF('Loan Tape (BoE)'!O27=1,"Yes","No") | P26: =IF('Loan Tape (BoE)'!P26=1,"Yes",IF('Loan Tape (BoE)'!P26=0,"No","")) | Q26: =IF('Loan Tape (BoE)'!Q26=1,"Yes",IF('Loan Tape (BoE)'!Q26=0,"No","")) | R26: =IF('Loan Tape (BoE)'!R26=1,"Yes",IF('Loan Tape (BoE)'!R26=0,"No","")) | S26: =IF('Loan Tape (BoE)'!S26=1,"Yes",IF('Loan Tape (BoE)'!S26=0,"No","")) | T26: =IF('Loan Tape (BoE)'!T26=1,"Yes",IF('Loan Tape (BoE)'!T26=0,"No","")) | U26: =R26+S26 | V26: =IFERROR(IFS('Loan Tape (BoE)'!U27=1,"Employed",'Loan Tape (BoE)'!U27=2,"Self-Employed",'Loan Tape (BoE)'!U27=3,"Unemployed",'Loan Tape (BoE)'!U27=4,"Retired"),"") | W26: =IFERROR(IFS('Loan Tape (BoE)'!V27=1,"Employed",'Loan Tape (BoE)'!V27=2,"Self-Employed",'Loan Tape (BoE)'!V27=3,"Unemployed",'Loan Tape (BoE)'!V27=4,"Retired"),"") | X26: =IF(OR(V26="Self-Employed",W26="Self-Employed"),"Yes","No") | Y26: ='Loan Tape (BoE)'!W27 | Z26: ='Loan Tape (BoE)'!X27 | AA26: =IF(T26=1,Y26,MIN(Y26,Z26)) | AB26: ='Loan Tape (BoE)'!Y27 | AC26: ='Loan Tape (BoE)'!Z27 | AD26: =AB26+AC26 | AE26: ='Loan Tape (BoE)'!AA27 | AF26: ='Loan Tape (BoE)'!AB27 | AG26: =AE26+AF26 | AH26: =MAX('Loan Tape (BoE)'!AC27,'Loan Tape (BoE)'!AD27) | AI26: ='Loan Tape (BoE)'!AE27 | AJ26: =B26*H26/12 | AK26: =IF(AJ26>0,AI26/AJ26,0) | AL26: =IF('Loan Tape (BoE)'!AF27=1,"Yes","No") | AM26: =IF('Loan Tape (BoE)'!AH27=1,"Yes","No") | AN26: =IF('Loan Tape (BoE)'!AI27=1,"Yes","No") | AO26: =IF('Loan Tape (BoE)'!AJ27=1,"Yes","No") | AP26: =IF(OR('Loan Tape (BoE)'!AQ26=1,'Loan Tape (BoE)'!AQ26=2),"Yes",IF('Loan Tape (BoE)'!AQ26=0,"No","")) | AQ26: =IF('Loan Tape (BoE)'!BV49_26<>"",'Loan Tape (BoE)'!BV49_26,"") | AR26: =IF('Loan Tape (BoE)'!BV260_26<>"",'Loan Tape (BoE)'!BV50_26,"") | AS26: =IFERROR(INDEX('FF Adj Parameters'!$A$103:$B$1026,MATCH('Loan Tape (BoE)'!P26,INDEX('FF Adj Parameters'!$A$103:$B$1026,,1),0),2),"Unknown") | AT26: =IF(N26="Interest Only",M5*O5/12,IF(AND(O5>0,ISNUMBER(O5),ISNUMBER(M5)),ABS(PMT(O5/12,AU5,-M5)),0)) | AU26: =IF(ISNUMBER(L26),MAX(0,(L5-'Control Panel'!$B$10)*12/365.25),0) | AV26: =IF(ISNUMBER(L26),IF(L5>'Control Panel'!$B$10,"Valid","Past Maturity"),"No Date") | AW26: =IF(ISNUMBER(K26),MAX(0,('Control Panel'!$B$10-K5)*12/365.25),0)
A27: ='Loan Tape (BoE)'!A28 | B27: =IFERROR(INDEX('FF Adj Parameters'!$A$89:$B$92,MATCH('Loan Tape (BoE)'!C27,INDEX('FF Adj Parameters'!$A$89:$B$92,,1),0),2),"Unknown") | C27: ='Loan Tape (BoE)'!C28 | D27: ='Loan Tape (BoE)'!D28 | E27: ='Loan Tape (BoE)'!E28 | F27: ='Loan Tape (BoE)'!F28 | G27: ='Loan Tape (BoE)'!G28 | H27: ='Loan Tape (BoE)'!H28/100 | I27: =IFERROR(IFS('Loan Tape (BoE)'!I28=1,"House",'Loan Tape (BoE)'!I28=2,"Flat",'Loan Tape (BoE)'!I28=3,"Bungalow",'Loan Tape (BoE)'!I28=4,"Maisonette"),"") | J27: ='Loan Tape (BoE)'!J28 | K27: ='Loan Tape (BoE)'!K28 | L27: =IFERROR(IFS('Loan Tape (BoE)'!L28=1,"Owner Occupied",'Loan Tape (BoE)'!L28=2,"BTL",'Loan Tape (BoE)'!L28=3,"Second Home",'Loan Tape (BoE)'!L28=4,"Investment"),"") | M27: =IFERROR(IFS('Loan Tape (BoE)'!M28=1,"Purchase",'Loan Tape (BoE)'!M28=2,"Remortgage",OR('Loan Tape (BoE)'!M28=3,'Loan Tape (BoE)'!M28=4),"Cash-out"),"") | N27: =IFERROR(INDEX('FF Adj Parameters'!$A$96:$B$99,MATCH('Loan Tape (BoE)'!R27,INDEX('FF Adj Parameters'!$A$96:$B$99,,1),0),2),"Unknown") | O27: =IF('Loan Tape (BoE)'!O28=1,"Yes","No") | P27: =IF('Loan Tape (BoE)'!P27=1,"Yes",IF('Loan Tape (BoE)'!P27=0,"No","")) | Q27: =IF('Loan Tape (BoE)'!Q27=1,"Yes",IF('Loan Tape (BoE)'!Q27=0,"No","")) | R27: =IF('Loan Tape (BoE)'!R27=1,"Yes",IF('Loan Tape (BoE)'!R27=0,"No","")) | S27: =IF('Loan Tape (BoE)'!S27=1,"Yes",IF('Loan Tape (BoE)'!S27=0,"No","")) | T27: =IF('Loan Tape (BoE)'!T27=1,"Yes",IF('Loan Tape (BoE)'!T27=0,"No","")) | U27: =R27+S27 | V27: =IFERROR(IFS('Loan Tape (BoE)'!U28=1,"Employed",'Loan Tape (BoE)'!U28=2,"Self-Employed",'Loan Tape (BoE)'!U28=3,"Unemployed",'Loan Tape (BoE)'!U28=4,"Retired"),"") | W27: =IFERROR(IFS('Loan Tape (BoE)'!V28=1,"Employed",'Loan Tape (BoE)'!V28=2,"Self-Employed",'Loan Tape (BoE)'!V28=3,"Unemployed",'Loan Tape (BoE)'!V28=4,"Retired"),"") | X27: =IF(OR(V27="Self-Employed",W27="Self-Employed"),"Yes","No") | Y27: ='Loan Tape (BoE)'!W28 | Z27: ='Loan Tape (BoE)'!X28 | AA27: =IF(T27=1,Y27,MIN(Y27,Z27)) | AB27: ='Loan Tape (BoE)'!Y28 | AC27: ='Loan Tape (BoE)'!Z28 | AD27: =AB27+AC27 | AE27: ='Loan Tape (BoE)'!AA28 | AF27: ='Loan Tape (BoE)'!AB28 | AG27: =AE27+AF27 | AH27: =MAX('Loan Tape (BoE)'!AC28,'Loan Tape (BoE)'!AD28) | AI27: ='Loan Tape (BoE)'!AE28 | AJ27: =B27*H27/12 | AK27: =IF(AJ27>0,AI27/AJ27,0) | AL27: =IF('Loan Tape (BoE)'!AF28=1,"Yes","No") | AM27: =IF('Loan Tape (BoE)'!AH28=1,"Yes","No") | AN27: =IF('Loan Tape (BoE)'!AI28=1,"Yes","No") | AO27: =IF('Loan Tape (BoE)'!AJ28=1,"Yes","No") | AP27: =IF(OR('Loan Tape (BoE)'!AQ27=1,'Loan Tape (BoE)'!AQ27=2),"Yes",IF('Loan Tape (BoE)'!AQ27=0,"No","")) | AQ27: =IF('Loan Tape (BoE)'!BV49_27<>"",'Loan Tape (BoE)'!BV49_27,"") | AR27: =IF('Loan Tape (BoE)'!BV270_27<>"",'Loan Tape (BoE)'!BV50_27,"") | AS27: =IFERROR(INDEX('FF Adj Parameters'!$A$103:$B$1027,MATCH('Loan Tape (BoE)'!P27,INDEX('FF Adj Parameters'!$A$103:$B$1027,,1),0),2),"Unknown") | AT27: =IF(N27="Interest Only",M5*O5/12,IF(AND(O5>0,ISNUMBER(O5),ISNUMBER(M5)),ABS(PMT(O5/12,AU5,-M5)),0)) | AU27: =IF(ISNUMBER(L27),MAX(0,(L5-'Control Panel'!$B$10)*12/365.25),0) | AV27: =IF(ISNUMBER(L27),IF(L5>'Control Panel'!$B$10,"Valid","Past Maturity"),"No Date") | AW27: =IF(ISNUMBER(K27),MAX(0,('Control Panel'!$B$10-K5)*12/365.25),0)
A28: ='Loan Tape (BoE)'!A29 | B28: =IFERROR(INDEX('FF Adj Parameters'!$A$89:$B$92,MATCH('Loan Tape (BoE)'!C28,INDEX('FF Adj Parameters'!$A$89:$B$92,,1),0),2),"Unknown") | C28: ='Loan Tape (BoE)'!C29 | D28: ='Loan Tape (BoE)'!D29 | E28: ='Loan Tape (BoE)'!E29 | F28: ='Loan Tape (BoE)'!F29 | G28: ='Loan Tape (BoE)'!G29 | H28: ='Loan Tape (BoE)'!H29/100 | I28: =IFERROR(IFS('Loan Tape (BoE)'!I29=1,"House",'Loan Tape (BoE)'!I29=2,"Flat",'Loan Tape (BoE)'!I29=3,"Bungalow",'Loan Tape (BoE)'!I29=4,"Maisonette"),"") | J28: ='Loan Tape (BoE)'!J29 | K28: ='Loan Tape (BoE)'!K29 | L28: =IFERROR(IFS('Loan Tape (BoE)'!L29=1,"Owner Occupied",'Loan Tape (BoE)'!L29=2,"BTL",'Loan Tape (BoE)'!L29=3,"Second Home",'Loan Tape (BoE)'!L29=4,"Investment"),"") | M28: =IFERROR(IFS('Loan Tape (BoE)'!M29=1,"Purchase",'Loan Tape (BoE)'!M29=2,"Remortgage",OR('Loan Tape (BoE)'!M29=3,'Loan Tape (BoE)'!M29=4),"Cash-out"),"") | N28: =IFERROR(INDEX('FF Adj Parameters'!$A$96:$B$99,MATCH('Loan Tape (BoE)'!R28,INDEX('FF Adj Parameters'!$A$96:$B$99,,1),0),2),"Unknown") | O28: =IF('Loan Tape (BoE)'!O29=1,"Yes","No") | P28: =IF('Loan Tape (BoE)'!P28=1,"Yes",IF('Loan Tape (BoE)'!P28=0,"No","")) | Q28: =IF('Loan Tape (BoE)'!Q28=1,"Yes",IF('Loan Tape (BoE)'!Q28=0,"No","")) | R28: =IF('Loan Tape (BoE)'!R28=1,"Yes",IF('Loan Tape (BoE)'!R28=0,"No","")) | S28: =IF('Loan Tape (BoE)'!S28=1,"Yes",IF('Loan Tape (BoE)'!S28=0,"No","")) | T28: =IF('Loan Tape (BoE)'!T28=1,"Yes",IF('Loan Tape (BoE)'!T28=0,"No","")) | U28: =R28+S28 | V28: =IFERROR(IFS('Loan Tape (BoE)'!U29=1,"Employed",'Loan Tape (BoE)'!U29=2,"Self-Employed",'Loan Tape (BoE)'!U29=3,"Unemployed",'Loan Tape (BoE)'!U29=4,"Retired"),"") | W28: =IFERROR(IFS('Loan Tape (BoE)'!V29=1,"Employed",'Loan Tape (BoE)'!V29=2,"Self-Employed",'Loan Tape (BoE)'!V29=3,"Unemployed",'Loan Tape (BoE)'!V29=4,"Retired"),"") | X28: =IF(OR(V28="Self-Employed",W28="Self-Employed"),"Yes","No") | Y28: ='Loan Tape (BoE)'!W29 | Z28: ='Loan Tape (BoE)'!X29 | AA28: =IF(T28=1,Y28,MIN(Y28,Z28)) | AB28: ='Loan Tape (BoE)'!Y29 | AC28: ='Loan Tape (BoE)'!Z29 | AD28: =AB28+AC28 | AE28: ='Loan Tape (BoE)'!AA29 | AF28: ='Loan Tape (BoE)'!AB29 | AG28: =AE28+AF28 | AH28: =MAX('Loan Tape (BoE)'!AC29,'Loan Tape (BoE)'!AD29) | AI28: ='Loan Tape (BoE)'!AE29 | AJ28: =B28*H28/12 | AK28: =IF(AJ28>0,AI28/AJ28,0) | AL28: =IF('Loan Tape (BoE)'!AF29=1,"Yes","No") | AM28: =IF('Loan Tape (BoE)'!AH29=1,"Yes","No") | AN28: =IF('Loan Tape (BoE)'!AI29=1,"Yes","No") | AO28: =IF('Loan Tape (BoE)'!AJ29=1,"Yes","No") | AP28: =IF(OR('Loan Tape (BoE)'!AQ28=1,'Loan Tape (BoE)'!AQ28=2),"Yes",IF('Loan Tape (BoE)'!AQ28=0,"No","")) | AQ28: =IF('Loan Tape (BoE)'!BV49_28<>"",'Loan Tape (BoE)'!BV49_28,"") | AR28: =IF('Loan Tape (BoE)'!BV280_28<>"",'Loan Tape (BoE)'!BV50_28,"") | AS28: =IFERROR(INDEX('FF Adj Parameters'!$A$103:$B$1028,MATCH('Loan Tape (BoE)'!P28,INDEX('FF Adj Parameters'!$A$103:$B$1028,,1),0),2),"Unknown") | AT28: =IF(N28="Interest Only",M5*O5/12,IF(AND(O5>0,ISNUMBER(O5),ISNUMBER(M5)),ABS(PMT(O5/12,AU5,-M5)),0)) | AU28: =IF(ISNUMBER(L28),MAX(0,(L5-'Control Panel'!$B$10)*12/365.25),0) | AV28: =IF(ISNUMBER(L28),IF(L5>'Control Panel'!$B$10,"Valid","Past Maturity"),"No Date") | AW28: =IF(ISNUMBER(K28),MAX(0,('Control Panel'!$B$10-K5)*12/365.25),0)
A29: ='Loan Tape (BoE)'!A30 | B29: =IFERROR(INDEX('FF Adj Parameters'!$A$89:$B$92,MATCH('Loan Tape (BoE)'!C29,INDEX('FF Adj Parameters'!$A$89:$B$92,,1),0),2),"Unknown") | C29: ='Loan Tape (BoE)'!C30 | D29: ='Loan Tape (BoE)'!D30 | E29: ='Loan Tape (BoE)'!E30 | F29: ='Loan Tape (BoE)'!F30 | G29: ='Loan Tape (BoE)'!G30 | H29: ='Loan Tape (BoE)'!H30/100 | I29: =IFERROR(IFS('Loan Tape (BoE)'!I30=1,"House",'Loan Tape (BoE)'!I30=2,"Flat",'Loan Tape (BoE)'!I30=3,"Bungalow",'Loan Tape (BoE)'!I30=4,"Maisonette"),"") | J29: ='Loan Tape (BoE)'!J30 | K29: ='Loan Tape (BoE)'!K30 | L29: =IFERROR(IFS('Loan Tape (BoE)'!L30=1,"Owner Occupied",'Loan Tape (BoE)'!L30=2,"BTL",'Loan Tape (BoE)'!L30=3,"Second Home",'Loan Tape (BoE)'!L30=4,"Investment"),"") | M29: =IFERROR(IFS('Loan Tape (BoE)'!M30=1,"Purchase",'Loan Tape (BoE)'!M30=2,"Remortgage",OR('Loan Tape (BoE)'!M30=3,'Loan Tape (BoE)'!M30=4),"Cash-out"),"") | N29: =IFERROR(INDEX('FF Adj Parameters'!$A$96:$B$99,MATCH('Loan Tape (BoE)'!R29,INDEX('FF Adj Parameters'!$A$96:$B$99,,1),0),2),"Unknown") | O29: =IF('Loan Tape (BoE)'!O30=1,"Yes","No") | P29: =IF('Loan Tape (BoE)'!P29=1,"Yes",IF('Loan Tape (BoE)'!P29=0,"No","")) | Q29: =IF('Loan Tape (BoE)'!Q29=1,"Yes",IF('Loan Tape (BoE)'!Q29=0,"No","")) | R29: =IF('Loan Tape (BoE)'!R29=1,"Yes",IF('Loan Tape (BoE)'!R29=0,"No","")) | S29: =IF('Loan Tape (BoE)'!S29=1,"Yes",IF('Loan Tape (BoE)'!S29=0,"No","")) | T29: =IF('Loan Tape (BoE)'!T29=1,"Yes",IF('Loan Tape (BoE)'!T29=0,"No","")) | U29: =R29+S29 | V29: =IFERROR(IFS('Loan Tape (BoE)'!U30=1,"Employed",'Loan Tape (BoE)'!U30=2,"Self-Employed",'Loan Tape (BoE)'!U30=3,"Unemployed",'Loan Tape (BoE)'!U30=4,"Retired"),"") | W29: =IFERROR(IFS('Loan Tape (BoE)'!V30=1,"Employed",'Loan Tape (BoE)'!V30=2,"Self-Employed",'Loan Tape (BoE)'!V30=3,"Unemployed",'Loan Tape (BoE)'!V30=4,"Retired"),"") | X29: =IF(OR(V29="Self-Employed",W29="Self-Employed"),"Yes","No") | Y29: ='Loan Tape (BoE)'!W30 | Z29: ='Loan Tape (BoE)'!X30 | AA29: =IF(T29=1,Y29,MIN(Y29,Z29)) | AB29: ='Loan Tape (BoE)'!Y30 | AC29: ='Loan Tape (BoE)'!Z30 | AD29: =AB29+AC29 | AE29: ='Loan Tape (BoE)'!AA30 | AF29: ='Loan Tape (BoE)'!AB30 | AG29: =AE29+AF29 | AH29: =MAX('Loan Tape (BoE)'!AC30,'Loan Tape (BoE)'!AD30) | AI29: ='Loan Tape (BoE)'!AE30 | AJ29: =B29*H29/12 | AK29: =IF(AJ29>0,AI29/AJ29,0) | AL29: =IF('Loan Tape (BoE)'!AF30=1,"Yes","No") | AM29: =IF('Loan Tape (BoE)'!AH30=1,"Yes","No") | AN29: =IF('Loan Tape (BoE)'!AI30=1,"Yes","No") | AO29: =IF('Loan Tape (BoE)'!AJ30=1,"Yes","No") | AP29: =IF(OR('Loan Tape (BoE)'!AQ29=1,'Loan Tape (BoE)'!AQ29=2),"Yes",IF('Loan Tape (BoE)'!AQ29=0,"No","")) | AQ29: =IF('Loan Tape (BoE)'!BV49_29<>"",'Loan Tape (BoE)'!BV49_29,"") | AR29: =IF('Loan Tape (BoE)'!BV290_29<>"",'Loan Tape (BoE)'!BV50_29,"") | AS29: =IFERROR(INDEX('FF Adj Parameters'!$A$103:$B$1029,MATCH('Loan Tape (BoE)'!P29,INDEX('FF Adj Parameters'!$A$103:$B$1029,,1),0),2),"Unknown") | AT29: =IF(N29="Interest Only",M5*O5/12,IF(AND(O5>0,ISNUMBER(O5),ISNUMBER(M5)),ABS(PMT(O5/12,AU5,-M5)),0)) | AU29: =IF(ISNUMBER(L29),MAX(0,(L5-'Control Panel'!$B$10)*12/365.25),0) | AV29: =IF(ISNUMBER(L29),IF(L5>'Control Panel'!$B$10,"Valid","Past Maturity"),"No Date") | AW29: =IF(ISNUMBER(K29),MAX(0,('Control Panel'!$B$10-K5)*12/365.25),0)
A30: ='Loan Tape (BoE)'!A31 | B30: =IFERROR(INDEX('FF Adj Parameters'!$A$89:$B$92,MATCH('Loan Tape (BoE)'!C30,INDEX('FF Adj Parameters'!$A$89:$B$92,,1),0),2),"Unknown") | C30: ='Loan Tape (BoE)'!C31 | D30: ='Loan Tape (BoE)'!D31 | E30: ='Loan Tape (BoE)'!E31 | F30: ='Loan Tape (BoE)'!F31 | G30: ='Loan Tape (BoE)'!G31 | H30: ='Loan Tape (BoE)'!H31/100 | I30: =IFERROR(IFS('Loan Tape (BoE)'!I31=1,"House",'Loan Tape (BoE)'!I31=2,"Flat",'Loan Tape (BoE)'!I31=3,"Bungalow",'Loan Tape (BoE)'!I31=4,"Maisonette"),"") | J30: ='Loan Tape (BoE)'!J31 | K30: ='Loan Tape (BoE)'!K31 | L30: =IFERROR(IFS('Loan Tape (BoE)'!L31=1,"Owner Occupied",'Loan Tape (BoE)'!L31=2,"BTL",'Loan Tape (BoE)'!L31=3,"Second Home",'Loan Tape (BoE)'!L31=4,"Investment"),"") | M30: =IFERROR(IFS('Loan Tape (BoE)'!M31=1,"Purchase",'Loan Tape (BoE)'!M31=2,"Remortgage",OR('Loan Tape (BoE)'!M31=3,'Loan Tape (BoE)'!M31=4),"Cash-out"),"") | N30: =IFERROR(INDEX('FF Adj Parameters'!$A$96:$B$99,MATCH('Loan Tape (BoE)'!R30,INDEX('FF Adj Parameters'!$A$96:$B$99,,1),0),2),"Unknown") | O30: =IF('Loan Tape (BoE)'!O31=1,"Yes","No") | P30: =IF('Loan Tape (BoE)'!P30=1,"Yes",IF('Loan Tape (BoE)'!P30=0,"No","")) | Q30: =IF('Loan Tape (BoE)'!Q30=1,"Yes",IF('Loan Tape (BoE)'!Q30=0,"No","")) | R30: =IF('Loan Tape (BoE)'!R30=1,"Yes",IF('Loan Tape (BoE)'!R30=0,"No","")) | S30: =IF('Loan Tape (BoE)'!S30=1,"Yes",IF('Loan Tape (BoE)'!S30=0,"No","")) | T30: =IF('Loan Tape (BoE)'!T30=1,"Yes",IF('Loan Tape (BoE)'!T30=0,"No","")) | U30: =R30+S30 | V30: =IFERROR(IFS('Loan Tape (BoE)'!U31=1,"Employed",'Loan Tape (BoE)'!U31=2,"Self-Employed",'Loan Tape (BoE)'!U31=3,"Unemployed",'Loan Tape (BoE)'!U31=4,"Retired"),"") | W30: =IFERROR(IFS('Loan Tape (BoE)'!V31=1,"Employed",'Loan Tape (BoE)'!V31=2,"Self-Employed",'Loan Tape (BoE)'!V31=3,"Unemployed",'Loan Tape (BoE)'!V31=4,"Retired"),"") | X30: =IF(OR(V30="Self-Employed",W30="Self-Employed"),"Yes","No") | Y30: ='Loan Tape (BoE)'!W31 | Z30: ='Loan Tape (BoE)'!X31 | AA30: =IF(T30=1,Y30,MIN(Y30,Z30)) | AB30: ='Loan Tape (BoE)'!Y31 | AC30: ='Loan Tape (BoE)'!Z31 | AD30: =AB30+AC30 | AE30: ='Loan Tape (BoE)'!AA31 | AF30: ='Loan Tape (BoE)'!AB31 | AG30: =AE30+AF30 | AH30: =MAX('Loan Tape (BoE)'!AC31,'Loan Tape (BoE)'!AD31) | AI30: ='Loan Tape (BoE)'!AE31 | AJ30: =B30*H30/12 | AK30: =IF(AJ30>0,AI30/AJ30,0) | AL30: =IF('Loan Tape (BoE)'!AF31=1,"Yes","No") | AM30: =IF('Loan Tape (BoE)'!AH31=1,"Yes","No") | AN30: =IF('Loan Tape (BoE)'!AI31=1,"Yes","No") | AO30: =IF('Loan Tape (BoE)'!AJ31=1,"Yes","No") | AP30: =IF(OR('Loan Tape (BoE)'!AQ30=1,'Loan Tape (BoE)'!AQ30=2),"Yes",IF('Loan Tape (BoE)'!AQ30=0,"No","")) | AQ30: =IF('Loan Tape (BoE)'!BV49_30<>"",'Loan Tape (BoE)'!BV49_30,"") | AR30: =IF('Loan Tape (BoE)'!BV300_30<>"",'Loan Tape (BoE)'!BV50_30,"") | AS30: =IFERROR(INDEX('FF Adj Parameters'!$A$103:$B$1030,MATCH('Loan Tape (BoE)'!P30,INDEX('FF Adj Parameters'!$A$103:$B$1030,,1),0),2),"Unknown") | AT30: =IF(N30="Interest Only",M5*O5/12,IF(AND(O5>0,ISNUMBER(O5),ISNUMBER(M5)),ABS(PMT(O5/12,AU5,-M5)),0)) | AU30: =IF(ISNUMBER(L30),MAX(0,(L5-'Control Panel'!$B$10)*12/365.25),0) | AV30: =IF(ISNUMBER(L30),IF(L5>'Control Panel'!$B$10,"Valid","Past Maturity"),"No Date") | AW30: =IF(ISNUMBER(K30),MAX(0,('Control Panel'!$B$10-K5)*12/365.25),0)
A31: ='Loan Tape (BoE)'!A32 | B31: =IFERROR(INDEX('FF Adj Parameters'!$A$89:$B$92,MATCH('Loan Tape (BoE)'!C31,INDEX('FF Adj Parameters'!$A$89:$B$92,,1),0),2),"Unknown") | C31: ='Loan Tape (BoE)'!C32 | D31: ='Loan Tape (BoE)'!D32 | E31: ='Loan Tape (BoE)'!E32 | F31: ='Loan Tape (BoE)'!F32 | G31: ='Loan Tape (BoE)'!G32 | H31: ='Loan Tape (BoE)'!H32/100 | I31: =IFERROR(IFS('Loan Tape (BoE)'!I32=1,"House",'Loan Tape (BoE)'!I32=2,"Flat",'Loan Tape (BoE)'!I32=3,"Bungalow",'Loan Tape (BoE)'!I32=4,"Maisonette"),"") | J31: ='Loan Tape (BoE)'!J32 | K31: ='Loan Tape (BoE)'!K32 | L31: =IFERROR(IFS('Loan Tape (BoE)'!L32=1,"Owner Occupied",'Loan Tape (BoE)'!L32=2,"BTL",'Loan Tape (BoE)'!L32=3,"Second Home",'Loan Tape (BoE)'!L32=4,"Investment"),"") | M31: =IFERROR(IFS('Loan Tape (BoE)'!M32=1,"Purchase",'Loan Tape (BoE)'!M32=2,"Remortgage",OR('Loan Tape (BoE)'!M32=3,'Loan Tape (BoE)'!M32=4),"Cash-out"),"") | N31: =IFERROR(INDEX('FF Adj Parameters'!$A$96:$B$99,MATCH('Loan Tape (BoE)'!R31,INDEX('FF Adj Parameters'!$A$96:$B$99,,1),0),2),"Unknown") | O31: =IF('Loan Tape (BoE)'!O32=1,"Yes","No") | P31: =IF('Loan Tape (BoE)'!P31=1,"Yes",IF('Loan Tape (BoE)'!P31=0,"No","")) | Q31: =IF('Loan Tape (BoE)'!Q31=1,"Yes",IF('Loan Tape (BoE)'!Q31=0,"No","")) | R31: =IF('Loan Tape (BoE)'!R31=1,"Yes",IF('Loan Tape (BoE)'!R31=0,"No","")) | S31: =IF('Loan Tape (BoE)'!S31=1,"Yes",IF('Loan Tape (BoE)'!S31=0,"No","")) | T31: =IF('Loan Tape (BoE)'!T31=1,"Yes",IF('Loan Tape (BoE)'!T31=0,"No","")) | U31: =R31+S31 | V31: =IFERROR(IFS('Loan Tape (BoE)'!U32=1,"Employed",'Loan Tape (BoE)'!U32=2,"Self-Employed",'Loan Tape (BoE)'!U32=3,"Unemployed",'Loan Tape (BoE)'!U32=4,"Retired"),"") | W31: =IFERROR(IFS('Loan Tape (BoE)'!V32=1,"Employed",'Loan Tape (BoE)'!V32=2,"Self-Employed",'Loan Tape (BoE)'!V32=3,"Unemployed",'Loan Tape (BoE)'!V32=4,"Retired"),"") | X31: =IF(OR(V31="Self-Employed",W31="Self-Employed"),"Yes","No") | Y31: ='Loan Tape (BoE)'!W32 | Z31: ='Loan Tape (BoE)'!X32 | AA31: =IF(T31=1,Y31,MIN(Y31,Z31)) | AB31: ='Loan Tape (BoE)'!Y32 | AC31: ='Loan Tape (BoE)'!Z32 | AD31: =AB31+AC31 | AE31: ='Loan Tape (BoE)'!AA32 | AF31: ='Loan Tape (BoE)'!AB32 | AG31: =AE31+AF31 | AH31: =MAX('Loan Tape (BoE)'!AC32,'Loan Tape (BoE)'!AD32) | AI31: ='Loan Tape (BoE)'!AE32 | AJ31: =B31*H31/12 | AK31: =IF(AJ31>0,AI31/AJ31,0) | AL31: =IF('Loan Tape (BoE)'!AF32=1,"Yes","No") | AM31: =IF('Loan Tape (BoE)'!AH32=1,"Yes","No") | AN31: =IF('Loan Tape (BoE)'!AI32=1,"Yes","No") | AO31: =IF('Loan Tape (BoE)'!AJ32=1,"Yes","No") | AP31: =IF(OR('Loan Tape (BoE)'!AQ31=1,'Loan Tape (BoE)'!AQ31=2),"Yes",IF('Loan Tape (BoE)'!AQ31=0,"No","")) | AQ31: =IF('Loan Tape (BoE)'!BV49_31<>"",'Loan Tape (BoE)'!BV49_31,"") | AR31: =IF('Loan Tape (BoE)'!BV310_31<>"",'Loan Tape (BoE)'!BV50_31,"") | AS31: =IFERROR(INDEX('FF Adj Parameters'!$A$103:$B$1031,MATCH('Loan Tape (BoE)'!P31,INDEX('FF Adj Parameters'!$A$103:$B$1031,,1),0),2),"Unknown") | AT31: =IF(N31="Interest Only",M5*O5/12,IF(AND(O5>0,ISNUMBER(O5),ISNUMBER(M5)),ABS(PMT(O5/12,AU5,-M5)),0)) | AU31: =IF(ISNUMBER(L31),MAX(0,(L5-'Control Panel'!$B$10)*12/365.25),0) | AV31: =IF(ISNUMBER(L31),IF(L5>'Control Panel'!$B$10,"Valid","Past Maturity"),"No Date") | AW31: =IF(ISNUMBER(K31),MAX(0,('Control Panel'!$B$10-K5)*12/365.25),0)
A32: ='Loan Tape (BoE)'!A33 | B32: =IFERROR(INDEX('FF Adj Parameters'!$A$89:$B$92,MATCH('Loan Tape (BoE)'!C32,INDEX('FF Adj Parameters'!$A$89:$B$92,,1),0),2),"Unknown") | C32: ='Loan Tape (BoE)'!C33 | D32: ='Loan Tape (BoE)'!D33 | E32: ='Loan Tape (BoE)'!E33 | F32: ='Loan Tape (BoE)'!F33 | G32: ='Loan Tape (BoE)'!G33 | H32: ='Loan Tape (BoE)'!H33/100 | I32: =IFERROR(IFS('Loan Tape (BoE)'!I33=1,"House",'Loan Tape (BoE)'!I33=2,"Flat",'Loan Tape (BoE)'!I33=3,"Bungalow",'Loan Tape (BoE)'!I33=4,"Maisonette"),"") | J32: ='Loan Tape (BoE)'!J33 | K32: ='Loan Tape (BoE)'!K33 | L32: =IFERROR(IFS('Loan Tape (BoE)'!L33=1,"Owner Occupied",'Loan Tape (BoE)'!L33=2,"BTL",'Loan Tape (BoE)'!L33=3,"Second Home",'Loan Tape (BoE)'!L33=4,"Investment"),"") | M32: =IFERROR(IFS('Loan Tape (BoE)'!M33=1,"Purchase",'Loan Tape (BoE)'!M33=2,"Remortgage",OR('Loan Tape (BoE)'!M33=3,'Loan Tape (BoE)'!M33=4),"Cash-out"),"") | N32: =IFERROR(INDEX('FF Adj Parameters'!$A$96:$B$99,MATCH('Loan Tape (BoE)'!R32,INDEX('FF Adj Parameters'!$A$96:$B$99,,1),0),2),"Unknown") | O32: =IF('Loan Tape (BoE)'!O33=1,"Yes","No") | P32: =IF('Loan Tape (BoE)'!P32=1,"Yes",IF('Loan Tape (BoE)'!P32=0,"No","")) | Q32: =IF('Loan Tape (BoE)'!Q32=1,"Yes",IF('Loan Tape (BoE)'!Q32=0,"No","")) | R32: =IF('Loan Tape (BoE)'!R32=1,"Yes",IF('Loan Tape (BoE)'!R32=0,"No","")) | S32: =IF('Loan Tape (BoE)'!S32=1,"Yes",IF('Loan Tape (BoE)'!S32=0,"No","")) | T32: =IF('Loan Tape (BoE)'!T32=1,"Yes",IF('Loan Tape (BoE)'!T32=0,"No","")) | U32: =R32+S32 | V32: =IFERROR(IFS('Loan Tape (BoE)'!U33=1,"Employed",'Loan Tape (BoE)'!U33=2,"Self-Employed",'Loan Tape (BoE)'!U33=3,"Unemployed",'Loan Tape (BoE)'!U33=4,"Retired"),"") | W32: =IFERROR(IFS('Loan Tape (BoE)'!V33=1,"Employed",'Loan Tape (BoE)'!V33=2,"Self-Employed",'Loan Tape (BoE)'!V33=3,"Unemployed",'Loan Tape (BoE)'!V33=4,"Retired"),"") | X32: =IF(OR(V32="Self-Employed",W32="Self-Employed"),"Yes","No") | Y32: ='Loan Tape (BoE)'!W33 | Z32: ='Loan Tape (BoE)'!X33 | AA32: =IF(T32=1,Y32,MIN(Y32,Z32)) | AB32: ='Loan Tape (BoE)'!Y33 | AC32: ='Loan Tape (BoE)'!Z33 | AD32: =AB32+AC32 | AE32: ='Loan Tape (BoE)'!AA33 | AF32: ='Loan Tape (BoE)'!AB33 | AG32: =AE32+AF32 | AH32: =MAX('Loan Tape (BoE)'!AC33,'Loan Tape (BoE)'!AD33) | AI32: ='Loan Tape (BoE)'!AE33 | AJ32: =B32*H32/12 | AK32: =IF(AJ32>0,AI32/AJ32,0) | AL32: =IF('Loan Tape (BoE)'!AF33=1,"Yes","No") | AM32: =IF('Loan Tape (BoE)'!AH33=1,"Yes","No") | AN32: =IF('Loan Tape (BoE)'!AI33=1,"Yes","No") | AO32: =IF('Loan Tape (BoE)'!AJ33=1,"Yes","No") | AP32: =IF(OR('Loan Tape (BoE)'!AQ32=1,'Loan Tape (BoE)'!AQ32=2),"Yes",IF('Loan Tape (BoE)'!AQ32=0,"No","")) | AQ32: =IF('Loan Tape (BoE)'!BV49_32<>"",'Loan Tape (BoE)'!BV49_32,"") | AR32: =IF('Loan Tape (BoE)'!BV320_32<>"",'Loan Tape (BoE)'!BV50_32,"") | AS32: =IFERROR(INDEX('FF Adj Parameters'!$A$103:$B$1032,MATCH('Loan Tape (BoE)'!P32,INDEX('FF Adj Parameters'!$A$103:$B$1032,,1),0),2),"Unknown") | AT32: =IF(N32="Interest Only",M5*O5/12,IF(AND(O5>0,ISNUMBER(O5),ISNUMBER(M5)),ABS(PMT(O5/12,AU5,-M5)),0)) | AU32: =IF(ISNUMBER(L32),MAX(0,(L5-'Control Panel'!$B$10)*12/365.25),0) | AV32: =IF(ISNUMBER(L32),IF(L5>'Control Panel'!$B$10,"Valid","Past Maturity"),"No Date") | AW32: =IF(ISNUMBER(K32),MAX(0,('Control Panel'!$B$10-K5)*12/365.25),0)
A33: ='Loan Tape (BoE)'!A34 | B33: =IFERROR(INDEX('FF Adj Parameters'!$A$89:$B$92,MATCH('Loan Tape (BoE)'!C33,INDEX('FF Adj Parameters'!$A$89:$B$92,,1),0),2),"Unknown") | C33: ='Loan Tape (BoE)'!C34 | D33: ='Loan Tape (BoE)'!D34 | E33: ='Loan Tape (BoE)'!E34 | F33: ='Loan Tape (BoE)'!F34 | G33: ='Loan Tape (BoE)'!G34 | H33: ='Loan Tape (BoE)'!H34/100 | I33: =IFERROR(IFS('Loan Tape (BoE)'!I34=1,"House",'Loan Tape (BoE)'!I34=2,"Flat",'Loan Tape (BoE)'!I34=3,"Bungalow",'Loan Tape (BoE)'!I34=4,"Maisonette"),"") | J33: ='Loan Tape (BoE)'!J34 | K33: ='Loan Tape (BoE)'!K34 | L33: =IFERROR(IFS('Loan Tape (BoE)'!L34=1,"Owner Occupied",'Loan Tape (BoE)'!L34=2,"BTL",'Loan Tape (BoE)'!L34=3,"Second Home",'Loan Tape (BoE)'!L34=4,"Investment"),"") | M33: =IFERROR(IFS('Loan Tape (BoE)'!M34=1,"Purchase",'Loan Tape (BoE)'!M34=2,"Remortgage",OR('Loan Tape (BoE)'!M34=3,'Loan Tape (BoE)'!M34=4),"Cash-out"),"") | N33: =IFERROR(INDEX('FF Adj Parameters'!$A$96:$B$99,MATCH('Loan Tape (BoE)'!R33,INDEX('FF Adj Parameters'!$A$96:$B$99,,1),0),2),"Unknown") | O33: =IF('Loan Tape (BoE)'!O34=1,"Yes","No") | P33: =IF('Loan Tape (BoE)'!P33=1,"Yes",IF('Loan Tape (BoE)'!P33=0,"No","")) | Q33: =IF('Loan Tape (BoE)'!Q33=1,"Yes",IF('Loan Tape (BoE)'!Q33=0,"No","")) | R33: =IF('Loan Tape (BoE)'!R33=1,"Yes",IF('Loan Tape (BoE)'!R33=0,"No","")) | S33: =IF('Loan Tape (BoE)'!S33=1,"Yes",IF('Loan Tape (BoE)'!S33=0,"No","")) | T33: =IF('Loan Tape (BoE)'!T33=1,"Yes",IF('Loan Tape (BoE)'!T33=0,"No","")) | U33: =R33+S33 | V33: =IFERROR(IFS('Loan Tape (BoE)'!U34=1,"Employed",'Loan Tape (BoE)'!U34=2,"Self-Employed",'Loan Tape (BoE)'!U34=3,"Unemployed",'Loan Tape (BoE)'!U34=4,"Retired"),"") | W33: =IFERROR(IFS('Loan Tape (BoE)'!V34=1,"Employed",'Loan Tape (BoE)'!V34=2,"Self-Employed",'Loan Tape (BoE)'!V34=3,"Unemployed",'Loan Tape (BoE)'!V34=4,"Retired"),"") | X33: =IF(OR(V33="Self-Employed",W33="Self-Employed"),"Yes","No") | Y33: ='Loan Tape (BoE)'!W34 | Z33: ='Loan Tape (BoE)'!X34 | AA33: =IF(T33=1,Y33,MIN(Y33,Z33)) | AB33: ='Loan Tape (BoE)'!Y34 | AC33: ='Loan Tape (BoE)'!Z34 | AD33: =AB33+AC33 | AE33: ='Loan Tape (BoE)'!AA34 | AF33: ='Loan Tape (BoE)'!AB34 | AG33: =AE33+AF33 | AH33: =MAX('Loan Tape (BoE)'!AC34,'Loan Tape (BoE)'!AD34) | AI33: ='Loan Tape (BoE)'!AE34 | AJ33: =B33*H33/12 | AK33: =IF(AJ33>0,AI33/AJ33,0) | AL33: =IF('Loan Tape (BoE)'!AF34=1,"Yes","No") | AM33: =IF('Loan Tape (BoE)'!AH34=1,"Yes","No") | AN33: =IF('Loan Tape (BoE)'!AI34=1,"Yes","No") | AO33: =IF('Loan Tape (BoE)'!AJ34=1,"Yes","No") | AP33: =IF(OR('Loan Tape (BoE)'!AQ33=1,'Loan Tape (BoE)'!AQ33=2),"Yes",IF('Loan Tape (BoE)'!AQ33=0,"No","")) | AQ33: =IF('Loan Tape (BoE)'!BV49_33<>"",'Loan Tape (BoE)'!BV49_33,"") | AR33: =IF('Loan Tape (BoE)'!BV330_33<>"",'Loan Tape (BoE)'!BV50_33,"") | AS33: =IFERROR(INDEX('FF Adj Parameters'!$A$103:$B$1033,MATCH('Loan Tape (BoE)'!P33,INDEX('FF Adj Parameters'!$A$103:$B$1033,,1),0),2),"Unknown") | AT33: =IF(N33="Interest Only",M5*O5/12,IF(AND(O5>0,ISNUMBER(O5),ISNUMBER(M5)),ABS(PMT(O5/12,AU5,-M5)),0)) | AU33: =IF(ISNUMBER(L33),MAX(0,(L5-'Control Panel'!$B$10)*12/365.25),0) | AV33: =IF(ISNUMBER(L33),IF(L5>'Control Panel'!$B$10,"Valid","Past Maturity"),"No Date") | AW33: =IF(ISNUMBER(K33),MAX(0,('Control Panel'!$B$10-K5)*12/365.25),0)
A34: ='Loan Tape (BoE)'!A35 | B34: =IFERROR(INDEX('FF Adj Parameters'!$A$89:$B$92,MATCH('Loan Tape (BoE)'!C34,INDEX('FF Adj Parameters'!$A$89:$B$92,,1),0),2),"Unknown") | C34: ='Loan Tape (BoE)'!C35 | D34: ='Loan Tape (BoE)'!D35 | E34: ='Loan Tape (BoE)'!E35 | F34: ='Loan Tape (BoE)'!F35 | G34: ='Loan Tape (BoE)'!G35 | H34: ='Loan Tape (BoE)'!H35/100 | I34: =IFERROR(IFS('Loan Tape (BoE)'!I35=1,"House",'Loan Tape (BoE)'!I35=2,"Flat",'Loan Tape (BoE)'!I35=3,"Bungalow",'Loan Tape (BoE)'!I35=4,"Maisonette"),"") | J34: ='Loan Tape (BoE)'!J35 | K34: ='Loan Tape (BoE)'!K35 | L34: =IFERROR(IFS('Loan Tape (BoE)'!L35=1,"Owner Occupied",'Loan Tape (BoE)'!L35=2,"BTL",'Loan Tape (BoE)'!L35=3,"Second Home",'Loan Tape (BoE)'!L35=4,"Investment"),"") | M34: =IFERROR(IFS('Loan Tape (BoE)'!M35=1,"Purchase",'Loan Tape (BoE)'!M35=2,"Remortgage",OR('Loan Tape (BoE)'!M35=3,'Loan Tape (BoE)'!M35=4),"Cash-out"),"") | N34: =IFERROR(INDEX('FF Adj Parameters'!$A$96:$B$99,MATCH('Loan Tape (BoE)'!R34,INDEX('FF Adj Parameters'!$A$96:$B$99,,1),0),2),"Unknown") | O34: =IF('Loan Tape (BoE)'!O35=1,"Yes","No") | P34: =IF('Loan Tape (BoE)'!P34=1,"Yes",IF('Loan Tape (BoE)'!P34=0,"No","")) | Q34: =IF('Loan Tape (BoE)'!Q34=1,"Yes",IF('Loan Tape (BoE)'!Q34=0,"No","")) | R34: =IF('Loan Tape (BoE)'!R34=1,"Yes",IF('Loan Tape (BoE)'!R34=0,"No","")) | S34: =IF('Loan Tape (BoE)'!S34=1,"Yes",IF('Loan Tape (BoE)'!S34=0,"No","")) | T34: =IF('Loan Tape (BoE)'!T34=1,"Yes",IF('Loan Tape (BoE)'!T34=0,"No","")) | U34: =R34+S34 | V34: =IFERROR(IFS('Loan Tape (BoE)'!U35=1,"Employed",'Loan Tape (BoE)'!U35=2,"Self-Employed",'Loan Tape (BoE)'!U35=3,"Unemployed",'Loan Tape (BoE)'!U35=4,"Retired"),"") | W34: =IFERROR(IFS('Loan Tape (BoE)'!V35=1,"Employed",'Loan Tape (BoE)'!V35=2,"Self-Employed",'Loan Tape (BoE)'!V35=3,"Unemployed",'Loan Tape (BoE)'!V35=4,"Retired"),"") | X34: =IF(OR(V34="Self-Employed",W34="Self-Employed"),"Yes","No") | Y34: ='Loan Tape (BoE)'!W35 | Z34: ='Loan Tape (BoE)'!X35 | AA34: =IF(T34=1,Y34,MIN(Y34,Z34)) | AB34: ='Loan Tape (BoE)'!Y35 | AC34: ='Loan Tape (BoE)'!Z35 | AD34: =AB34+AC34 | AE34: ='Loan Tape (BoE)'!AA35 | AF34: ='Loan Tape (BoE)'!AB35 | AG34: =AE34+AF34 | AH34: =MAX('Loan Tape (BoE)'!AC35,'Loan Tape (BoE)'!AD35) | AI34: ='Loan Tape (BoE)'!AE35 | AJ34: =B34*H34/12 | AK34: =IF(AJ34>0,AI34/AJ34,0) | AL34: =IF('Loan Tape (BoE)'!AF35=1,"Yes","No") | AM34: =IF('Loan Tape (BoE)'!AH35=1,"Yes","No") | AN34: =IF('Loan Tape (BoE)'!AI35=1,"Yes","No") | AO34: =IF('Loan Tape (BoE)'!AJ35=1,"Yes","No") | AP34: =IF(OR('Loan Tape (BoE)'!AQ34=1,'Loan Tape (BoE)'!AQ34=2),"Yes",IF('Loan Tape (BoE)'!AQ34=0,"No","")) | AQ34: =IF('Loan Tape (BoE)'!BV49_34<>"",'Loan Tape (BoE)'!BV49_34,"") | AR34: =IF('Loan Tape (BoE)'!BV340_34<>"",'Loan Tape (BoE)'!BV50_34,"") | AS34: =IFERROR(INDEX('FF Adj Parameters'!$A$103:$B$1034,MATCH('Loan Tape (BoE)'!P34,INDEX('FF Adj Parameters'!$A$103:$B$1034,,1),0),2),"Unknown") | AT34: =IF(N34="Interest Only",M5*O5/12,IF(AND(O5>0,ISNUMBER(O5),ISNUMBER(M5)),ABS(PMT(O5/12,AU5,-M5)),0)) | AU34: =IF(ISNUMBER(L34),MAX(0,(L5-'Control Panel'!$B$10)*12/365.25),0) | AV34: =IF(ISNUMBER(L34),IF(L5>'Control Panel'!$B$10,"Valid","Past Maturity"),"No Date") | AW34: =IF(ISNUMBER(K34),MAX(0,('Control Panel'!$B$10-K5)*12/365.25),0)
A35: ='Loan Tape (BoE)'!A36 | B35: =IFERROR(INDEX('FF Adj Parameters'!$A$89:$B$92,MATCH('Loan Tape (BoE)'!C35,INDEX('FF Adj Parameters'!$A$89:$B$92,,1),0),2),"Unknown") | C35: ='Loan Tape (BoE)'!C36 | D35: ='Loan Tape (BoE)'!D36 | E35: ='Loan Tape (BoE)'!E36 | F35: ='Loan Tape (BoE)'!F36 | G35: ='Loan Tape (BoE)'!G36 | H35: ='Loan Tape (BoE)'!H36/100 | I35: =IFERROR(IFS('Loan Tape (BoE)'!I36=1,"House",'Loan Tape (BoE)'!I36=2,"Flat",'Loan Tape (BoE)'!I36=3,"Bungalow",'Loan Tape (BoE)'!I36=4,"Maisonette"),"") | J35: ='Loan Tape (BoE)'!J36 | K35: ='Loan Tape (BoE)'!K36 | L35: =IFERROR(IFS('Loan Tape (BoE)'!L36=1,"Owner Occupied",'Loan Tape (BoE)'!L36=2,"BTL",'Loan Tape (BoE)'!L36=3,"Second Home",'Loan Tape (BoE)'!L36=4,"Investment"),"") | M35: =IFERROR(IFS('Loan Tape (BoE)'!M36=1,"Purchase",'Loan Tape (BoE)'!M36=2,"Remortgage",OR('Loan Tape (BoE)'!M36=3,'Loan Tape (BoE)'!M36=4),"Cash-out"),"") | N35: =IFERROR(INDEX('FF Adj Parameters'!$A$96:$B$99,MATCH('Loan Tape (BoE)'!R35,INDEX('FF Adj Parameters'!$A$96:$B$99,,1),0),2),"Unknown") | O35: =IF('Loan Tape (BoE)'!O36=1,"Yes","No") | P35: =IF('Loan Tape (BoE)'!P35=1,"Yes",IF('Loan Tape (BoE)'!P35=0,"No","")) | Q35: =IF('Loan Tape (BoE)'!Q35=1,"Yes",IF('Loan Tape (BoE)'!Q35=0,"No","")) | R35: =IF('Loan Tape (BoE)'!R35=1,"Yes",IF('Loan Tape (BoE)'!R35=0,"No","")) | S35: =IF('Loan Tape (BoE)'!S35=1,"Yes",IF('Loan Tape (BoE)'!S35=0,"No","")) | T35: =IF('Loan Tape (BoE)'!T35=1,"Yes",IF('Loan Tape (BoE)'!T35=0,"No","")) | U35: =R35+S35 | V35: =IFERROR(IFS('Loan Tape (BoE)'!U36=1,"Employed",'Loan Tape (BoE)'!U36=2,"Self-Employed",'Loan Tape (BoE)'!U36=3,"Unemployed",'Loan Tape (BoE)'!U36=4,"Retired"),"") | W35: =IFERROR(IFS('Loan Tape (BoE)'!V36=1,"Employed",'Loan Tape (BoE)'!V36=2,"Self-Employed",'Loan Tape (BoE)'!V36=3,"Unemployed",'Loan Tape (BoE)'!V36=4,"Retired"),"") | X35: =IF(OR(V35="Self-Employed",W35="Self-Employed"),"Yes","No") | Y35: ='Loan Tape (BoE)'!W36 | Z35: ='Loan Tape (BoE)'!X36 | AA35: =IF(T35=1,Y35,MIN(Y35,Z35)) | AB35: ='Loan Tape (BoE)'!Y36 | AC35: ='Loan Tape (BoE)'!Z36 | AD35: =AB35+AC35 | AE35: ='Loan Tape (BoE)'!AA36 | AF35: ='Loan Tape (BoE)'!AB36 | AG35: =AE35+AF35 | AH35: =MAX('Loan Tape (BoE)'!AC36,'Loan Tape (BoE)'!AD36) | AI35: ='Loan Tape (BoE)'!AE36 | AJ35: =B35*H35/12 | AK35: =IF(AJ35>0,AI35/AJ35,0) | AL35: =IF('Loan Tape (BoE)'!AF36=1,"Yes","No") | AM35: =IF('Loan Tape (BoE)'!AH36=1,"Yes","No") | AN35: =IF('Loan Tape (BoE)'!AI36=1,"Yes","No") | AO35: =IF('Loan Tape (BoE)'!AJ36=1,"Yes","No") | AP35: =IF(OR('Loan Tape (BoE)'!AQ35=1,'Loan Tape (BoE)'!AQ35=2),"Yes",IF('Loan Tape (BoE)'!AQ35=0,"No","")) | AQ35: =IF('Loan Tape (BoE)'!BV49_335<>"",'Loan Tape (BoE)'!BV49_35,"") | AR35: =IF('Loan Tape (BoE)'!BV350_35<>"",'Loan Tape (BoE)'!BV50_35,"") | AS35: =IFERROR(INDEX('FF Adj Parameters'!$A$103:$B$1035,MATCH('Loan Tape (BoE)'!P35,INDEX('FF Adj Parameters'!$A$103:$B$1035,,1),0),2),"Unknown") | AT35: =IF(N35="Interest Only",M5*O5/12,IF(AND(O5>0,ISNUMBER(O5),ISNUMBER(M5)),ABS(PMT(O5/12,AU5,-M5)),0)) | AU35: =IF(ISNUMBER(L35),MAX(0,(L5-'Control Panel'!$B$10)*12/365.25),0) | AV35: =IF(ISNUMBER(L35),IF(L5>'Control Panel'!$B$10,"Valid","Past Maturity"),"No Date") | AW35: =IF(ISNUMBER(K35),MAX(0,('Control Panel'!$B$10-K5)*12/365.25),0)
A36: ='Loan Tape (BoE)'!A37 | B36: =IFERROR(INDEX('FF Adj Parameters'!$A$89:$B$92,MATCH('Loan Tape (BoE)'!C36,INDEX('FF Adj Parameters'!$A$89:$B$92,,1),0),2),"Unknown") | C36: ='Loan Tape (BoE)'!C37 | D36: ='Loan Tape (BoE)'!D37 | E36: ='Loan Tape (BoE)'!E37 | F36: ='Loan Tape (BoE)'!F37 | G36: ='Loan Tape (BoE)'!G37 | H36: ='Loan Tape (BoE)'!H37/100 | I36: =IFERROR(IFS('Loan Tape (BoE)'!I37=1,"House",'Loan Tape (BoE)'!I37=2,"Flat",'Loan Tape (BoE)'!I37=3,"Bungalow",'Loan Tape (BoE)'!I37=4,"Maisonette"),"") | J36: ='Loan Tape (BoE)'!J37 | K36: ='Loan Tape (BoE)'!K37 | L36: =IFERROR(IFS('Loan Tape (BoE)'!L37=1,"Owner Occupied",'Loan Tape (BoE)'!L37=2,"BTL",'Loan Tape (BoE)'!L37=3,"Second Home",'Loan Tape (BoE)'!L37=4,"Investment"),"") | M36: =IFERROR(IFS('Loan Tape (BoE)'!M37=1,"Purchase",'Loan Tape (BoE)'!M37=2,"Remortgage",OR('Loan Tape (BoE)'!M37=3,'Loan Tape (BoE)'!M37=4),"Cash-out"),"") | N36: =IFERROR(INDEX('FF Adj Parameters'!$A$96:$B$99,MATCH('Loan Tape (BoE)'!R36,INDEX('FF Adj Parameters'!$A$96:$B$99,,1),0),2),"Unknown") | O36: =IF('Loan Tape (BoE)'!O37=1,"Yes","No") | P36: =IF('Loan Tape (BoE)'!P36=1,"Yes",IF('Loan Tape (BoE)'!P36=0,"No","")) | Q36: =IF('Loan Tape (BoE)'!Q36=1,"Yes",IF('Loan Tape (BoE)'!Q36=0,"No","")) | R36: =IF('Loan Tape (BoE)'!R36=1,"Yes",IF('Loan Tape (BoE)'!R36=0,"No","")) | S36: =IF('Loan Tape (BoE)'!S36=1,"Yes",IF('Loan Tape (BoE)'!S36=0,"No","")) | T36: =IF('Loan Tape (BoE)'!T36=1,"Yes",IF('Loan Tape (BoE)'!T36=0,"No","")) | U36: =R36+S36 | V36: =IFERROR(IFS('Loan Tape (BoE)'!U37=1,"Employed",'Loan Tape (BoE)'!U37=2,"Self-Employed",'Loan Tape (BoE)'!U37=3,"Unemployed",'Loan Tape (BoE)'!U37=4,"Retired"),"") | W36: =IFERROR(IFS('Loan Tape (BoE)'!V37=1,"Employed",'Loan Tape (BoE)'!V37=2,"Self-Employed",'Loan Tape (BoE)'!V37=3,"Unemployed",'Loan Tape (BoE)'!V37=4,"Retired"),"") | X36: =IF(OR(V36="Self-Employed",W36="Self-Employed"),"Yes","No") | Y36: ='Loan Tape (BoE)'!W37 | Z36: ='Loan Tape (BoE)'!X37 | AA36: =IF(T36=1,Y36,MIN(Y36,Z36)) | AB36: ='Loan Tape (BoE)'!Y37 | AC36: ='Loan Tape (BoE)'!Z37 | AD36: =AB36+AC36 | AE36: ='Loan Tape (BoE)'!AA37 | AF36: ='Loan Tape (BoE)'!AB37 | AG36: =AE36+AF36 | AH36: =MAX('Loan Tape (BoE)'!AC37,'Loan Tape (BoE)'!AD37) | AI36: ='Loan Tape (BoE)'!AE37 | AJ36: =B36*H36/12 | AK36: =IF(AJ36>0,AI36/AJ36,0) | AL36: =IF('Loan Tape (BoE)'!AF37=1,"Yes","No") | AM36: =IF('Loan Tape (BoE)'!AH37=1,"Yes","No") | AN36: =IF('Loan Tape (BoE)'!AI37=1,"Yes","No") | AO36: =IF('Loan Tape (BoE)'!AJ37=1,"Yes","No") | AP36: =IF(OR('Loan Tape (BoE)'!AQ36=1,'Loan Tape (BoE)'!AQ36=2),"Yes",IF('Loan Tape (BoE)'!AQ36=0,"No","")) | AQ36: =IF('Loan Tape (BoE)'!BV49_36<>"",'Loan Tape (BoE)'!BV49_36,"") | AR36: =IF('Loan Tape (BoE)'!BV360_36<>"",'Loan Tape (BoE)'!BV50_36,"") | AS36: =IFERROR(INDEX('FF Adj Parameters'!$A$103:$B$1036,MATCH('Loan Tape (BoE)'!P36,INDEX('FF Adj Parameters'!$A$103:$B$1036,,1),0),2),"Unknown") | AT36: =IF(N36="Interest Only",M5*O5/12,IF(AND(O5>0,ISNUMBER(O5),ISNUMBER(M5)),ABS(PMT(O5/12,AU5,-M5)),0)) | AU36: =IF(ISNUMBER(L36),MAX(0,(L5-'Control Panel'!$B$10)*12/365.25),0) | AV36: =IF(ISNUMBER(L36),IF(L5>'Control Panel'!$B$10,"Valid","Past Maturity"),"No Date") | AW36: =IF(ISNUMBER(K36),MAX(0,('Control Panel'!$B$10-K5)*12/365.25),0)
A37: ='Loan Tape (BoE)'!A38 | B37: =IFERROR(INDEX('FF Adj Parameters'!$A$89:$B$92,MATCH('Loan Tape (BoE)'!C37,INDEX('FF Adj Parameters'!$A$89:$B$92,,1),0),2),"Unknown") | C37: ='Loan Tape (BoE)'!C38 | D37: ='Loan Tape (BoE)'!D38 | E37: ='Loan Tape (BoE)'!E38 | F37: ='Loan Tape (BoE)'!F38 | G37: ='Loan Tape (BoE)'!G38 | H37: ='Loan Tape (BoE)'!H38/100 | I37: =IFERROR(IFS('Loan Tape (BoE)'!I38=1,"House",'Loan Tape (BoE)'!I38=2,"Flat",'Loan Tape (BoE)'!I38=3,"Bungalow",'Loan Tape (BoE)'!I38=4,"Maisonette"),"") | J37: ='Loan Tape (BoE)'!J38 | K37: ='Loan Tape (BoE)'!K38 | L37: =IFERROR(IFS('Loan Tape (BoE)'!L38=1,"Owner Occupied",'Loan Tape (BoE)'!L38=2,"BTL",'Loan Tape (BoE)'!L38=3,"Second Home",'Loan Tape (BoE)'!L38=4,"Investment"),"") | M37: =IFERROR(IFS('Loan Tape (BoE)'!M38=1,"Purchase",'Loan Tape (BoE)'!M38=2,"Remortgage",OR('Loan Tape (BoE)'!M38=3,'Loan Tape (BoE)'!M38=4),"Cash-out"),"") | N37: =IFERROR(INDEX('FF Adj Parameters'!$A$96:$B$99,MATCH('Loan Tape (BoE)'!R37,INDEX('FF Adj Parameters'!$A$96:$B$99,,1),0),2),"Unknown") | O37: =IF('Loan Tape (BoE)'!O38=1,"Yes","No") | P37: =IF('Loan Tape (BoE)'!P37=1,"Yes",IF('Loan Tape (BoE)'!P37=0,"No","")) | Q37: =IF('Loan Tape (BoE)'!Q37=1,"Yes",IF('Loan Tape (BoE)'!Q37=0,"No","")) | R37: =IF('Loan Tape (BoE)'!R37=1,"Yes",IF('Loan Tape (BoE)'!R37=0,"No","")) | S37: =IF('Loan Tape (BoE)'!S37=1,"Yes",IF('Loan Tape (BoE)'!S37=0,"No","")) | T37: =IF('Loan Tape (BoE)'!T37=1,"Yes",IF('Loan Tape (BoE)'!T37=0,"No","")) | U37: =R37+S37 | V37: =IFERROR(IFS('Loan Tape (BoE)'!U38=1,"Employed",'Loan Tape (BoE)'!U38=2,"Self-Employed",'Loan Tape (BoE)'!U38=3,"Unemployed",'Loan Tape (BoE)'!U38=4,"Retired"),"") | W37: =IFERROR(IFS('Loan Tape (BoE)'!V38=1,"Employed",'Loan Tape (BoE)'!V38=2,"Self-Employed",'Loan Tape (BoE)'!V38=3,"Unemployed",'Loan Tape (BoE)'!V38=4,"Retired"),"") | X37: =IF(OR(V37="Self-Employed",W37="Self-Employed"),"Yes","No") | Y37: ='Loan Tape (BoE)'!W38 | Z37: ='Loan Tape (BoE)'!X38 | AA37: =IF(T37=1,Y37,MIN(Y37,Z37)) | AB37: ='Loan Tape (BoE)'!Y38 | AC37: ='Loan Tape (BoE)'!Z38 | AD37: =AB37+AC37 | AE37: ='Loan Tape (BoE)'!AA38 | AF37: ='Loan Tape (BoE)'!AB38 | AG37: =AE37+AF37 | AH37: =MAX('Loan Tape (BoE)'!AC38,'Loan Tape (BoE)'!AD38) | AI37: ='Loan Tape (BoE)'!AE38 | AJ37: =B37*H37/12 | AK37: =IF(AJ37>0,AI37/AJ37,0) | AL37: =IF('Loan Tape (BoE)'!AF38=1,"Yes","No") | AM37: =IF('Loan Tape (BoE)'!AH38=1,"Yes","No") | AN37: =IF('Loan Tape (BoE)'!AI38=1,"Yes","No") | AO37: =IF('Loan Tape (BoE)'!AJ38=1,"Yes","No") | AP37: =IF(OR('Loan Tape (BoE)'!AQ37=1,'Loan Tape (BoE)'!AQ37=2),"Yes",IF('Loan Tape (BoE)'!AQ37=0,"No","")) | AQ37: =IF('Loan Tape (BoE)'!BV49_37<>"",'Loan Tape (BoE)'!BV49_37,"") | AR37: =IF('Loan Tape (BoE)'!BV370_37<>"",'Loan Tape (BoE)'!BV50_37,"") | AS37: =IFERROR(INDEX('FF Adj Parameters'!$A$103:$B$1037,MATCH('Loan Tape (BoE)'!P37,INDEX('FF Adj Parameters'!$A$103:$B$1037,,1),0),2),"Unknown") | AT37: =IF(N37="Interest Only",M5*O5/12,IF(AND(O5>0,ISNUMBER(O5),ISNUMBER(M5)),ABS(PMT(O5/12,AU5,-M5)),0)) | AU37: =IF(ISNUMBER(L37),MAX(0,(L5-'Control Panel'!$B$10)*12/365.25),0) | AV37: =IF(ISNUMBER(L37),IF(L5>'Control Panel'!$B$10,"Valid","Past Maturity"),"No Date") | AW37: =IF(ISNUMBER(K37),MAX(0,('Control Panel'!$B$10-K5)*12/365.25),0)
A38: ='Loan Tape (BoE)'!A39 | B38: =IFERROR(INDEX('FF Adj Parameters'!$A$89:$B$92,MATCH('Loan Tape (BoE)'!C38,INDEX('FF Adj Parameters'!$A$89:$B$92,,1),0),2),"Unknown") | C38: ='Loan Tape (BoE)'!C39 | D38: ='Loan Tape (BoE)'!D39 | E38: ='Loan Tape (BoE)'!E39 | F38: ='Loan Tape (BoE)'!F39 | G38: ='Loan Tape (BoE)'!G39 | H38: ='Loan Tape (BoE)'!H39/100 | I38: =IFERROR(IFS('Loan Tape (BoE)'!I39=1,"House",'Loan Tape (BoE)'!I39=2,"Flat",'Loan Tape (BoE)'!I39=3,"Bungalow",'Loan Tape (BoE)'!I39=4,"Maisonette"),"") | J38: ='Loan Tape (BoE)'!J39 | K38: ='Loan Tape (BoE)'!K39 | L38: =IFERROR(IFS('Loan Tape (BoE)'!L39=1,"Owner Occupied",'Loan Tape (BoE)'!L39=2,"BTL",'Loan Tape (BoE)'!L39=3,"Second Home",'Loan Tape (BoE)'!L39=4,"Investment"),"") | M38: =IFERROR(IFS('Loan Tape (BoE)'!M39=1,"Purchase",'Loan Tape (BoE)'!M39=2,"Remortgage",OR('Loan Tape (BoE)'!M39=3,'Loan Tape (BoE)'!M39=4),"Cash-out"),"") | N38: =IFERROR(INDEX('FF Adj Parameters'!$A$96:$B$99,MATCH('Loan Tape (BoE)'!R38,INDEX('FF Adj Parameters'!$A$96:$B$99,,1),0),2),"Unknown") | O38: =IF('Loan Tape (BoE)'!O39=1,"Yes","No") | P38: =IF('Loan Tape (BoE)'!P38=1,"Yes",IF('Loan Tape (BoE)'!P38=0,"No","")) | Q38: =IF('Loan Tape (BoE)'!Q38=1,"Yes",IF('Loan Tape (BoE)'!Q38=0,"No","")) | R38: =IF('Loan Tape (BoE)'!R38=1,"Yes",IF('Loan Tape (BoE)'!R38=0,"No","")) | S38: =IF('Loan Tape (BoE)'!S38=1,"Yes",IF('Loan Tape (BoE)'!S38=0,"No","")) | T38: =IF('Loan Tape (BoE)'!T38=1,"Yes",IF('Loan Tape (BoE)'!T38=0,"No","")) | U38: =R38+S38 | V38: =IFERROR(IFS('Loan Tape (BoE)'!U39=1,"Employed",'Loan Tape (BoE)'!U39=2,"Self-Employed",'Loan Tape (BoE)'!U39=3,"Unemployed",'Loan Tape (BoE)'!U39=4,"Retired"),"") | W38: =IFERROR(IFS('Loan Tape (BoE)'!V39=1,"Employed",'Loan Tape (BoE)'!V39=2,"Self-Employed",'Loan Tape (BoE)'!V39=3,"Unemployed",'Loan Tape (BoE)'!V39=4,"Retired"),"") | X38: =IF(OR(V38="Self-Employed",W38="Self-Employed"),"Yes","No") | Y38: ='Loan Tape (BoE)'!W39 | Z38: ='Loan Tape (BoE)'!X39 | AA38: =IF(T38=1,Y38,MIN(Y38,Z38)) | AB38: ='Loan Tape (BoE)'!Y39 | AC38: ='Loan Tape (BoE)'!Z39 | AD38: =AB38+AC38 | AE38: ='Loan Tape (BoE)'!AA39 | AF38: ='Loan Tape (BoE)'!AB39 | AG38: =AE38+AF38 | AH38: =MAX('Loan Tape (BoE)'!AC39,'Loan Tape (BoE)'!AD39) | AI38: ='Loan Tape (BoE)'!AE39 | AJ38: =B38*H38/12 | AK38: =IF(AJ38>0,AI38/AJ38,0) | AL38: =IF('Loan Tape (BoE)'!AF39=1,"Yes","No") | AM38: =IF('Loan Tape (BoE)'!AH39=1,"Yes","No") | AN38: =IF('Loan Tape (BoE)'!AI39=1,"Yes","No") | AO38: =IF('Loan Tape (BoE)'!AJ39=1,"Yes","No") | AP38: =IF(OR('Loan Tape (BoE)'!AQ38=1,'Loan Tape (BoE)'!AQ38=2),"Yes",IF('Loan Tape (BoE)'!AQ38=0,"No","")) | AQ38: =IF('Loan Tape (BoE)'!BV49_38<>"",'Loan Tape (BoE)'!BV49_38,"") | AR38: =IF('Loan Tape (BoE)'!BV380_38<>"",'Loan Tape (BoE)'!BV50_38,"") | AS38: =IFERROR(INDEX('FF Adj Parameters'!$A$103:$B$1038,MATCH('Loan Tape (BoE)'!P38,INDEX('FF Adj Parameters'!$A$103:$B$1038,,1),0),2),"Unknown") | AT38: =IF(N38="Interest Only",M5*O5/12,IF(AND(O5>0,ISNUMBER(O5),ISNUMBER(M5)),ABS(PMT(O5/12,AU5,-M5)),0)) | AU38: =IF(ISNUMBER(L38),MAX(0,(L5-'Control Panel'!$B$10)*12/365.25),0) | AV38: =IF(ISNUMBER(L38),IF(L5>'Control Panel'!$B$10,"Valid","Past Maturity"),"No Date") | AW38: =IF(ISNUMBER(K38),MAX(0,('Control Panel'!$B$10-K5)*12/365.25),0)
A39: ='Loan Tape (BoE)'!A40 | B39: =IFERROR(INDEX('FF Adj Parameters'!$A$89:$B$92,MATCH('Loan Tape (BoE)'!C39,INDEX('FF Adj Parameters'!$A$89:$B$92,,1),0),2),"Unknown") | C39: ='Loan Tape (BoE)'!C40 | D39: ='Loan Tape (BoE)'!D40 | E39: ='Loan Tape (BoE)'!E40 | F39: ='Loan Tape (BoE)'!F40 | G39: ='Loan Tape (BoE)'!G40 | H39: ='Loan Tape (BoE)'!H40/100 | I39: =IFERROR(IFS('Loan Tape (BoE)'!I40=1,"House",'Loan Tape (BoE)'!I40=2,"Flat",'Loan Tape (BoE)'!I40=3,"Bungalow",'Loan Tape (BoE)'!I40=4,"Maisonette"),"") | J39: ='Loan Tape (BoE)'!J40 | K39: ='Loan Tape (BoE)'!K40 | L39: =IFERROR(IFS('Loan Tape (BoE)'!L40=1,"Owner Occupied",'Loan Tape (BoE)'!L40=2,"BTL",'Loan Tape (BoE)'!L40=3,"Second Home",'Loan Tape (BoE)'!L40=4,"Investment"),"") | M39: =IFERROR(IFS('Loan Tape (BoE)'!M40=1,"Purchase",'Loan Tape (BoE)'!M40=2,"Remortgage",OR('Loan Tape (BoE)'!M40=3,'Loan Tape (BoE)'!M40=4),"Cash-out"),"") | N39: =IFERROR(INDEX('FF Adj Parameters'!$A$96:$B$99,MATCH('Loan Tape (BoE)'!R39,INDEX('FF Adj Parameters'!$A$96:$B$99,,1),0),2),"Unknown") | O39: =IF('Loan Tape (BoE)'!O40=1,"Yes","No") | P39: =IF('Loan Tape (BoE)'!P39=1,"Yes",IF('Loan Tape (BoE)'!P39=0,"No","")) | Q39: =IF('Loan Tape (BoE)'!Q39=1,"Yes",IF('Loan Tape (BoE)'!Q39=0,"No","")) | R39: =IF('Loan Tape (BoE)'!R39=1,"Yes",IF('Loan Tape (BoE)'!R39=0,"No","")) | S39: =IF('Loan Tape (BoE)'!S39=1,"Yes",IF('Loan Tape (BoE)'!S39=0,"No","")) | T39: =IF('Loan Tape (BoE)'!T39=1,"Yes",IF('Loan Tape (BoE)'!T39=0,"No","")) | U39: =R39+S39 | V39: =IFERROR(IFS('Loan Tape (BoE)'!U40=1,"Employed",'Loan Tape (BoE)'!U40=2,"Self-Employed",'Loan Tape (BoE)'!U40=3,"Unemployed",'Loan Tape (BoE)'!U40=4,"Retired"),"") | W39: =IFERROR(IFS('Loan Tape (BoE)'!V40=1,"Employed",'Loan Tape (BoE)'!V40=2,"Self-Employed",'Loan Tape (BoE)'!V40=3,"Unemployed",'Loan Tape (BoE)'!V40=4,"Retired"),"") | X39: =IF(OR(V39="Self-Employed",W39="Self-Employed"),"Yes","No") | Y39: ='Loan Tape (BoE)'!W40 | Z39: ='Loan Tape (BoE)'!X40 | AA39: =IF(T39=1,Y39,MIN(Y39,Z39)) | AB39: ='Loan Tape (BoE)'!Y40 | AC39: ='Loan Tape (BoE)'!Z40 | AD39: =AB39+AC39 | AE39: ='Loan Tape (BoE)'!AA40 | AF39: ='Loan Tape (BoE)'!AB40 | AG39: =AE39+AF39 | AH39: =MAX('Loan Tape (BoE)'!AC40,'Loan Tape (BoE)'!AD40) | AI39: ='Loan Tape (BoE)'!AE40 | AJ39: =B39*H39/12 | AK39: =IF(AJ39>0,AI39/AJ39,0) | AL39: =IF('Loan Tape (BoE)'!AF40=1,"Yes","No") | AM39: =IF('Loan Tape (BoE)'!AH40=1,"Yes","No") | AN39: =IF('Loan Tape (BoE)'!AI40=1,"Yes","No") | AO39: =IF('Loan Tape (BoE)'!AJ40=1,"Yes","No") | AP39: =IF(OR('Loan Tape (BoE)'!AQ39=1,'Loan Tape (BoE)'!AQ39=2),"Yes",IF('Loan Tape (BoE)'!AQ39=0,"No","")) | AQ39: =IF('Loan Tape (BoE)'!BV49_39<>"",'Loan Tape (BoE)'!BV49_39,"") | AR39: =IF('Loan Tape (BoE)'!BV390_39<>"",'Loan Tape (BoE)'!BV50_39,"") | AS39: =IFERROR(INDEX('FF Adj Parameters'!$A$103:$B$1039,MATCH('Loan Tape (BoE)'!P39,INDEX('FF Adj Parameters'!$A$103:$B$1039,,1),0),2),"Unknown") | AT39: =IF(N39="Interest Only",M5*O5/12,IF(AND(O5>0,ISNUMBER(O5),ISNUMBER(M5)),ABS(PMT(O5/12,AU5,-M5)),0)) | AU39: =IF(ISNUMBER(L39),MAX(0,(L5-'Control Panel'!$B$10)*12/365.25),0) | AV39: =IF(ISNUMBER(L39),IF(L5>'Control Panel'!$B$10,"Valid","Past Maturity"),"No Date") | AW39: =IF(ISNUMBER(K39),MAX(0,('Control Panel'!$B$10-K5)*12/365.25),0)
A40: ='Loan Tape (BoE)'!A41 | B40: =IFERROR(INDEX('FF Adj Parameters'!$A$89:$B$92,MATCH('Loan Tape (BoE)'!C40,INDEX('FF Adj Parameters'!$A$89:$B$92,,1),0),2),"Unknown") | C40: ='Loan Tape (BoE)'!C41 | D40: ='Loan Tape (BoE)'!D41 | E40: ='Loan Tape (BoE)'!E41 | F40: ='Loan Tape (BoE)'!F41 | G40: ='Loan Tape (BoE)'!G41 | H40: ='Loan Tape (BoE)'!H41/100 | I40: =IFERROR(IFS('Loan Tape (BoE)'!I41=1,"House",'Loan Tape (BoE)'!I41=2,"Flat",'Loan Tape (BoE)'!I41=3,"Bungalow",'Loan Tape (BoE)'!I41=4,"Maisonette"),"") | J40: ='Loan Tape (BoE)'!J41 | K40: ='Loan Tape (BoE)'!K41 | L40: =IFERROR(IFS('Loan Tape (BoE)'!L41=1,"Owner Occupied",'Loan Tape (BoE)'!L41=2,"BTL",'Loan Tape (BoE)'!L41=3,"Second Home",'Loan Tape (BoE)'!L41=4,"Investment"),"") | M40: =IFERROR(IFS('Loan Tape (BoE)'!M41=1,"Purchase",'Loan Tape (BoE)'!M41=2,"Remortgage",OR('Loan Tape (BoE)'!M41=3,'Loan Tape (BoE)'!M41=4),"Cash-out"),"") | N40: =IFERROR(INDEX('FF Adj Parameters'!$A$96:$B$99,MATCH('Loan Tape (BoE)'!R40,INDEX('FF Adj Parameters'!$A$96:$B$99,,1),0),2),"Unknown") | O40: =IF('Loan Tape (BoE)'!O41=1,"Yes","No") | P40: =IF('Loan Tape (BoE)'!P40=1,"Yes",IF('Loan Tape (BoE)'!P40=0,"No","")) | Q40: =IF('Loan Tape (BoE)'!Q40=1,"Yes",IF('Loan Tape (BoE)'!Q40=0,"No","")) | R40: =IF('Loan Tape (BoE)'!R40=1,"Yes",IF('Loan Tape (BoE)'!R40=0,"No","")) | S40: =IF('Loan Tape (BoE)'!S40=1,"Yes",IF('Loan Tape (BoE)'!S40=0,"No","")) | T40: =IF('Loan Tape (BoE)'!T40=1,"Yes",IF('Loan Tape (BoE)'!T40=0,"No","")) | U40: =R40+S40 | V40: =IFERROR(IFS('Loan Tape (BoE)'!U41=1,"Employed",'Loan Tape (BoE)'!U41=2,"Self-Employed",'Loan Tape (BoE)'!U41=3,"Unemployed",'Loan Tape (BoE)'!U41=4,"Retired"),"") | W40: =IFERROR(IFS('Loan Tape (BoE)'!V41=1,"Employed",'Loan Tape (BoE)'!V41=2,"Self-Employed",'Loan Tape (BoE)'!V41=3,"Unemployed",'Loan Tape (BoE)'!V41=4,"Retired"),"") | X40: =IF(OR(V40="Self-Employed",W40="Self-Employed"),"Yes","No") | Y40: ='Loan Tape (BoE)'!W41 | Z40: ='Loan Tape (BoE)'!X41 | AA40: =IF(T40=1,Y40,MIN(Y40,Z40)) | AB40: ='Loan Tape (BoE)'!Y41 | AC40: ='Loan Tape (BoE)'!Z41 | AD40: =AB40+AC40 | AE40: ='Loan Tape (BoE)'!AA41 | AF40: ='Loan Tape (BoE)'!AB41 | AG40: =AE40+AF40 | AH40: =MAX('Loan Tape (BoE)'!AC41,'Loan Tape (BoE)'!AD41) | AI40: ='Loan Tape (BoE)'!AE41 | AJ40: =B40*H40/12 | AK40: =IF(AJ40>0,AI40/AJ40,0) | AL40: =IF('Loan Tape (BoE)'!AF41=1,"Yes","No") | AM40: =IF('Loan Tape (BoE)'!AH41=1,"Yes","No") | AN40: =IF('Loan Tape (BoE)'!AI41=1,"Yes","No") | AO40: =IF('Loan Tape (BoE)'!AJ41=1,"Yes","No") | AP40: =IF(OR('Loan Tape (BoE)'!AQ40=1,'Loan Tape (BoE)'!AQ40=2),"Yes",IF('Loan Tape (BoE)'!AQ40=0,"No","")) | AQ40: =IF('Loan Tape (BoE)'!BV49_40<>"",'Loan Tape (BoE)'!BV49_40,"") | AR40: =IF('Loan Tape (BoE)'!BV400_40<>"",'Loan Tape (BoE)'!BV50_40,"") | AS40: =IFERROR(INDEX('FF Adj Parameters'!$A$103:$B$1040,MATCH('Loan Tape (BoE)'!P40,INDEX('FF Adj Parameters'!$A$103:$B$1040,,1),0),2),"Unknown") | AT40: =IF(N40="Interest Only",M5*O5/12,IF(AND(O5>0,ISNUMBER(O5),ISNUMBER(M5)),ABS(PMT(O5/12,AU5,-M5)),0)) | AU40: =IF(ISNUMBER(L40),MAX(0,(L5-'Control Panel'!$B$10)*12/365.25),0) | AV40: =IF(ISNUMBER(L40),IF(L5>'Control Panel'!$B$10,"Valid","Past Maturity"),"No Date") | AW40: =IF(ISNUMBER(K40),MAX(0,('Control Panel'!$B$10-K5)*12/365.25),0)
A41: ='Loan Tape (BoE)'!A42 | B41: =IFERROR(INDEX('FF Adj Parameters'!$A$89:$B$92,MATCH('Loan Tape (BoE)'!C41,INDEX('FF Adj Parameters'!$A$89:$B$92,,1),0),2),"Unknown") | C41: ='Loan Tape (BoE)'!C42 | D41: ='Loan Tape (BoE)'!D42 | E41: ='Loan Tape (BoE)'!E42 | F41: ='Loan Tape (BoE)'!F42 | G41: ='Loan Tape (BoE)'!G42 | H41: ='Loan Tape (BoE)'!H42/100 | I41: =IFERROR(IFS('Loan Tape (BoE)'!I42=1,"House",'Loan Tape (BoE)'!I42=2,"Flat",'Loan Tape (BoE)'!I42=3,"Bungalow",'Loan Tape (BoE)'!I42=4,"Maisonette"),"") | J41: ='Loan Tape (BoE)'!J42 | K41: ='Loan Tape (BoE)'!K42 | L41: =IFERROR(IFS('Loan Tape (BoE)'!L42=1,"Owner Occupied",'Loan Tape (BoE)'!L42=2,"BTL",'Loan Tape (BoE)'!L42=3,"Second Home",'Loan Tape (BoE)'!L42=4,"Investment"),"") | M41: =IFERROR(IFS('Loan Tape (BoE)'!M42=1,"Purchase",'Loan Tape (BoE)'!M42=2,"Remortgage",OR('Loan Tape (BoE)'!M42=3,'Loan Tape (BoE)'!M42=4),"Cash-out"),"") | N41: =IFERROR(INDEX('FF Adj Parameters'!$A$96:$B$99,MATCH('Loan Tape (BoE)'!R41,INDEX('FF Adj Parameters'!$A$96:$B$99,,1),0),2),"Unknown") | O41: =IF('Loan Tape (BoE)'!O42=1,"Yes","No") | P41: =IF('Loan Tape (BoE)'!P41=1,"Yes",IF('Loan Tape (BoE)'!P41=0,"No","")) | Q41: =IF('Loan Tape (BoE)'!Q41=1,"Yes",IF('Loan Tape (BoE)'!Q41=0,"No","")) | R41: =IF('Loan Tape (BoE)'!R41=1,"Yes",IF('Loan Tape (BoE)'!R41=0,"No","")) | S41: =IF('Loan Tape (BoE)'!S41=1,"Yes",IF('Loan Tape (BoE)'!S41=0,"No","")) | T41: =IF('Loan Tape (BoE)'!T41=1,"Yes",IF('Loan Tape (BoE)'!T41=0,"No","")) | U41: =R41+S41 | V41: =IFERROR(IFS('Loan Tape (BoE)'!U42=1,"Employed",'Loan Tape (BoE)'!U42=2,"Self-Employed",'Loan Tape (BoE)'!U42=3,"Unemployed",'Loan Tape (BoE)'!U42=4,"Retired"),"") | W41: =IFERROR(IFS('Loan Tape (BoE)'!V42=1,"Employed",'Loan Tape (BoE)'!V42=2,"Self-Employed",'Loan Tape (BoE)'!V42=3,"Unemployed",'Loan Tape (BoE)'!V42=4,"Retired"),"") | X41: =IF(OR(V41="Self-Employed",W41="Self-Employed"),"Yes","No") | Y41: ='Loan Tape (BoE)'!W42 | Z41: ='Loan Tape (BoE)'!X42 | AA41: =IF(T41=1,Y41,MIN(Y41,Z41)) | AB41: ='Loan Tape (BoE)'!Y42 | AC41: ='Loan Tape (BoE)'!Z42 | AD41: =AB41+AC41 | AE41: ='Loan Tape (BoE)'!AA42 | AF41: ='Loan Tape (BoE)'!AB42 | AG41: =AE41+AF41 | AH41: =MAX('Loan Tape (BoE)'!AC42,'Loan Tape (BoE)'!AD42) | AI41: ='Loan Tape (BoE)'!AE42 | AJ41: =B41*H41/12 | AK41: =IF(AJ41>0,AI41/AJ41,0) | AL41: =IF('Loan Tape (BoE)'!AF42=1,"Yes","No") | AM41: =IF('Loan Tape (BoE)'!AH42=1,"Yes","No") | AN41: =IF('Loan Tape (BoE)'!AI42=1,"Yes","No") | AO41: =IF('Loan Tape (BoE)'!AJ42=1,"Yes","No") | AP41: =IF(OR('Loan Tape (BoE)'!AQ41=1,'Loan Tape (BoE)'!AQ41=2),"Yes",IF('Loan Tape (BoE)'!AQ41=0,"No","")) | AQ41: =IF('Loan Tape (BoE)'!BV49_41<>"",'Loan Tape (BoE)'!BV49_41,"") | AR41: =IF('Loan Tape (BoE)'!BV410_41<>"",'Loan Tape (BoE)'!BV50_41,"") | AS41: =IFERROR(INDEX('FF Adj Parameters'!$A$103:$B$1041,MATCH('Loan Tape (BoE)'!P41,INDEX('FF Adj Parameters'!$A$103:$B$1041,,1),0),2),"Unknown") | AT41: =IF(N41="Interest Only",M5*O5/12,IF(AND(O5>0,ISNUMBER(O5),ISNUMBER(M5)),ABS(PMT(O5/12,AU5,-M5)),0)) | AU41: =IF(ISNUMBER(L41),MAX(0,(L5-'Control Panel'!$B$10)*12/365.25),0) | AV41: =IF(ISNUMBER(L41),IF(L5>'Control Panel'!$B$10,"Valid","Past Maturity"),"No Date") | AW41: =IF(ISNUMBER(K41),MAX(0,('Control Panel'!$B$10-K5)*12/365.25),0)
A42: ='Loan Tape (BoE)'!A43 | B42: =IFERROR(INDEX('FF Adj Parameters'!$A$89:$B$92,MATCH('Loan Tape (BoE)'!C42,INDEX('FF Adj Parameters'!$A$89:$B$92,,1),0),2),"Unknown") | C42: ='Loan Tape (BoE)'!C43 | D42: ='Loan Tape (BoE)'!D43 | E42: ='Loan Tape (BoE)'!E43 | F42: ='Loan Tape (BoE)'!F43 | G42: ='Loan Tape (BoE)'!G43 | H42: ='Loan Tape (BoE)'!H43/100 | I42: =IFERROR(IFS('Loan Tape (BoE)'!I43=1,"House",'Loan Tape (BoE)'!I43=2,"Flat",'Loan Tape (BoE)'!I43=3,"Bungalow",'Loan Tape (BoE)'!I43=4,"Maisonette"),"") | J42: ='Loan Tape (BoE)'!J43 | K42: ='Loan Tape (BoE)'!K43 | L42: =IFERROR(IFS('Loan Tape (BoE)'!L43=1,"Owner Occupied",'Loan Tape (BoE)'!L43=2,"BTL",'Loan Tape (BoE)'!L43=3,"Second Home",'Loan Tape (BoE)'!L43=4,"Investment"),"") | M42: =IFERROR(IFS('Loan Tape (BoE)'!M43=1,"Purchase",'Loan Tape (BoE)'!M43=2,"Remortgage",OR('Loan Tape (BoE)'!M43=3,'Loan Tape (BoE)'!M43=4),"Cash-out"),"") | N42: =IFERROR(INDEX('FF Adj Parameters'!$A$96:$B$99,MATCH('Loan Tape (BoE)'!R42,INDEX('FF Adj Parameters'!$A$96:$B$99,,1),0),2),"Unknown") | O42: =IF('Loan Tape (BoE)'!O43=1,"Yes","No") | P42: =IF('Loan Tape (BoE)'!P42=1,"Yes",IF('Loan Tape (BoE)'!P42=0,"No","")) | Q42: =IF('Loan Tape (BoE)'!Q42=1,"Yes",IF('Loan Tape (BoE)'!Q42=0,"No","")) | R42: =IF('Loan Tape (BoE)'!R42=1,"Yes",IF('Loan Tape (BoE)'!R42=0,"No","")) | S42: =IF('Loan Tape (BoE)'!S42=1,"Yes",IF('Loan Tape (BoE)'!S42=0,"No","")) | T42: =IF('Loan Tape (BoE)'!T42=1,"Yes",IF('Loan Tape (BoE)'!T42=0,"No","")) | U42: =R42+S42 | V42: =IFERROR(IFS('Loan Tape (BoE)'!U43=1,"Employed",'Loan Tape (BoE)'!U43=2,"Self-Employed",'Loan Tape (BoE)'!U43=3,"Unemployed",'Loan Tape (BoE)'!U43=4,"Retired"),"") | W42: =IFERROR(IFS('Loan Tape (BoE)'!V43=1,"Employed",'Loan Tape (BoE)'!V43=2,"Self-Employed",'Loan Tape (BoE)'!V43=3,"Unemployed",'Loan Tape (BoE)'!V43=4,"Retired"),"") | X42: =IF(OR(V42="Self-Employed",W42="Self-Employed"),"Yes","No") | Y42: ='Loan Tape (BoE)'!W43 | Z42: ='Loan Tape (BoE)'!X43 | AA42: =IF(T42=1,Y42,MIN(Y42,Z42)) | AB42: ='Loan Tape (BoE)'!Y43 | AC42: ='Loan Tape (BoE)'!Z43 | AD42: =AB42+AC42 | AE42: ='Loan Tape (BoE)'!AA43 | AF42: ='Loan Tape (BoE)'!AB43 | AG42: =AE42+AF42 | AH42: =MAX('Loan Tape (BoE)'!AC43,'Loan Tape (BoE)'!AD43) | AI42: ='Loan Tape (BoE)'!AE43 | AJ42: =B42*H42/12 | AK42: =IF(AJ42>0,AI42/AJ42,0) | AL42: =IF('Loan Tape (BoE)'!AF43=1,"Yes","No") | AM42: =IF('Loan Tape (BoE)'!AH43=1,"Yes","No") | AN42: =IF('Loan Tape (BoE)'!AI43=1,"Yes","No") | AO42: =IF('Loan Tape (BoE)'!AJ43=1,"Yes","No") | AP42: =IF(OR('Loan Tape (BoE)'!AQ42=1,'Loan Tape (BoE)'!AQ42=2),"Yes",IF('Loan Tape (BoE)'!AQ42=0,"No","")) | AQ42: =IF('Loan Tape (BoE)'!BV49_42<>"",'Loan Tape (BoE)'!BV49_42,"") | AR42: =IF('Loan Tape (BoE)'!BV420_42<>"",'Loan Tape (BoE)'!BV50_42,"") | AS42: =IFERROR(INDEX('FF Adj Parameters'!$A$103:$B$1042,MATCH('Loan Tape (BoE)'!P42,INDEX('FF Adj Parameters'!$A$103:$B$1042,,1),0),2),"Unknown") | AT42: =IF(N42="Interest Only",M5*O5/12,IF(AND(O5>0,ISNUMBER(O5),ISNUMBER(M5)),ABS(PMT(O5/12,AU5,-M5)),0)) | AU42: =IF(ISNUMBER(L42),MAX(0,(L5-'Control Panel'!$B$10)*12/365.25),0) | AV42: =IF(ISNUMBER(L42),IF(L5>'Control Panel'!$B$10,"Valid","Past Maturity"),"No Date") | AW42: =IF(ISNUMBER(K42),MAX(0,('Control Panel'!$B$10-K5)*12/365.25),0)
A43: ='Loan Tape (BoE)'!A44 | B43: =IFERROR(INDEX('FF Adj Parameters'!$A$89:$B$92,MATCH('Loan Tape (BoE)'!C43,INDEX('FF Adj Parameters'!$A$89:$B$92,,1),0),2),"Unknown") | C43: ='Loan Tape (BoE)'!C44 | D43: ='Loan Tape (BoE)'!D44 | E43: ='Loan Tape (BoE)'!E44 | F43: ='Loan Tape (BoE)'!F44 | G43: ='Loan Tape (BoE)'!G44 | H43: ='Loan Tape (BoE)'!H44/100 | I43: =IFERROR(IFS('Loan Tape (BoE)'!I44=1,"House",'Loan Tape (BoE)'!I44=2,"Flat",'Loan Tape (BoE)'!I44=3,"Bungalow",'Loan Tape (BoE)'!I44=4,"Maisonette"),"") | J43: ='Loan Tape (BoE)'!J44 | K43: ='Loan Tape (BoE)'!K44 | L43: =IFERROR(IFS('Loan Tape (BoE)'!L44=1,"Owner Occupied",'Loan Tape (BoE)'!L44=2,"BTL",'Loan Tape (BoE)'!L44=3,"Second Home",'Loan Tape (BoE)'!L44=4,"Investment"),"") | M43: =IFERROR(IFS('Loan Tape (BoE)'!M44=1,"Purchase",'Loan Tape (BoE)'!M44=2,"Remortgage",OR('Loan Tape (BoE)'!M44=3,'Loan Tape (BoE)'!M44=4),"Cash-out"),"") | N43: =IFERROR(INDEX('FF Adj Parameters'!$A$96:$B$99,MATCH('Loan Tape (BoE)'!R43,INDEX('FF Adj Parameters'!$A$96:$B$99,,1),0),2),"Unknown") | O43: =IF('Loan Tape (BoE)'!O44=1,"Yes","No") | P43: =IF('Loan Tape (BoE)'!P43=1,"Yes",IF('Loan Tape (BoE)'!P43=0,"No","")) | Q43: =IF('Loan Tape (BoE)'!Q43=1,"Yes",IF('Loan Tape (BoE)'!Q43=0,"No","")) | R43: =IF('Loan Tape (BoE)'!R43=1,"Yes",IF('Loan Tape (BoE)'!R43=0,"No","")) | S43: =IF('Loan Tape (BoE)'!S43=1,"Yes",IF('Loan Tape (BoE)'!S43=0,"No","")) | T43: =IF('Loan Tape (BoE)'!T43=1,"Yes",IF('Loan Tape (BoE)'!T43=0,"No","")) | U43: =R43+S43 | V43: =IFERROR(IFS('Loan Tape (BoE)'!U44=1,"Employed",'Loan Tape (BoE)'!U44=2,"Self-Employed",'Loan Tape (BoE)'!U44=3,"Unemployed",'Loan Tape (BoE)'!U44=4,"Retired"),"") | W43: =IFERROR(IFS('Loan Tape (BoE)'!V44=1,"Employed",'Loan Tape (BoE)'!V44=2,"Self-Employed",'Loan Tape (BoE)'!V44=3,"Unemployed",'Loan Tape (BoE)'!V44=4,"Retired"),"") | X43: =IF(OR(V43="Self-Employed",W43="Self-Employed"),"Yes","No") | Y43: ='Loan Tape (BoE)'!W44 | Z43: ='Loan Tape (BoE)'!X44 | AA43: =IF(T43=1,Y43,MIN(Y43,Z43)) | AB43: ='Loan Tape (BoE)'!Y44 | AC43: ='Loan Tape (BoE)'!Z44 | AD43: =AB43+AC43 | AE43: ='Loan Tape (BoE)'!AA44 | AF43: ='Loan Tape (BoE)'!AB44 | AG43: =AE43+AF43 | AH43: =MAX('Loan Tape (BoE)'!AC44,'Loan Tape (BoE)'!AD44) | AI43: ='Loan Tape (BoE)'!AE44 | AJ43: =B43*H43/12 | AK43: =IF(AJ43>0,AI43/AJ43,0) | AL43: =IF('Loan Tape (BoE)'!AF44=1,"Yes","No") | AM43: =IF('Loan Tape (BoE)'!AH44=1,"Yes","No") | AN43: =IF('Loan Tape (BoE)'!AI44=1,"Yes","No") | AO43: =IF('Loan Tape (BoE)'!AJ44=1,"Yes","No") | AP43: =IF(OR('Loan Tape (BoE)'!AQ43=1,'Loan Tape (BoE)'!AQ43=2),"Yes",IF('Loan Tape (BoE)'!AQ43=0,"No","")) | AQ43: =IF('Loan Tape (BoE)'!BV49_43<>"",'Loan Tape (BoE)'!BV49_43,"") | AR43: =IF('Loan Tape (BoE)'!BV430_43<>"",'Loan Tape (BoE)'!BV50_43,"") | AS43: =IFERROR(INDEX('FF Adj Parameters'!$A$103:$B$1043,MATCH('Loan Tape (BoE)'!P43,INDEX('FF Adj Parameters'!$A$103:$B$1043,,1),0),2),"Unknown") | AT43: =IF(N43="Interest Only",M5*O5/12,IF(AND(O5>0,ISNUMBER(O5),ISNUMBER(M5)),ABS(PMT(O5/12,AU5,-M5)),0)) | AU43: =IF(ISNUMBER(L43),MAX(0,(L5-'Control Panel'!$B$10)*12/365.25),0) | AV43: =IF(ISNUMBER(L43),IF(L5>'Control Panel'!$B$10,"Valid","Past Maturity"),"No Date") | AW43: =IF(ISNUMBER(K43),MAX(0,('Control Panel'!$B$10-K5)*12/365.25),0)
A44: ='Loan Tape (BoE)'!A45 | B44: =IFERROR(INDEX('FF Adj Parameters'!$A$89:$B$92,MATCH('Loan Tape (BoE)'!C44,INDEX('FF Adj Parameters'!$A$89:$B$92,,1),0),2),"Unknown") | C44: ='Loan Tape (BoE)'!C45 | D44: ='Loan Tape (BoE)'!D45 | E44: ='Loan Tape (BoE)'!E45 | F44: ='Loan Tape (BoE)'!F45 | G44: ='Loan Tape (BoE)'!G45 | H44: ='Loan Tape (BoE)'!H45/100 | I44: =IFERROR(IFS('Loan Tape (BoE)'!I45=1,"House",'Loan Tape (BoE)'!I45=2,"Flat",'Loan Tape (BoE)'!I45=3,"Bungalow",'Loan Tape (BoE)'!I45=4,"Maisonette"),"") | J44: ='Loan Tape (BoE)'!J45 | K44: ='Loan Tape (BoE)'!K45 | L44: =IFERROR(IFS('Loan Tape (BoE)'!L45=1,"Owner Occupied",'Loan Tape (BoE)'!L45=2,"BTL",'Loan Tape (BoE)'!L45=3,"Second Home",'Loan Tape (BoE)'!L45=4,"Investment"),"") | M44: =IFERROR(IFS('Loan Tape (BoE)'!M45=1,"Purchase",'Loan Tape (BoE)'!M45=2,"Remortgage",OR('Loan Tape (BoE)'!M45=3,'Loan Tape (BoE)'!M45=4),"Cash-out"),"") | N44: =IFERROR(INDEX('FF Adj Parameters'!$A$96:$B$99,MATCH('Loan Tape (BoE)'!R44,INDEX('FF Adj Parameters'!$A$96:$B$99,,1),0),2),"Unknown") | O44: =IF('Loan Tape (BoE)'!O45=1,"Yes","No") | P44: =IF('Loan Tape (BoE)'!P44=1,"Yes",IF('Loan Tape (BoE)'!P44=0,"No","")) | Q44: =IF('Loan Tape (BoE)'!Q44=1,"Yes",IF('Loan Tape (BoE)'!Q44=0,"No","")) | R44: =IF('Loan Tape (BoE)'!R44=1,"Yes",IF('Loan Tape (BoE)'!R44=0,"No","")) | S44: =IF('Loan Tape (BoE)'!S44=1,"Yes",IF('Loan Tape (BoE)'!S44=0,"No","")) | T44: =IF('Loan Tape (BoE)'!T44=1,"Yes",IF('Loan Tape (BoE)'!T44=0,"No","")) | U44: =R44+S44 | V44: =IFERROR(IFS('Loan Tape (BoE)'!U45=1,"Employed",'Loan Tape (BoE)'!U45=2,"Self-Employed",'Loan Tape (BoE)'!U45=3,"Unemployed",'Loan Tape (BoE)'!U45=4,"Retired"),"") | W44: =IFERROR(IFS('Loan Tape (BoE)'!V45=1,"Employed",'Loan Tape (BoE)'!V45=2,"Self-Employed",'Loan Tape (BoE)'!V45=3,"Unemployed",'Loan Tape (BoE)'!V45=4,"Retired"),"") | X44: =IF(OR(V44="Self-Employed",W44="Self-Employed"),"Yes","No") | Y44: ='Loan Tape (BoE)'!W45 | Z44: ='Loan Tape (BoE)'!X45 | AA44: =IF(T44=1,Y44,MIN(Y44,Z44)) | AB44: ='Loan Tape (BoE)'!Y45 | AC44: ='Loan Tape (BoE)'!Z45 | AD44: =AB44+AC44 | AE44: ='Loan Tape (BoE)'!AA45 | AF44: ='Loan Tape (BoE)'!AB45 | AG44: =AE44+AF44 | AH44: =MAX('Loan Tape (BoE)'!AC45,'Loan Tape (BoE)'!AD45) | AI44: ='Loan Tape (BoE)'!AE45 | AJ44: =B44*H44/12 | AK44: =IF(AJ44>0,AI44/AJ44,0) | AL44: =IF('Loan Tape (BoE)'!AF45=1,"Yes","No") | AM44: =IF('Loan Tape (BoE)'!AH45=1,"Yes","No") | AN44: =IF('Loan Tape (BoE)'!AI45=1,"Yes","No") | AO44: =IF('Loan Tape (BoE)'!AJ45=1,"Yes","No") | AP44: =IF(OR('Loan Tape (BoE)'!AQ44=1,'Loan Tape (BoE)'!AQ44=2),"Yes",IF('Loan Tape (BoE)'!AQ44=0,"No","")) | AQ44: =IF('Loan Tape (BoE)'!BV49_44<>"",'Loan Tape (BoE)'!BV49_44,"") | AR44: =IF('Loan Tape (BoE)'!BV440_44<>"",'Loan Tape (BoE)'!BV50_44,"") | AS44: =IFERROR(INDEX('FF Adj Parameters'!$A$103:$B$1044,MATCH('Loan Tape (BoE)'!P44,INDEX('FF Adj Parameters'!$A$103:$B$1044,,1),0),2),"Unknown") | AT44: =IF(N44="Interest Only",M5*O5/12,IF(AND(O5>0,ISNUMBER(O5),ISNUMBER(M5)),ABS(PMT(O5/12,AU5,-M5)),0)) | AU44: =IF(ISNUMBER(L44),MAX(0,(L5-'Control Panel'!$B$10)*12/365.25),0) | AV44: =IF(ISNUMBER(L44),IF(L5>'Control Panel'!$B$10,"Valid","Past Maturity"),"No Date") | AW44: =IF(ISNUMBER(K44),MAX(0,('Control Panel'!$B$10-K5)*12/365.25),0)
A45: ='Loan Tape (BoE)'!A46 | B45: =IFERROR(INDEX('FF Adj Parameters'!$A$89:$B$92,MATCH('Loan Tape (BoE)'!C45,INDEX('FF Adj Parameters'!$A$89:$B$92,,1),0),2),"Unknown") | C45: ='Loan Tape (BoE)'!C46 | D45: ='Loan Tape (BoE)'!D46 | E45: ='Loan Tape (BoE)'!E46 | F45: ='Loan Tape (BoE)'!F46 | G45: ='Loan Tape (BoE)'!G46 | H45: ='Loan Tape (BoE)'!H46/100 | I45: =IFERROR(IFS('Loan Tape (BoE)'!I46=1,"House",'Loan Tape (BoE)'!I46=2,"Flat",'Loan Tape (BoE)'!I46=3,"Bungalow",'Loan Tape (BoE)'!I46=4,"Maisonette"),"") | J45: ='Loan Tape (BoE)'!J46 | K45: ='Loan Tape (BoE)'!K46 | L45: =IFERROR(IFS('Loan Tape (BoE)'!L46=1,"Owner Occupied",'Loan Tape (BoE)'!L46=2,"BTL",'Loan Tape (BoE)'!L46=3,"Second Home",'Loan Tape (BoE)'!L46=4,"Investment"),"") | M45: =IFERROR(IFS('Loan Tape (BoE)'!M46=1,"Purchase",'Loan Tape (BoE)'!M46=2,"Remortgage",OR('Loan Tape (BoE)'!M46=3,'Loan Tape (BoE)'!M46=4),"Cash-out"),"") | N45: =IFERROR(INDEX('FF Adj Parameters'!$A$96:$B$99,MATCH('Loan Tape (BoE)'!R45,INDEX('FF Adj Parameters'!$A$96:$B$99,,1),0),2),"Unknown") | O45: =IF('Loan Tape (BoE)'!O46=1,"Yes","No") | P45: =IF('Loan Tape (BoE)'!P45=1,"Yes",IF('Loan Tape (BoE)'!P45=0,"No","")) | Q45: =IF('Loan Tape (BoE)'!Q45=1,"Yes",IF('Loan Tape (BoE)'!Q45=0,"No","")) | R45: =IF('Loan Tape (BoE)'!R45=1,"Yes",IF('Loan Tape (BoE)'!R45=0,"No","")) | S45: =IF('Loan Tape (BoE)'!S45=1,"Yes",IF('Loan Tape (BoE)'!S45=0,"No","")) | T45: =IF('Loan Tape (BoE)'!T45=1,"Yes",IF('Loan Tape (BoE)'!T45=0,"No","")) | U45: =R45+S45 | V45: =IFERROR(IFS('Loan Tape (BoE)'!U46=1,"Employed",'Loan Tape (BoE)'!U46=2,"Self-Employed",'Loan Tape (BoE)'!U46=3,"Unemployed",'Loan Tape (BoE)'!U46=4,"Retired"),"") | W45: =IFERROR(IFS('Loan Tape (BoE)'!V46=1,"Employed",'Loan Tape (BoE)'!V46=2,"Self-Employed",'Loan Tape (BoE)'!V46=3,"Unemployed",'Loan Tape (BoE)'!V46=4,"Retired"),"") | X45: =IF(OR(V45="Self-Employed",W45="Self-Employed"),"Yes","No") | Y45: ='Loan Tape (BoE)'!W46 | Z45: ='Loan Tape (BoE)'!X46 | AA45: =IF(T45=1,Y45,MIN(Y45,Z45)) | AB45: ='Loan Tape (BoE)'!Y46 | AC45: ='Loan Tape (BoE)'!Z46 | AD45: =AB45+AC45 | AE45: ='Loan Tape (BoE)'!AA46 | AF45: ='Loan Tape (BoE)'!AB46 | AG45: =AE45+AF45 | AH45: =MAX('Loan Tape (BoE)'!AC46,'Loan Tape (BoE)'!AD46) | AI45: ='Loan Tape (BoE)'!AE46 | AJ45: =B45*H45/12 | AK45: =IF(AJ45>0,AI45/AJ45,0) | AL45: =IF('Loan Tape (BoE)'!AF46=1,"Yes","No") | AM45: =IF('Loan Tape (BoE)'!AH46=1,"Yes","No") | AN45: =IF('Loan Tape (BoE)'!AI46=1,"Yes","No") | AO45: =IF('Loan Tape (BoE)'!AJ46=1,"Yes","No") | AP45: =IF(OR('Loan Tape (BoE)'!AQ45=1,'Loan Tape (BoE)'!AQ45=2),"Yes",IF('Loan Tape (BoE)'!AQ45=0,"No","")) | AQ45: =IF('Loan Tape (BoE)'!BV49_445<>"",'Loan Tape (BoE)'!BV49_45,"") | AR45: =IF('Loan Tape (BoE)'!BV450_45<>"",'Loan Tape (BoE)'!BV50_45,"") | AS45: =IFERROR(INDEX('FF Adj Parameters'!$A$103:$B$1045,MATCH('Loan Tape (BoE)'!P45,INDEX('FF Adj Parameters'!$A$103:$B$1045,,1),0),2),"Unknown") | AT45: =IF(N45="Interest Only",M5*O5/12,IF(AND(O5>0,ISNUMBER(O5),ISNUMBER(M5)),ABS(PMT(O5/12,AU5,-M5)),0)) | AU45: =IF(ISNUMBER(L45),MAX(0,(L5-'Control Panel'!$B$10)*12/365.25),0) | AV45: =IF(ISNUMBER(L45),IF(L5>'Control Panel'!$B$10,"Valid","Past Maturity"),"No Date") | AW45: =IF(ISNUMBER(K45),MAX(0,('Control Panel'!$B$10-K5)*12/365.25),0)
A46: ='Loan Tape (BoE)'!A47 | B46: =IFERROR(INDEX('FF Adj Parameters'!$A$89:$B$92,MATCH('Loan Tape (BoE)'!C46,INDEX('FF Adj Parameters'!$A$89:$B$92,,1),0),2),"Unknown") | C46: ='Loan Tape (BoE)'!C47 | D46: ='Loan Tape (BoE)'!D47 | E46: ='Loan Tape (BoE)'!E47 | F46: ='Loan Tape (BoE)'!F47 | G46: ='Loan Tape (BoE)'!G47 | H46: ='Loan Tape (BoE)'!H47/100 | I46: =IFERROR(IFS('Loan Tape (BoE)'!I47=1,"House",'Loan Tape (BoE)'!I47=2,"Flat",'Loan Tape (BoE)'!I47=3,"Bungalow",'Loan Tape (BoE)'!I47=4,"Maisonette"),"") | J46: ='Loan Tape (BoE)'!J47 | K46: ='Loan Tape (BoE)'!K47 | L46: =IFERROR(IFS('Loan Tape (BoE)'!L47=1,"Owner Occupied",'Loan Tape (BoE)'!L47=2,"BTL",'Loan Tape (BoE)'!L47=3,"Second Home",'Loan Tape (BoE)'!L47=4,"Investment"),"") | M46: =IFERROR(IFS('Loan Tape (BoE)'!M47=1,"Purchase",'Loan Tape (BoE)'!M47=2,"Remortgage",OR('Loan Tape (BoE)'!M47=3,'Loan Tape (BoE)'!M47=4),"Cash-out"),"") | N46: =IFERROR(INDEX('FF Adj Parameters'!$A$96:$B$99,MATCH('Loan Tape (BoE)'!R46,INDEX('FF Adj Parameters'!$A$96:$B$99,,1),0),2),"Unknown") | O46: =IF('Loan Tape (BoE)'!O47=1,"Yes","No") | P46: =IF('Loan Tape (BoE)'!P46=1,"Yes",IF('Loan Tape (BoE)'!P46=0,"No","")) | Q46: =IF('Loan Tape (BoE)'!Q46=1,"Yes",IF('Loan Tape (BoE)'!Q46=0,"No","")) | R46: =IF('Loan Tape (BoE)'!R46=1,"Yes",IF('Loan Tape (BoE)'!R46=0,"No","")) | S46: =IF('Loan Tape (BoE)'!S46=1,"Yes",IF('Loan Tape (BoE)'!S46=0,"No","")) | T46: =IF('Loan Tape (BoE)'!T46=1,"Yes",IF('Loan Tape (BoE)'!T46=0,"No","")) | U46: =R46+S46 | V46: =IFERROR(IFS('Loan Tape (BoE)'!U47=1,"Employed",'Loan Tape (BoE)'!U47=2,"Self-Employed",'Loan Tape (BoE)'!U47=3,"Unemployed",'Loan Tape (BoE)'!U47=4,"Retired"),"") | W46: =IFERROR(IFS('Loan Tape (BoE)'!V47=1,"Employed",'Loan Tape (BoE)'!V47=2,"Self-Employed",'Loan Tape (BoE)'!V47=3,"Unemployed",'Loan Tape (BoE)'!V47=4,"Retired"),"") | X46: =IF(OR(V46="Self-Employed",W46="Self-Employed"),"Yes","No") | Y46: ='Loan Tape (BoE)'!W47 | Z46: ='Loan Tape (BoE)'!X47 | AA46: =IF(T46=1,Y46,MIN(Y46,Z46)) | AB46: ='Loan Tape (BoE)'!Y47 | AC46: ='Loan Tape (BoE)'!Z47 | AD46: =AB46+AC46 | AE46: ='Loan Tape (BoE)'!AA47 | AF46: ='Loan Tape (BoE)'!AB47 | AG46: =AE46+AF46 | AH46: =MAX('Loan Tape (BoE)'!AC47,'Loan Tape (BoE)'!AD47) | AI46: ='Loan Tape (BoE)'!AE47 | AJ46: =B46*H46/12 | AK46: =IF(AJ46>0,AI46/AJ46,0) | AL46: =IF('Loan Tape (BoE)'!AF47=1,"Yes","No") | AM46: =IF('Loan Tape (BoE)'!AH47=1,"Yes","No") | AN46: =IF('Loan Tape (BoE)'!AI47=1,"Yes","No") | AO46: =IF('Loan Tape (BoE)'!AJ47=1,"Yes","No") | AP46: =IF(OR('Loan Tape (BoE)'!AQ46=1,'Loan Tape (BoE)'!AQ46=2),"Yes",IF('Loan Tape (BoE)'!AQ46=0,"No","")) | AQ46: =IF('Loan Tape (BoE)'!BV49_46<>"",'Loan Tape (BoE)'!BV49_46,"") | AR46: =IF('Loan Tape (BoE)'!BV460_46<>"",'Loan Tape (BoE)'!BV50_46,"") | AS46: =IFERROR(INDEX('FF Adj Parameters'!$A$103:$B$1046,MATCH('Loan Tape (BoE)'!P46,INDEX('FF Adj Parameters'!$A$103:$B$1046,,1),0),2),"Unknown") | AT46: =IF(N46="Interest Only",M5*O5/12,IF(AND(O5>0,ISNUMBER(O5),ISNUMBER(M5)),ABS(PMT(O5/12,AU5,-M5)),0)) | AU46: =IF(ISNUMBER(L46),MAX(0,(L5-'Control Panel'!$B$10)*12/365.25),0) | AV46: =IF(ISNUMBER(L46),IF(L5>'Control Panel'!$B$10,"Valid","Past Maturity"),"No Date") | AW46: =IF(ISNUMBER(K46),MAX(0,('Control Panel'!$B$10-K5)*12/365.25),0)
A47: ='Loan Tape (BoE)'!A48 | B47: =IFERROR(INDEX('FF Adj Parameters'!$A$89:$B$92,MATCH('Loan Tape (BoE)'!C47,INDEX('FF Adj Parameters'!$A$89:$B$92,,1),0),2),"Unknown") | C47: ='Loan Tape (BoE)'!C48 | D47: ='Loan Tape (BoE)'!D48 | E47: ='Loan Tape (BoE)'!E48 | F47: ='Loan Tape (BoE)'!F48 | G47: ='Loan Tape (BoE)'!G48 | H47: ='Loan Tape (BoE)'!H48/100 | I47: =IFERROR(IFS('Loan Tape (BoE)'!I48=1,"House",'Loan Tape (BoE)'!I48=2,"Flat",'Loan Tape (BoE)'!I48=3,"Bungalow",'Loan Tape (BoE)'!I48=4,"Maisonette"),"") | J47: ='Loan Tape (BoE)'!J48 | K47: ='Loan Tape (BoE)'!K48 | L47: =IFERROR(IFS('Loan Tape (BoE)'!L48=1,"Owner Occupied",'Loan Tape (BoE)'!L48=2,"BTL",'Loan Tape (BoE)'!L48=3,"Second Home",'Loan Tape (BoE)'!L48=4,"Investment"),"") | M47: =IFERROR(IFS('Loan Tape (BoE)'!M48=1,"Purchase",'Loan Tape (BoE)'!M48=2,"Remortgage",OR('Loan Tape (BoE)'!M48=3,'Loan Tape (BoE)'!M48=4),"Cash-out"),"") | N47: =IFERROR(INDEX('FF Adj Parameters'!$A$96:$B$99,MATCH('Loan Tape (BoE)'!R47,INDEX('FF Adj Parameters'!$A$96:$B$99,,1),0),2),"Unknown") | O47: =IF('Loan Tape (BoE)'!O48=1,"Yes","No") | P47: =IF('Loan Tape (BoE)'!P47=1,"Yes",IF('Loan Tape (BoE)'!P47=0,"No","")) | Q47: =IF('Loan Tape (BoE)'!Q47=1,"Yes",IF('Loan Tape (BoE)'!Q47=0,"No","")) | R47: =IF('Loan Tape (BoE)'!R47=1,"Yes",IF('Loan Tape (BoE)'!R47=0,"No","")) | S47: =IF('Loan Tape (BoE)'!S47=1,"Yes",IF('Loan Tape (BoE)'!S47=0,"No","")) | T47: =IF('Loan Tape (BoE)'!T47=1,"Yes",IF('Loan Tape (BoE)'!T47=0,"No","")) | U47: =R47+S47 | V47: =IFERROR(IFS('Loan Tape (BoE)'!U48=1,"Employed",'Loan Tape (BoE)'!U48=2,"Self-Employed",'Loan Tape (BoE)'!U48=3,"Unemployed",'Loan Tape (BoE)'!U48=4,"Retired"),"") | W47: =IFERROR(IFS('Loan Tape (BoE)'!V48=1,"Employed",'Loan Tape (BoE)'!V48=2,"Self-Employed",'Loan Tape (BoE)'!V48=3,"Unemployed",'Loan Tape (BoE)'!V48=4,"Retired"),"") | X47: =IF(OR(V47="Self-Employed",W47="Self-Employed"),"Yes","No") | Y47: ='Loan Tape (BoE)'!W48 | Z47: ='Loan Tape (BoE)'!X48 | AA47: =IF(T47=1,Y47,MIN(Y47,Z47)) | AB47: ='Loan Tape (BoE)'!Y48 | AC47: ='Loan Tape (BoE)'!Z48 | AD47: =AB47+AC47 | AE47: ='Loan Tape (BoE)'!AA48 | AF47: ='Loan Tape (BoE)'!AB48 | AG47: =AE47+AF47 | AH47: =MAX('Loan Tape (BoE)'!AC48,'Loan Tape (BoE)'!AD48) | AI47: ='Loan Tape (BoE)'!AE48 | AJ47: =B47*H47/12 | AK47: =IF(AJ47>0,AI47/AJ47,0) | AL47: =IF('Loan Tape (BoE)'!AF48=1,"Yes","No") | AM47: =IF('Loan Tape (BoE)'!AH48=1,"Yes","No") | AN47: =IF('Loan Tape (BoE)'!AI48=1,"Yes","No") | AO47: =IF('Loan Tape (BoE)'!AJ48=1,"Yes","No") | AP47: =IF(OR('Loan Tape (BoE)'!AQ47=1,'Loan Tape (BoE)'!AQ47=2),"Yes",IF('Loan Tape (BoE)'!AQ47=0,"No","")) | AQ47: =IF('Loan Tape (BoE)'!BV49_47<>"",'Loan Tape (BoE)'!BV49_47,"") | AR47: =IF('Loan Tape (BoE)'!BV470_47<>"",'Loan Tape (BoE)'!BV50_47,"") | AS47: =IFERROR(INDEX('FF Adj Parameters'!$A$103:$B$1047,MATCH('Loan Tape (BoE)'!P47,INDEX('FF Adj Parameters'!$A$103:$B$1047,,1),0),2),"Unknown") | AT47: =IF(N47="Interest Only",M5*O5/12,IF(AND(O5>0,ISNUMBER(O5),ISNUMBER(M5)),ABS(PMT(O5/12,AU5,-M5)),0)) | AU47: =IF(ISNUMBER(L47),MAX(0,(L5-'Control Panel'!$B$10)*12/365.25),0) | AV47: =IF(ISNUMBER(L47),IF(L5>'Control Panel'!$B$10,"Valid","Past Maturity"),"No Date") | AW47: =IF(ISNUMBER(K47),MAX(0,('Control Panel'!$B$10-K5)*12/365.25),0)
A48: ='Loan Tape (BoE)'!A49 | B48: =IFERROR(INDEX('FF Adj Parameters'!$A$89:$B$92,MATCH('Loan Tape (BoE)'!C48,INDEX('FF Adj Parameters'!$A$89:$B$92,,1),0),2),"Unknown") | C48: ='Loan Tape (BoE)'!C49 | D48: ='Loan Tape (BoE)'!D49 | E48: ='Loan Tape (BoE)'!E49 | F48: ='Loan Tape (BoE)'!F49 | G48: ='Loan Tape (BoE)'!G49 | H48: ='Loan Tape (BoE)'!H49/100 | I48: =IFERROR(IFS('Loan Tape (BoE)'!I49=1,"House",'Loan Tape (BoE)'!I49=2,"Flat",'Loan Tape (BoE)'!I49=3,"Bungalow",'Loan Tape (BoE)'!I49=4,"Maisonette"),"") | J48: ='Loan Tape (BoE)'!J49 | K48: ='Loan Tape (BoE)'!K49 | L48: =IFERROR(IFS('Loan Tape (BoE)'!L49=1,"Owner Occupied",'Loan Tape (BoE)'!L49=2,"BTL",'Loan Tape (BoE)'!L49=3,"Second Home",'Loan Tape (BoE)'!L49=4,"Investment"),"") | M48: =IFERROR(IFS('Loan Tape (BoE)'!M49=1,"Purchase",'Loan Tape (BoE)'!M49=2,"Remortgage",OR('Loan Tape (BoE)'!M49=3,'Loan Tape (BoE)'!M49=4),"Cash-out"),"") | N48: =IFERROR(INDEX('FF Adj Parameters'!$A$96:$B$99,MATCH('Loan Tape (BoE)'!R48,INDEX('FF Adj Parameters'!$A$96:$B$99,,1),0),2),"Unknown") | O48: =IF('Loan Tape (BoE)'!O49=1,"Yes","No") | P48: =IF('Loan Tape (BoE)'!P48=1,"Yes",IF('Loan Tape (BoE)'!P48=0,"No","")) | Q48: =IF('Loan Tape (BoE)'!Q48=1,"Yes",IF('Loan Tape (BoE)'!Q48=0,"No","")) | R48: =IF('Loan Tape (BoE)'!R48=1,"Yes",IF('Loan Tape (BoE)'!R48=0,"No","")) | S48: =IF('Loan Tape (BoE)'!S48=1,"Yes",IF('Loan Tape (BoE)'!S48=0,"No","")) | T48: =IF('Loan Tape (BoE)'!T48=1,"Yes",IF('Loan Tape (BoE)'!T48=0,"No","")) | U48: =R48+S48 | V48: =IFERROR(IFS('Loan Tape (BoE)'!U49=1,"Employed",'Loan Tape (BoE)'!U49=2,"Self-Employed",'Loan Tape (BoE)'!U49=3,"Unemployed",'Loan Tape (BoE)'!U49=4,"Retired"),"") | W48: =IFERROR(IFS('Loan Tape (BoE)'!V49=1,"Employed",'Loan Tape (BoE)'!V49=2,"Self-Employed",'Loan Tape (BoE)'!V49=3,"Unemployed",'Loan Tape (BoE)'!V49=4,"Retired"),"") | X48: =IF(OR(V48="Self-Employed",W48="Self-Employed"),"Yes","No") | Y48: ='Loan Tape (BoE)'!W49 | Z48: ='Loan Tape (BoE)'!X49 | AA48: =IF(T48=1,Y48,MIN(Y48,Z48)) | AB48: ='Loan Tape (BoE)'!Y49 | AC48: ='Loan Tape (BoE)'!Z49 | AD48: =AB48+AC48 | AE48: ='Loan Tape (BoE)'!AA49 | AF48: ='Loan Tape (BoE)'!AB49 | AG48: =AE48+AF48 | AH48: =MAX('Loan Tape (BoE)'!AC49,'Loan Tape (BoE)'!AD49) | AI48: ='Loan Tape (BoE)'!AE49 | AJ48: =B48*H48/12 | AK48: =IF(AJ48>0,AI48/AJ48,0) | AL48: =IF('Loan Tape (BoE)'!AF49=1,"Yes","No") | AM48: =IF('Loan Tape (BoE)'!AH49=1,"Yes","No") | AN48: =IF('Loan Tape (BoE)'!AI49=1,"Yes","No") | AO48: =IF('Loan Tape (BoE)'!AJ49=1,"Yes","No") | AP48: =IF(OR('Loan Tape (BoE)'!AQ48=1,'Loan Tape (BoE)'!AQ48=2),"Yes",IF('Loan Tape (BoE)'!AQ48=0,"No","")) | AQ48: =IF('Loan Tape (BoE)'!BV49_48<>"",'Loan Tape (BoE)'!BV49_48,"") | AR48: =IF('Loan Tape (BoE)'!BV480_48<>"",'Loan Tape (BoE)'!BV50_48,"") | AS48: =IFERROR(INDEX('FF Adj Parameters'!$A$103:$B$1048,MATCH('Loan Tape (BoE)'!P48,INDEX('FF Adj Parameters'!$A$103:$B$1048,,1),0),2),"Unknown") | AT48: =IF(N48="Interest Only",M5*O5/12,IF(AND(O5>0,ISNUMBER(O5),ISNUMBER(M5)),ABS(PMT(O5/12,AU5,-M5)),0)) | AU48: =IF(ISNUMBER(L48),MAX(0,(L5-'Control Panel'!$B$10)*12/365.25),0) | AV48: =IF(ISNUMBER(L48),IF(L5>'Control Panel'!$B$10,"Valid","Past Maturity"),"No Date") | AW48: =IF(ISNUMBER(K48),MAX(0,('Control Panel'!$B$10-K5)*12/365.25),0)
A49: ='Loan Tape (BoE)'!A50 | B49: =IFERROR(INDEX('FF Adj Parameters'!$A$89:$B$92,MATCH('Loan Tape (BoE)'!C49,INDEX('FF Adj Parameters'!$A$89:$B$92,,1),0),2),"Unknown") | C49: ='Loan Tape (BoE)'!C50 | D49: ='Loan Tape (BoE)'!D50 | E49: ='Loan Tape (BoE)'!E50 | F49: ='Loan Tape (BoE)'!F50 | G49: ='Loan Tape (BoE)'!G50 | H49: ='Loan Tape (BoE)'!H50/100 | I49: =IFERROR(IFS('Loan Tape (BoE)'!I50=1,"House",'Loan Tape (BoE)'!I50=2,"Flat",'Loan Tape (BoE)'!I50=3,"Bungalow",'Loan Tape (BoE)'!I50=4,"Maisonette"),"") | J49: ='Loan Tape (BoE)'!J50 | K49: ='Loan Tape (BoE)'!K50 | L49: =IFERROR(IFS('Loan Tape (BoE)'!L50=1,"Owner Occupied",'Loan Tape (BoE)'!L50=2,"BTL",'Loan Tape (BoE)'!L50=3,"Second Home",'Loan Tape (BoE)'!L50=4,"Investment"),"") | M49: =IFERROR(IFS('Loan Tape (BoE)'!M50=1,"Purchase",'Loan Tape (BoE)'!M50=2,"Remortgage",OR('Loan Tape (BoE)'!M50=3,'Loan Tape (BoE)'!M50=4),"Cash-out"),"") | N49: =IFERROR(INDEX('FF Adj Parameters'!$A$96:$B$99,MATCH('Loan Tape (BoE)'!R49,INDEX('FF Adj Parameters'!$A$96:$B$99,,1),0),2),"Unknown") | O49: =IF('Loan Tape (BoE)'!O50=1,"Yes","No") | P49: =IF('Loan Tape (BoE)'!P49=1,"Yes",IF('Loan Tape (BoE)'!P49=0,"No","")) | Q49: =IF('Loan Tape (BoE)'!Q49=1,"Yes",IF('Loan Tape (BoE)'!Q49=0,"No","")) | R49: =IF('Loan Tape (BoE)'!R49=1,"Yes",IF('Loan Tape (BoE)'!R49=0,"No","")) | S49: =IF('Loan Tape (BoE)'!S49=1,"Yes",IF('Loan Tape (BoE)'!S49=0,"No","")) | T49: =IF('Loan Tape (BoE)'!T49=1,"Yes",IF('Loan Tape (BoE)'!T49=0,"No","")) | U49: =R49+S49 | V49: =IFERROR(IFS('Loan Tape (BoE)'!U50=1,"Employed",'Loan Tape (BoE)'!U50=2,"Self-Employed",'Loan Tape (BoE)'!U50=3,"Unemployed",'Loan Tape (BoE)'!U50=4,"Retired"),"") | W49: =IFERROR(IFS('Loan Tape (BoE)'!V50=1,"Employed",'Loan Tape (BoE)'!V50=2,"Self-Employed",'Loan Tape (BoE)'!V50=3,"Unemployed",'Loan Tape (BoE)'!V50=4,"Retired"),"") | X49: =IF(OR(V49="Self-Employed",W49="Self-Employed"),"Yes","No") | Y49: ='Loan Tape (BoE)'!W50 | Z49: ='Loan Tape (BoE)'!X50 | AA49: =IF(T49=1,Y49,MIN(Y49,Z49)) | AB49: ='Loan Tape (BoE)'!Y50 | AC49: ='Loan Tape (BoE)'!Z50 | AD49: =AB49+AC49 | AE49: ='Loan Tape (BoE)'!AA50 | AF49: ='Loan Tape (BoE)'!AB50 | AG49: =AE49+AF49 | AH49: =MAX('Loan Tape (BoE)'!AC50,'Loan Tape (BoE)'!AD50) | AI49: ='Loan Tape (BoE)'!AE50 | AJ49: =B49*H49/12 | AK49: =IF(AJ49>0,AI49/AJ49,0) | AL49: =IF('Loan Tape (BoE)'!AF50=1,"Yes","No") | AM49: =IF('Loan Tape (BoE)'!AH50=1,"Yes","No") | AN49: =IF('Loan Tape (BoE)'!AI50=1,"Yes","No") | AO49: =IF('Loan Tape (BoE)'!AJ50=1,"Yes","No") | AP49: =IF(OR('Loan Tape (BoE)'!AQ49=1,'Loan Tape (BoE)'!AQ49=2),"Yes",IF('Loan Tape (BoE)'!AQ49=0,"No","")) | AQ49: =IF('Loan Tape (BoE)'!BV49_49<>"",'Loan Tape (BoE)'!BV49_49,"") | AR49: =IF('Loan Tape (BoE)'!BV490_49<>"",'Loan Tape (BoE)'!BV50_49,"") | AS49: =IFERROR(INDEX('FF Adj Parameters'!$A$103:$B$1049,MATCH('Loan Tape (BoE)'!P49,INDEX('FF Adj Parameters'!$A$103:$B$1049,,1),0),2),"Unknown") | AT49: =IF(N49="Interest Only",M5*O5/12,IF(AND(O5>0,ISNUMBER(O5),ISNUMBER(M5)),ABS(PMT(O5/12,AU5,-M5)),0)) | AU49: =IF(ISNUMBER(L49),MAX(0,(L5-'Control Panel'!$B$10)*12/365.25),0) | AV49: =IF(ISNUMBER(L49),IF(L5>'Control Panel'!$B$10,"Valid","Past Maturity"),"No Date") | AW49: =IF(ISNUMBER(K49),MAX(0,('Control Panel'!$B$10-K5)*12/365.25),0)
A50: ='Loan Tape (BoE)'!A51 | B50: =IFERROR(INDEX('FF Adj Parameters'!$A$89:$B$92,MATCH('Loan Tape (BoE)'!C50,INDEX('FF Adj Parameters'!$A$89:$B$92,,1),0),2),"Unknown") | C50: ='Loan Tape (BoE)'!C51 | D50: ='Loan Tape (BoE)'!D51 | E50: ='Loan Tape (BoE)'!E51 | F50: ='Loan Tape (BoE)'!F51 | G50: ='Loan Tape (BoE)'!G51 | H50: ='Loan Tape (BoE)'!H51/100 | I50: =IFERROR(IFS('Loan Tape (BoE)'!I51=1,"House",'Loan Tape (BoE)'!I51=2,"Flat",'Loan Tape (BoE)'!I51=3,"Bungalow",'Loan Tape (BoE)'!I51=4,"Maisonette"),"") | J50: ='Loan Tape (BoE)'!J51 | K50: ='Loan Tape (BoE)'!K51 | L50: =IFERROR(IFS('Loan Tape (BoE)'!L51=1,"Owner Occupied",'Loan Tape (BoE)'!L51=2,"BTL",'Loan Tape (BoE)'!L51=3,"Second Home",'Loan Tape (BoE)'!L51=4,"Investment"),"") | M50: =IFERROR(IFS('Loan Tape (BoE)'!M51=1,"Purchase",'Loan Tape (BoE)'!M51=2,"Remortgage",OR('Loan Tape (BoE)'!M51=3,'Loan Tape (BoE)'!M51=4),"Cash-out"),"") | N50: =IFERROR(INDEX('FF Adj Parameters'!$A$96:$B$99,MATCH('Loan Tape (BoE)'!R50,INDEX('FF Adj Parameters'!$A$96:$B$99,,1),0),2),"Unknown") | O50: =IF('Loan Tape (BoE)'!O51=1,"Yes","No") | P50: =IF('Loan Tape (BoE)'!P50=1,"Yes",IF('Loan Tape (BoE)'!P50=0,"No","")) | Q50: =IF('Loan Tape (BoE)'!Q50=1,"Yes",IF('Loan Tape (BoE)'!Q50=0,"No","")) | R50: =IF('Loan Tape (BoE)'!R50=1,"Yes",IF('Loan Tape (BoE)'!R50=0,"No","")) | S50: =IF('Loan Tape (BoE)'!S50=1,"Yes",IF('Loan Tape (BoE)'!S50=0,"No","")) | T50: =IF('Loan Tape (BoE)'!T50=1,"Yes",IF('Loan Tape (BoE)'!T50=0,"No","")) | U50: =R50+S50 | V50: =IFERROR(IFS('Loan Tape (BoE)'!U51=1,"Employed",'Loan Tape (BoE)'!U51=2,"Self-Employed",'Loan Tape (BoE)'!U51=3,"Unemployed",'Loan Tape (BoE)'!U51=4,"Retired"),"") | W50: =IFERROR(IFS('Loan Tape (BoE)'!V51=1,"Employed",'Loan Tape (BoE)'!V51=2,"Self-Employed",'Loan Tape (BoE)'!V51=3,"Unemployed",'Loan Tape (BoE)'!V51=4,"Retired"),"") | X50: =IF(OR(V50="Self-Employed",W50="Self-Employed"),"Yes","No") | Y50: ='Loan Tape (BoE)'!W51 | Z50: ='Loan Tape (BoE)'!X51 | AA50: =IF(T50=1,Y50,MIN(Y50,Z50)) | AB50: ='Loan Tape (BoE)'!Y51 | AC50: ='Loan Tape (BoE)'!Z51 | AD50: =AB50+AC50 | AE50: ='Loan Tape (BoE)'!AA51 | AF50: ='Loan Tape (BoE)'!AB51 | AG50: =AE50+AF50 | AH50: =MAX('Loan Tape (BoE)'!AC51,'Loan Tape (BoE)'!AD51) | AI50: ='Loan Tape (BoE)'!AE51 | AJ50: =B50*H50/12 | AK50: =IF(AJ50>0,AI50/AJ50,0) | AL50: =IF('Loan Tape (BoE)'!AF51=1,"Yes","No") | AM50: =IF('Loan Tape (BoE)'!AH51=1,"Yes","No") | AN50: =IF('Loan Tape (BoE)'!AI51=1,"Yes","No") | AO50: =IF('Loan Tape (BoE)'!AJ51=1,"Yes","No") | AP50: =IF(OR('Loan Tape (BoE)'!AQ50=1,'Loan Tape (BoE)'!AQ50=2),"Yes",IF('Loan Tape (BoE)'!AQ50=0,"No","")) | AQ50: =IF('Loan Tape (BoE)'!BV49_500<>"",'Loan Tape (BoE)'!BV49_50,"") | AR50: =IF('Loan Tape (BoE)'!BV500_50<>"",'Loan Tape (BoE)'!BV50_50,"") | AS50: =IFERROR(INDEX('FF Adj Parameters'!$A$103:$B$1050,MATCH('Loan Tape (BoE)'!P50,INDEX('FF Adj Parameters'!$A$103:$B$1050,,1),0),2),"Unknown") | AT50: =IF(N50="Interest Only",M5*O5/12,IF(AND(O5>0,ISNUMBER(O5),ISNUMBER(M5)),ABS(PMT(O5/12,AU5,-M5)),0)) | AU50: =IF(ISNUMBER(L50),MAX(0,(L5-'Control Panel'!$B$10)*12/365.25),0) | AV50: =IF(ISNUMBER(L50),IF(L5>'Control Panel'!$B$10,"Valid","Past Maturity"),"No Date") | AW50: =IF(ISNUMBER(K50),MAX(0,('Control Panel'!$B$10-K5)*12/365.25),0)
A51: ='Loan Tape (BoE)'!A52 | B51: =IFERROR(INDEX('FF Adj Parameters'!$A$89:$B$92,MATCH('Loan Tape (BoE)'!C51,INDEX('FF Adj Parameters'!$A$89:$B$92,,1),0),2),"Unknown") | C51: ='Loan Tape (BoE)'!C52 | D51: ='Loan Tape (BoE)'!D52 | E51: ='Loan Tape (BoE)'!E52 | F51: ='Loan Tape (BoE)'!F52 | G51: ='Loan Tape (BoE)'!G52 | H51: ='Loan Tape (BoE)'!H52/100 | I51: =IFERROR(IFS('Loan Tape (BoE)'!I52=1,"House",'Loan Tape (BoE)'!I52=2,"Flat",'Loan Tape (BoE)'!I52=3,"Bungalow",'Loan Tape (BoE)'!I52=4,"Maisonette"),"") | J51: ='Loan Tape (BoE)'!J52 | K51: ='Loan Tape (BoE)'!K52 | L51: =IFERROR(IFS('Loan Tape (BoE)'!L52=1,"Owner Occupied",'Loan Tape (BoE)'!L52=2,"BTL",'Loan Tape (BoE)'!L52=3,"Second Home",'Loan Tape (BoE)'!L52=4,"Investment"),"") | M51: =IFERROR(IFS('Loan Tape (BoE)'!M52=1,"Purchase",'Loan Tape (BoE)'!M52=2,"Remortgage",OR('Loan Tape (BoE)'!M52=3,'Loan Tape (BoE)'!M52=4),"Cash-out"),"") | N51: =IFERROR(INDEX('FF Adj Parameters'!$A$96:$B$99,MATCH('Loan Tape (BoE)'!R51,INDEX('FF Adj Parameters'!$A$96:$B$99,,1),0),2),"Unknown") | O51: =IF('Loan Tape (BoE)'!O52=1,"Yes","No") | P51: =IF('Loan Tape (BoE)'!P51=1,"Yes",IF('Loan Tape (BoE)'!P51=0,"No","")) | Q51: =IF('Loan Tape (BoE)'!Q51=1,"Yes",IF('Loan Tape (BoE)'!Q51=0,"No","")) | R51: =IF('Loan Tape (BoE)'!R51=1,"Yes",IF('Loan Tape (BoE)'!R51=0,"No","")) | S51: =IF('Loan Tape (BoE)'!S51=1,"Yes",IF('Loan Tape (BoE)'!S51=0,"No","")) | T51: =IF('Loan Tape (BoE)'!T51=1,"Yes",IF('Loan Tape (BoE)'!T51=0,"No","")) | U51: =R51+S51 | V51: =IFERROR(IFS('Loan Tape (BoE)'!U52=1,"Employed",'Loan Tape (BoE)'!U52=2,"Self-Employed",'Loan Tape (BoE)'!U52=3,"Unemployed",'Loan Tape (BoE)'!U52=4,"Retired"),"") | W51: =IFERROR(IFS('Loan Tape (BoE)'!V52=1,"Employed",'Loan Tape (BoE)'!V52=2,"Self-Employed",'Loan Tape (BoE)'!V52=3,"Unemployed",'Loan Tape (BoE)'!V52=4,"Retired"),"") | X51: =IF(OR(V51="Self-Employed",W51="Self-Employed"),"Yes","No") | Y51: ='Loan Tape (BoE)'!W52 | Z51: ='Loan Tape (BoE)'!X52 | AA51: =IF(T51=1,Y51,MIN(Y51,Z51)) | AB51: ='Loan Tape (BoE)'!Y52 | AC51: ='Loan Tape (BoE)'!Z52 | AD51: =AB51+AC51 | AE51: ='Loan Tape (BoE)'!AA52 | AF51: ='Loan Tape (BoE)'!AB52 | AG51: =AE51+AF51 | AH51: =MAX('Loan Tape (BoE)'!AC52,'Loan Tape (BoE)'!AD52) | AI51: ='Loan Tape (BoE)'!AE52 | AJ51: =B51*H51/12 | AK51: =IF(AJ51>0,AI51/AJ51,0) | AL51: =IF('Loan Tape (BoE)'!AF52=1,"Yes","No") | AM51: =IF('Loan Tape (BoE)'!AH52=1,"Yes","No") | AN51: =IF('Loan Tape (BoE)'!AI52=1,"Yes","No") | AO51: =IF('Loan Tape (BoE)'!AJ52=1,"Yes","No") | AP51: =IF(OR('Loan Tape (BoE)'!AQ51=1,'Loan Tape (BoE)'!AQ51=2),"Yes",IF('Loan Tape (BoE)'!AQ51=0,"No","")) | AQ51: =IF('Loan Tape (BoE)'!BV49_511<>"",'Loan Tape (BoE)'!BV49_51,"") | AR51: =IF('Loan Tape (BoE)'!BV510_51<>"",'Loan Tape (BoE)'!BV50_51,"") | AS51: =IFERROR(INDEX('FF Adj Parameters'!$A$103:$B$1051,MATCH('Loan Tape (BoE)'!P51,INDEX('FF Adj Parameters'!$A$103:$B$1051,,1),0),2),"Unknown") | AT51: =IF(N51="Interest Only",M5*O5/12,IF(AND(O5>0,ISNUMBER(O5),ISNUMBER(M5)),ABS(PMT(O5/12,AU5,-M5)),0)) | AU51: =IF(ISNUMBER(L51),MAX(0,(L5-'Control Panel'!$B$10)*12/365.25),0) | AV51: =IF(ISNUMBER(L51),IF(L5>'Control Panel'!$B$10,"Valid","Past Maturity"),"No Date") | AW51: =IF(ISNUMBER(K51),MAX(0,('Control Panel'!$B$10-K5)*12/365.25),0)
A52: ='Loan Tape (BoE)'!A53 | B52: =IFERROR(INDEX('FF Adj Parameters'!$A$89:$B$92,MATCH('Loan Tape (BoE)'!C52,INDEX('FF Adj Parameters'!$A$89:$B$92,,1),0),2),"Unknown") | C52: ='Loan Tape (BoE)'!C53 | D52: ='Loan Tape (BoE)'!D53 | E52: ='Loan Tape (BoE)'!E53 | F52: ='Loan Tape (BoE)'!F53 | G52: ='Loan Tape (BoE)'!G53 | H52: ='Loan Tape (BoE)'!H53/100 | I52: =IFERROR(IFS('Loan Tape (BoE)'!I53=1,"House",'Loan Tape (BoE)'!I53=2,"Flat",'Loan Tape (BoE)'!I53=3,"Bungalow",'Loan Tape (BoE)'!I53=4,"Maisonette"),"") | J52: ='Loan Tape (BoE)'!J53 | K52: ='Loan Tape (BoE)'!K53 | L52: =IFERROR(IFS('Loan Tape (BoE)'!L53=1,"Owner Occupied",'Loan Tape (BoE)'!L53=2,"BTL",'Loan Tape (BoE)'!L53=3,"Second Home",'Loan Tape (BoE)'!L53=4,"Investment"),"") | M52: =IFERROR(IFS('Loan Tape (BoE)'!M53=1,"Purchase",'Loan Tape (BoE)'!M53=2,"Remortgage",OR('Loan Tape (BoE)'!M53=3,'Loan Tape (BoE)'!M53=4),"Cash-out"),"") | N52: =IFERROR(INDEX('FF Adj Parameters'!$A$96:$B$99,MATCH('Loan Tape (BoE)'!R52,INDEX('FF Adj Parameters'!$A$96:$B$99,,1),0),2),"Unknown") | O52: =IF('Loan Tape (BoE)'!O53=1,"Yes","No") | P52: =IF('Loan Tape (BoE)'!P52=1,"Yes",IF('Loan Tape (BoE)'!P52=0,"No","")) | Q52: =IF('Loan Tape (BoE)'!Q52=1,"Yes",IF('Loan Tape (BoE)'!Q52=0,"No","")) | R52: =IF('Loan Tape (BoE)'!R52=1,"Yes",IF('Loan Tape (BoE)'!R52=0,"No","")) | S52: =IF('Loan Tape (BoE)'!S52=1,"Yes",IF('Loan Tape (BoE)'!S52=0,"No","")) | T52: =IF('Loan Tape (BoE)'!T52=1,"Yes",IF('Loan Tape (BoE)'!T52=0,"No","")) | U52: =R52+S52 | V52: =IFERROR(IFS('Loan Tape (BoE)'!U53=1,"Employed",'Loan Tape (BoE)'!U53=2,"Self-Employed",'Loan Tape (BoE)'!U53=3,"Unemployed",'Loan Tape (BoE)'!U53=4,"Retired"),"") | W52: =IFERROR(IFS('Loan Tape (BoE)'!V53=1,"Employed",'Loan Tape (BoE)'!V53=2,"Self-Employed",'Loan Tape (BoE)'!V53=3,"Unemployed",'Loan Tape (BoE)'!V53=4,"Retired"),"") | X52: =IF(OR(V52="Self-Employed",W52="Self-Employed"),"Yes","No") | Y52: ='Loan Tape (BoE)'!W53 | Z52: ='Loan Tape (BoE)'!X53 | AA52: =IF(T52=1,Y52,MIN(Y52,Z52)) | AB52: ='Loan Tape (BoE)'!Y53 | AC52: ='Loan Tape (BoE)'!Z53 | AD52: =AB52+AC52 | AE52: ='Loan Tape (BoE)'!AA53 | AF52: ='Loan Tape (BoE)'!AB53 | AG52: =AE52+AF52 | AH52: =MAX('Loan Tape (BoE)'!AC53,'Loan Tape (BoE)'!AD53) | AI52: ='Loan Tape (BoE)'!AE53 | AJ52: =B52*H52/12 | AK52: =IF(AJ52>0,AI52/AJ52,0) | AL52: =IF('Loan Tape (BoE)'!AF53=1,"Yes","No") | AM52: =IF('Loan Tape (BoE)'!AH53=1,"Yes","No") | AN52: =IF('Loan Tape (BoE)'!AI53=1,"Yes","No") | AO52: =IF('Loan Tape (BoE)'!AJ53=1,"Yes","No") | AP52: =IF(OR('Loan Tape (BoE)'!AQ52=1,'Loan Tape (BoE)'!AQ52=2),"Yes",IF('Loan Tape (BoE)'!AQ52=0,"No","")) | AQ52: =IF('Loan Tape (BoE)'!BV49_522<>"",'Loan Tape (BoE)'!BV49_52,"") | AR52: =IF('Loan Tape (BoE)'!BV520_52<>"",'Loan Tape (BoE)'!BV50_52,"") | AS52: =IFERROR(INDEX('FF Adj Parameters'!$A$103:$B$1052,MATCH('Loan Tape (BoE)'!P52,INDEX('FF Adj Parameters'!$A$103:$B$1052,,1),0),2),"Unknown") | AT52: =IF(N52="Interest Only",M5*O5/12,IF(AND(O5>0,ISNUMBER(O5),ISNUMBER(M5)),ABS(PMT(O5/12,AU5,-M5)),0)) | AU52: =IF(ISNUMBER(L52),MAX(0,(L5-'Control Panel'!$B$10)*12/365.25),0) | AV52: =IF(ISNUMBER(L52),IF(L5>'Control Panel'!$B$10,"Valid","Past Maturity"),"No Date") | AW52: =IF(ISNUMBER(K52),MAX(0,('Control Panel'!$B$10-K5)*12/365.25),0)
A53: ='Loan Tape (BoE)'!A54 | B53: =IFERROR(INDEX('FF Adj Parameters'!$A$89:$B$92,MATCH('Loan Tape (BoE)'!C53,INDEX('FF Adj Parameters'!$A$89:$B$92,,1),0),2),"Unknown") | C53: ='Loan Tape (BoE)'!C54 | D53: ='Loan Tape (BoE)'!D54 | E53: ='Loan Tape (BoE)'!E54 | F53: ='Loan Tape (BoE)'!F54 | G53: ='Loan Tape (BoE)'!G54 | H53: ='Loan Tape (BoE)'!H54/100 | I53: =IFERROR(IFS('Loan Tape (BoE)'!I54=1,"House",'Loan Tape (BoE)'!I54=2,"Flat",'Loan Tape (BoE)'!I54=3,"Bungalow",'Loan Tape (BoE)'!I54=4,"Maisonette"),"") | J53: ='Loan Tape (BoE)'!J54 | K53: ='Loan Tape (BoE)'!K54 | L53: =IFERROR(IFS('Loan Tape (BoE)'!L54=1,"Owner Occupied",'Loan Tape (BoE)'!L54=2,"BTL",'Loan Tape (BoE)'!L54=3,"Second Home",'Loan Tape (BoE)'!L54=4,"Investment"),"") | M53: =IFERROR(IFS('Loan Tape (BoE)'!M54=1,"Purchase",'Loan Tape (BoE)'!M54=2,"Remortgage",OR('Loan Tape (BoE)'!M54=3,'Loan Tape (BoE)'!M54=4),"Cash-out"),"") | N53: =IFERROR(INDEX('FF Adj Parameters'!$A$96:$B$99,MATCH('Loan Tape (BoE)'!R53,INDEX('FF Adj Parameters'!$A$96:$B$99,,1),0),2),"Unknown") | O53: =IF('Loan Tape (BoE)'!O54=1,"Yes","No") | P53: =IF('Loan Tape (BoE)'!P53=1,"Yes",IF('Loan Tape (BoE)'!P53=0,"No","")) | Q53: =IF('Loan Tape (BoE)'!Q53=1,"Yes",IF('Loan Tape (BoE)'!Q53=0,"No","")) | R53: =IF('Loan Tape (BoE)'!R53=1,"Yes",IF('Loan Tape (BoE)'!R53=0,"No","")) | S53: =IF('Loan Tape (BoE)'!S53=1,"Yes",IF('Loan Tape (BoE)'!S53=0,"No","")) | T53: =IF('Loan Tape (BoE)'!T53=1,"Yes",IF('Loan Tape (BoE)'!T53=0,"No","")) | U53: =R53+S53 | V53: =IFERROR(IFS('Loan Tape (BoE)'!U54=1,"Employed",'Loan Tape (BoE)'!U54=2,"Self-Employed",'Loan Tape (BoE)'!U54=3,"Unemployed",'Loan Tape (BoE)'!U54=4,"Retired"),"") | W53: =IFERROR(IFS('Loan Tape (BoE)'!V54=1,"Employed",'Loan Tape (BoE)'!V54=2,"Self-Employed",'Loan Tape (BoE)'!V54=3,"Unemployed",'Loan Tape (BoE)'!V54=4,"Retired"),"") | X53: =IF(OR(V53="Self-Employed",W53="Self-Employed"),"Yes","No") | Y53: ='Loan Tape (BoE)'!W54 | Z53: ='Loan Tape (BoE)'!X54 | AA53: =IF(T53=1,Y53,MIN(Y53,Z53)) | AB53: ='Loan Tape (BoE)'!Y54 | AC53: ='Loan Tape (BoE)'!Z54 | AD53: =AB53+AC53 | AE53: ='Loan Tape (BoE)'!AA54 | AF53: ='Loan Tape (BoE)'!AB54 | AG53: =AE53+AF53 | AH53: =MAX('Loan Tape (BoE)'!AC54,'Loan Tape (BoE)'!AD54) | AI53: ='Loan Tape (BoE)'!AE54 | AJ53: =B53*H53/12 | AK53: =IF(AJ53>0,AI53/AJ53,0) | AL53: =IF('Loan Tape (BoE)'!AF54=1,"Yes","No") | AM53: =IF('Loan Tape (BoE)'!AH54=1,"Yes","No") | AN53: =IF('Loan Tape (BoE)'!AI54=1,"Yes","No") | AO53: =IF('Loan Tape (BoE)'!AJ54=1,"Yes","No") | AP53: =IF(OR('Loan Tape (BoE)'!AQ53=1,'Loan Tape (BoE)'!AQ53=2),"Yes",IF('Loan Tape (BoE)'!AQ53=0,"No","")) | AQ53: =IF('Loan Tape (BoE)'!BV49_533<>"",'Loan Tape (BoE)'!BV49_53,"") | AR53: =IF('Loan Tape (BoE)'!BV530_53<>"",'Loan Tape (BoE)'!BV50_53,"") | AS53: =IFERROR(INDEX('FF Adj Parameters'!$A$103:$B$1053,MATCH('Loan Tape (BoE)'!P53,INDEX('FF Adj Parameters'!$A$103:$B$1053,,1),0),2),"Unknown") | AT53: =IF(N53="Interest Only",M5*O5/12,IF(AND(O5>0,ISNUMBER(O5),ISNUMBER(M5)),ABS(PMT(O5/12,AU5,-M5)),0)) | AU53: =IF(ISNUMBER(L53),MAX(0,(L5-'Control Panel'!$B$10)*12/365.25),0) | AV53: =IF(ISNUMBER(L53),IF(L5>'Control Panel'!$B$10,"Valid","Past Maturity"),"No Date") | AW53: =IF(ISNUMBER(K53),MAX(0,('Control Panel'!$B$10-K5)*12/365.25),0)
